Workbook

Sheet Hallazgos
A1: Maestro de hallazgos · Plan to Release (P2R) · nivel alto
A2: Genérico para cualquier empresa. El paso concreto y la cuantificación se ponen al usarlo en cada celda. El detalle, para bajar a intervenciones, está en «Detalle hallazgos».
A4: ID | B4: Proceso | C4: Orden | D4: Fase | E4: Hallazgo | F4: Descripción | G4: Familia | H4: Naturaleza | I4: Métrica (volumen expuesto) | J4: Palancas | K4: Nº palancas | L4: Nº detalle | M4: Notas
A5: H01 | B5: P2R | C5: 1 | D5: Demanda y previsión | E5: Demanda sin previsión fiable | F5: No hay previsión, o la que hay no se cierra, no se consensúa ni se mide: el plan trabaja con una demanda que cambia o que no se conoce, y la demanda perdida no se registra. | G5: Ineficiencia (coste) | H5: Circulante × CMPC | I5: € de demanda mensual planificada sin previsión cerrada y consensuada | J5: PL01 | K5: =COUNTIF(Relación!$C$5:$C$16,A5) -> 1 | L5: =COUNTIF('Detalle hallazgos'!$G$5:$G$39,A5) -> 7 | M5: Agrupa «Previsión inestable», «Previsión sin medición ni aprendizaje» y «Sin previsión de demanda»: cada celda describe su caso.
A6: H03 | B6: P2R | C6: 2 | D6: S&OP y Plan Maestro | E6: Demanda y capacidad sin equilibrar | F6: Sin S&OP, la capacidad (turnos, reservas, intercompany) se decide por intuición y a mano, y el desequilibrio se arregla con urgencias. | G6: Ineficiencia (coste) | H6: Transformación (horas de línea, mermas) | I6: Horas de línea y turnos no ajustados a la carga / mes | J6: PL02 | K6: =COUNTIF(Relación!$C$5:$C$16,A6) -> 1 | L6: =COUNTIF('Detalle hallazgos'!$G$5:$G$39,A6) -> 4 | M6: Si pesan más las horas extra que las horas de línea, usa Fuga de P&L.
A7: H04 | B7: P2R | C7: 2 | D7: S&OP y Plan Maestro | E7: Stock sin política | F7: Sin segmentación ni estrategia por material, sobra stock de unos y falta de otros, en producto terminado y en materias primas. | G7: Ineficiencia (coste) | H7: Circulante × CMPC | I7: € de stock fuera de política (exceso y obsoleto) | J7: PL03 | K7: =COUNTIF(Relación!$C$5:$C$16,A7) -> 1 | L7: =COUNTIF('Detalle hallazgos'!$G$5:$G$39,A7) -> 3 | M7: La política la decide Planificación; el dato se guarda en R2M.
A8: H05 | B8: P2R | C8: 2 | D8: S&OP y Plan Maestro | E8: Fecha al cliente no fiable | F8: La fecha se promete sin comprobar disponibilidad, no se renegocia cuando no se llega y hay roturas en lo que debería estar en stock. | G8: Oportunidad (ingreso expuesto) | H8: Ingreso expuesto | I8: € de pedidos / mes entregados tarde o no servidos | J8: PL04, PL03 | K8: =COUNTIF(Relación!$C$5:$C$16,A8) -> 2 | L8: =COUNTIF('Detalle hallazgos'!$G$5:$G$39,A8) -> 3 | M8: Comparte ingreso con H11: cuantifica solo uno por celda.
A9: H06 | B9: P2R | C9: 3 | D9: Necesidades y Aprovisionamiento | E9: Faltas tardías y gestionadas a mano | F9: El MRP corre con poca frecuencia, las faltas se revisan todas a mano y acaban en compras y transportes urgentes. | G9: Ineficiencia (coste) | H9: Fuga de P&L | I9: € de sobrecoste urgente por faltas / mes | J9: PL05 | K9: =COUNTIF(Relación!$C$5:$C$16,A9) -> 1 | L9: =COUNTIF('Detalle hallazgos'!$G$5:$G$39,A9) -> 3
A10: H07 | B10: P2R | C10: 3 | D10: Necesidades y Aprovisionamiento | E10: Necesidades poco fiables | F10: Parámetros desactualizados, producto terminado y semielaborado sin sincronizar y agrupación de lotes a mano. | G10: Ineficiencia (coste) | H10: Circulante × CMPC | I10: € de stock de semielaborado y materia prima por encima de la necesidad | J10: PL05 | K10: =COUNTIF(Relación!$C$5:$C$16,A10) -> 1 | L10: =COUNTIF('Detalle hallazgos'!$G$5:$G$39,A10) -> 3
A11: H08 | B11: P2R | C11: 4 | D11: Programación | E11: Secuencia sin optimizar | F11: Se secuencia a mano, sin capacidad finita y con la ruta por defecto. | G11: Ineficiencia (coste) | H11: Transformación (horas de línea, mermas) | I11: Horas de cambio y de sobrecarga / semana | J11: PL06 | K11: =COUNTIF(Relación!$C$5:$C$16,A11) -> 1 | L11: =COUNTIF('Detalle hallazgos'!$G$5:$G$39,A11) -> 3
A12: H09 | B12: P2R | C12: 4 | D12: Programación | E12: Programa inestable | F12: Sin zona congelada ni reglas de prioridad, las urgencias obligan a resecuenciar. | G12: Ineficiencia (coste) | H12: Transformación (horas de línea, mermas) | I12: Resecuenciaciones / semana | J12: PL06 | K12: =COUNTIF(Relación!$C$5:$C$16,A12) -> 1 | L12: =COUNTIF('Detalle hallazgos'!$G$5:$G$39,A12) -> 2
A13: H10 | B13: P2R | C13: 5 | D13: Liberación | E13: Liberación sin control | F13: Se libera sin confirmar material, utillaje y aprovisionamiento a línea, y sin ventana de liberación. | G13: Ineficiencia (coste) | H13: Transformación (horas de línea, mermas) | I13: Arranques fallidos / mes | J13: PL07 | K13: =COUNTIF(Relación!$C$5:$C$16,A13) -> 1 | L13: =COUNTIF('Detalle hallazgos'!$G$5:$G$39,A13) -> 3
A14: H11 | B14: P2R | C14: 6 | D14: Seguimiento y Control | E14: Servicio sin control | F14: No hay KPIs formales de servicio ni de adherencia al programa, y los atrasos se ven cuando ya han ocurrido. | G14: Oportunidad (ingreso expuesto) | H14: Ingreso expuesto | I14: € de pedidos atrasados sin aviso / mes | J14: PL08 | K14: =COUNTIF(Relación!$C$5:$C$16,A14) -> 1 | L14: =COUNTIF('Detalle hallazgos'!$G$5:$G$39,A14) -> 2 | M14: Comparte ingreso con H05: cuantifica solo uno por celda.
A15: H12 | B15: P2R | C15: 6 | D15: Seguimiento y Control | E15: Ciclo sin aprendizaje | F15: Las desviaciones no tienen análisis de causa ni vuelven a la previsión ni a los parámetros, y el seguimiento se hace a mano. | G15: Ineficiencia (coste) | H15: Transformación (horas de línea, mermas) | I15: Desviaciones repetidas sin causa / mes | J15: PL08 | K15: =COUNTIF(Relación!$C$5:$C$16,A15) -> 1 | L15: =COUNTIF('Detalle hallazgos'!$G$5:$G$39,A15) -> 2

Sheet Palancas
A1: Maestro de palancas · Plan to Release (P2R) · nivel alto
A2: La palanca dice qué cambia. Cómo se hace (acciones, automatizaciones y agentes) se trabajará en las intervenciones, a partir de «Detalle palancas».
A4: ID | B4: Proceso | C4: Palanca | D4: Qué cambia | E4: Hallazgos que resuelve | F4: Nº hallazgos | G4: KPI | H4: Detalle (para intervenciones) | I4: Nº detalle
A5: PL01 | B5: P2R | C5: Gestión de la demanda | D5: Hay previsión, al menos de la demanda repetitiva; se cierra en fecha, se consensúa cada mes entre Comercial y Planificación, cubre el horizonte de las decisiones y se mide y corrige. | E5: H01 | F5: =COUNTIF(Relación!$A$5:$A$16,A5) -> 1 | G5: Precisión y sesgo por familia · cambios tras el cierre | H5: D-PL01, D-PL02, D-PL03, D-PL04, D-PL05 | I5: =COUNTIF('Detalle palancas'!$I$5:$I$28,A5) -> 5
A6: PL02 | B6: P2R | C6: S&OP y plan de capacidad | D6: Demanda y capacidad se equilibran cada mes, con datos y con dirección: turnos, reservas de capacidad e intercompany se deciden con escenarios, no con urgencias. | E6: H03 | F6: =COUNTIF(Relación!$A$5:$A$16,A6) -> 1 | G6: Ocupación real frente a planificada · horas extra no planificadas | H6: D-PL06, D-PL07, D-PL12, D-PL13 | I6: =COUNTIF('Detalle palancas'!$I$5:$I$28,A6) -> 4
A7: PL03 | B7: P2R | C7: Política de inventario por segmento | D7: Cada material, de producto terminado y de materia prima, tiene segmento, estrategia y stock objetivo, revisados periódicamente. | E7: H04, H05 | F7: =COUNTIF(Relación!$A$5:$A$16,A7) -> 2 | G7: € de stock fuera de política · roturas | H7: D-PL09 | I7: =COUNTIF('Detalle palancas'!$I$5:$I$28,A7) -> 1
A8: PL04 | B8: P2R | C8: Promesa de fecha fiable | D8: La fecha al cliente se confirma con disponibilidad real y se renegocia en cuanto se sabe que no se llega. | E8: H05 | F8: =COUNTIF(Relación!$A$5:$A$16,A8) -> 1 | G8: OTIF a fecha confirmada | H8: D-PL10, D-PL11, D-PL25 | I8: =COUNTIF('Detalle palancas'!$I$5:$I$28,A8) -> 3
A9: PL05 | B9: P2R | C9: Planificación de materiales por excepción | D9: Las necesidades se calculan a tiempo, con parámetros vigentes y en todos los niveles, y el planificador solo atiende las excepciones críticas. | E9: H06, H07 | F9: =COUNTIF(Relación!$A$5:$A$16,A9) -> 2 | G9: € urgentes por faltas · faltas detectadas a tiempo | H9: D-PL14, D-PL15, D-PL16, D-PL17, D-PL18 | I9: =COUNTIF('Detalle palancas'!$I$5:$I$28,A9) -> 5
A10: PL06 | B10: P2R | C10: Programación estable y optimizada | D10: El programa respeta la capacidad, minimiza los cambios y solo se modifica dentro de reglas: zona congelada y prioridades. | E10: H08, H09 | F10: =COUNTIF(Relación!$A$5:$A$16,A10) -> 2 | G10: Horas de cambio · adherencia al programa | H10: D-PL08, D-PL19, D-PL20 | I10: =COUNTIF('Detalle palancas'!$I$5:$I$28,A10) -> 3
A11: PL07 | B11: P2R | C11: Liberación controlada | D11: Una orden solo se libera con material, utillaje y aprovisionamiento a línea confirmados, y dentro de su ventana. | E11: H10 | F11: =COUNTIF(Relación!$A$5:$A$16,A11) -> 1 | G11: Arranques fallidos | H11: D-PL22 | I11: =COUNTIF('Detalle palancas'!$I$5:$I$28,A11) -> 1
A12: PL08 | B12: P2R | C12: Control del servicio y mejora continua | D12: Servicio y adherencia se miden solos, los riesgos se avisan antes y cada desviación tiene causa y una acción que vuelve a la planificación. | E12: H11, H12 | F12: =COUNTIF(Relación!$A$5:$A$16,A12) -> 2 | G12: OTIF · desviaciones con causa | H12: D-PL23, D-PL24 | I12: =COUNTIF('Detalle palancas'!$I$5:$I$28,A12) -> 2

Sheet Relación
A1: Relación palanca ↔ hallazgo · nivel alto
A2: Una fila por par, lista para importar.
A4: Palanca | B4: Texto de la palanca | C4: Hallazgo | D4: Texto del hallazgo | E4: Fase del hallazgo
A5: PL01 | B5: =INDEX(Palancas!$C$5:$C$12,MATCH(A5,Palancas!$A$5:$A$12,0)) -> Gestión de la demanda | C5: H01 | D5: =INDEX(Hallazgos!$E$5:$E$15,MATCH(C5,Hallazgos!$A$5:$A$15,0)) -> Demanda sin previsión fiable | E5: =INDEX(Hallazgos!$D$5:$D$15,MATCH(C5,Hallazgos!$A$5:$A$15,0)) -> Demanda y previsión
A6: PL02 | B6: =INDEX(Palancas!$C$5:$C$12,MATCH(A6,Palancas!$A$5:$A$12,0)) -> S&OP y plan de capacidad | C6: H03 | D6: =INDEX(Hallazgos!$E$5:$E$15,MATCH(C6,Hallazgos!$A$5:$A$15,0)) -> Demanda y capacidad sin equilibrar | E6: =INDEX(Hallazgos!$D$5:$D$15,MATCH(C6,Hallazgos!$A$5:$A$15,0)) -> S&OP y Plan Maestro
A7: PL03 | B7: =INDEX(Palancas!$C$5:$C$12,MATCH(A7,Palancas!$A$5:$A$12,0)) -> Política de inventario por segmento | C7: H04 | D7: =INDEX(Hallazgos!$E$5:$E$15,MATCH(C7,Hallazgos!$A$5:$A$15,0)) -> Stock sin política | E7: =INDEX(Hallazgos!$D$5:$D$15,MATCH(C7,Hallazgos!$A$5:$A$15,0)) -> S&OP y Plan Maestro
A8: PL03 | B8: =INDEX(Palancas!$C$5:$C$12,MATCH(A8,Palancas!$A$5:$A$12,0)) -> Política de inventario por segmento | C8: H05 | D8: =INDEX(Hallazgos!$E$5:$E$15,MATCH(C8,Hallazgos!$A$5:$A$15,0)) -> Fecha al cliente no fiable | E8: =INDEX(Hallazgos!$D$5:$D$15,MATCH(C8,Hallazgos!$A$5:$A$15,0)) -> S&OP y Plan Maestro
A9: PL04 | B9: =INDEX(Palancas!$C$5:$C$12,MATCH(A9,Palancas!$A$5:$A$12,0)) -> Promesa de fecha fiable | C9: H05 | D9: =INDEX(Hallazgos!$E$5:$E$15,MATCH(C9,Hallazgos!$A$5:$A$15,0)) -> Fecha al cliente no fiable | E9: =INDEX(Hallazgos!$D$5:$D$15,MATCH(C9,Hallazgos!$A$5:$A$15,0)) -> S&OP y Plan Maestro
A10: PL05 | B10: =INDEX(Palancas!$C$5:$C$12,MATCH(A10,Palancas!$A$5:$A$12,0)) -> Planificación de materiales por excepción | C10: H06 | D10: =INDEX(Hallazgos!$E$5:$E$15,MATCH(C10,Hallazgos!$A$5:$A$15,0)) -> Faltas tardías y gestionadas a mano | E10: =INDEX(Hallazgos!$D$5:$D$15,MATCH(C10,Hallazgos!$A$5:$A$15,0)) -> Necesidades y Aprovisionamiento
A11: PL05 | B11: =INDEX(Palancas!$C$5:$C$12,MATCH(A11,Palancas!$A$5:$A$12,0)) -> Planificación de materiales por excepción | C11: H07 | D11: =INDEX(Hallazgos!$E$5:$E$15,MATCH(C11,Hallazgos!$A$5:$A$15,0)) -> Necesidades poco fiables | E11: =INDEX(Hallazgos!$D$5:$D$15,MATCH(C11,Hallazgos!$A$5:$A$15,0)) -> Necesidades y Aprovisionamiento
A12: PL06 | B12: =INDEX(Palancas!$C$5:$C$12,MATCH(A12,Palancas!$A$5:$A$12,0)) -> Programación estable y optimizada | C12: H08 | D12: =INDEX(Hallazgos!$E$5:$E$15,MATCH(C12,Hallazgos!$A$5:$A$15,0)) -> Secuencia sin optimizar | E12: =INDEX(Hallazgos!$D$5:$D$15,MATCH(C12,Hallazgos!$A$5:$A$15,0)) -> Programación
A13: PL06 | B13: =INDEX(Palancas!$C$5:$C$12,MATCH(A13,Palancas!$A$5:$A$12,0)) -> Programación estable y optimizada | C13: H09 | D13: =INDEX(Hallazgos!$E$5:$E$15,MATCH(C13,Hallazgos!$A$5:$A$15,0)) -> Programa inestable | E13: =INDEX(Hallazgos!$D$5:$D$15,MATCH(C13,Hallazgos!$A$5:$A$15,0)) -> Programación
A14: PL07 | B14: =INDEX(Palancas!$C$5:$C$12,MATCH(A14,Palancas!$A$5:$A$12,0)) -> Liberación controlada | C14: H10 | D14: =INDEX(Hallazgos!$E$5:$E$15,MATCH(C14,Hallazgos!$A$5:$A$15,0)) -> Liberación sin control | E14: =INDEX(Hallazgos!$D$5:$D$15,MATCH(C14,Hallazgos!$A$5:$A$15,0)) -> Liberación
A15: PL08 | B15: =INDEX(Palancas!$C$5:$C$12,MATCH(A15,Palancas!$A$5:$A$12,0)) -> Control del servicio y mejora continua | C15: H11 | D15: =INDEX(Hallazgos!$E$5:$E$15,MATCH(C15,Hallazgos!$A$5:$A$15,0)) -> Servicio sin control | E15: =INDEX(Hallazgos!$D$5:$D$15,MATCH(C15,Hallazgos!$A$5:$A$15,0)) -> Seguimiento y Control
A16: PL08 | B16: =INDEX(Palancas!$C$5:$C$12,MATCH(A16,Palancas!$A$5:$A$12,0)) -> Control del servicio y mejora continua | C16: H12 | D16: =INDEX(Hallazgos!$E$5:$E$15,MATCH(C16,Hallazgos!$A$5:$A$15,0)) -> Ciclo sin aprendizaje | E16: =INDEX(Hallazgos!$D$5:$D$15,MATCH(C16,Hallazgos!$A$5:$A$15,0)) -> Seguimiento y Control

Sheet Detalle hallazgos
A1: Detalle de hallazgos (para intervenciones)
A2: Versión anterior sin los que borraste. «D-» indica detalle; cada uno cuelga de un hallazgo de nivel alto.
A4: ID detalle | B4: Fase | C4: Hallazgo (detalle) | D4: Familia | E4: Naturaleza | F4: Métrica (volumen expuesto) | G4: Nivel alto | H4: Hallazgo de nivel alto | I4: Palancas de detalle | J4: Notas
A5: D-H02 | B5: Demanda y previsión | C5: La previsión no tiene día de cierre y se cambia dentro del mes en curso | D5: Ineficiencia (coste) | E5: Circulante × CMPC | F5: Cambios de previsión dentro del mes en curso / mes | G5: H01 | H5: =INDEX(Hallazgos!$E$5:$E$15,MATCH(G5,Hallazgos!$A$5:$A$15,0)) -> Demanda sin previsión fiable | I5: D-PL02
A6: D-H03 | B6: Demanda y previsión | C6: No hay consenso de demanda entre Comercial y Planificación, o hay reunión pero no decide | D6: Ineficiencia (coste) | E6: Circulante × CMPC | F6: € de previsión mensual sin consensuar | G6: H01 | H6: =INDEX(Hallazgos!$E$5:$E$15,MATCH(G6,Hallazgos!$A$5:$A$15,0)) -> Demanda sin previsión fiable | I6: D-PL03
A7: D-H05 | B7: Demanda y previsión | C7: La demanda perdida (agotados, pedidos rechazados) no se registra y el histórico sale sesgado | D7: Ineficiencia (coste) | E7: Circulante × CMPC | F7: Agotados o rechazos / mes sin registrar | G7: H01 | H7: =INDEX(Hallazgos!$E$5:$E$15,MATCH(G7,Hallazgos!$A$5:$A$15,0)) -> Demanda sin previsión fiable | I7: D-PL04 | J7: Sin este dato, la previsión estadística (D-PL01) aprende el sesgo.
A8: D-H06 | B8: Demanda y previsión | C8: No se miden precisión ni sesgo, o se miden sin umbral | D8: Ineficiencia (coste) | E8: Circulante × CMPC | F8: Familias sin KPI de precisión | G8: H01 | H8: =INDEX(Hallazgos!$E$5:$E$15,MATCH(G8,Hallazgos!$A$5:$A$15,0)) -> Demanda sin previsión fiable | I8: D-PL05
A9: D-H07 | B9: Demanda y previsión | C9: Las desviaciones de previsión no llevan análisis de causa ni acción | D9: Ineficiencia (coste) | E9: Circulante × CMPC | F9: Desviaciones fuera de umbral sin acción / mes | G9: H01 | H9: =INDEX(Hallazgos!$E$5:$E$15,MATCH(G9,Hallazgos!$A$5:$A$15,0)) -> Demanda sin previsión fiable | I9: D-PL05, D-PL24
A10: D-H08 | B10: Demanda y previsión | C10: El horizonte de previsión es más corto que el plazo de las decisiones que alimenta (turnos, compras de plazo largo, intercompany) | D10: Ineficiencia (coste) | E10: Transformación (horas de línea, mermas) | F10: € de compras o turnos decididos sin previsión | G10: H01 | H10: =INDEX(Hallazgos!$E$5:$E$15,MATCH(G10,Hallazgos!$A$5:$A$15,0)) -> Demanda sin previsión fiable | I10: D-PL01
A11: D-H45 | B11: Demanda y previsión | C11: No hay previsión: se planifica solo con la cartera, aunque haya clientes o referencias con consumo repetitivo | D11: Ineficiencia (coste) | E11: Circulante × CMPC | F11: € de demanda repetitiva / mes sin previsión | G11: H01 | H11: =INDEX(Hallazgos!$E$5:$E$15,MATCH(G11,Hallazgos!$A$5:$A$15,0)) -> Demanda sin previsión fiable | I11: D-PL01 | J11: Caso de Ondupack y de MGT.
A12: D-H09 | B12: S&OP y Plan Maestro | C12: No hay S&OP: el desequilibrio entre demanda y capacidad no se decide con dirección y se arregla abajo, con urgencias | D12: Ineficiencia (coste) | E12: Fuga de P&L | F12: Horas extra y turnos no planificados / mes | G12: H03 | H12: =INDEX(Hallazgos!$E$5:$E$15,MATCH(G12,Hallazgos!$A$5:$A$15,0)) -> Demanda y capacidad sin equilibrar | I12: D-PL06 | J12: Puede solapar con D-H10 y D-H29 (mismas horas extra): cuantificar una vez.
A13: D-H10 | B13: S&OP y Plan Maestro | C13: La capacidad no se planifica con datos: turnos y balanceo se deciden por intuición, sin cruzar carga con capacidad | D13: Ineficiencia (coste) | E13: Transformación (horas de línea, mermas) | F13: Horas de línea / mes | G13: H03 | H13: =INDEX(Hallazgos!$E$5:$E$15,MATCH(G13,Hallazgos!$A$5:$A$15,0)) -> Demanda y capacidad sin equilibrar | I13: D-PL07
A14: D-H12 | B14: S&OP y Plan Maestro | C14: No hay política de stock por segmento: ABC/XYZ, MTS/MTO y stock de seguridad sin definir o sin revisar | D14: Ineficiencia (coste) | E14: Circulante × CMPC | F14: Materiales sin estrategia vigente | G14: H04 | H14: =INDEX(Hallazgos!$E$5:$E$15,MATCH(G14,Hallazgos!$A$5:$A$15,0)) -> Stock sin política | I14: D-PL09 | J14: La política la decide Planificación (P2R); el dato se guarda en R2M.
A15: D-H13 | B15: S&OP y Plan Maestro | C15: Stock de producto terminado excesivo u obsoleto por fabricar contra una previsión inflada | D15: Ineficiencia (coste) | E15: Circulante × CMPC | F15: € de stock sin movimiento > 6 meses | G15: H04 | H15: =INDEX(Hallazgos!$E$5:$E$15,MATCH(G15,Hallazgos!$A$5:$A$15,0)) -> Stock sin política | I15: D-PL09 | J15: Si el stock se deprecia o se destruye, esa pérdida es Fuga de P&L.
A16: D-H14 | B16: S&OP y Plan Maestro | C16: Roturas en materiales contra stock: hay pedidos que no se pueden servir | D16: Oportunidad (ingreso expuesto) | E16: Ingreso expuesto | F16: € de pedidos no servidos / mes | G16: H05 | H16: =INDEX(Hallazgos!$E$5:$E$15,MATCH(G16,Hallazgos!$A$5:$A$15,0)) -> Fecha al cliente no fiable | I16: D-PL09
A17: D-H15 | B17: S&OP y Plan Maestro | C17: La fecha al cliente se promete sin comprobar stock ni capacidad | D17: Oportunidad (ingreso expuesto) | E17: Ingreso expuesto | F17: € de pedidos / mes confirmados con fecha no viable | G17: H05 | H17: =INDEX(Hallazgos!$E$5:$E$15,MATCH(G17,Hallazgos!$A$5:$A$15,0)) -> Fecha al cliente no fiable | I17: D-PL10, D-PL25
A18: D-H16 | B18: S&OP y Plan Maestro | C18: Cuando se sabe que no se llega, la fecha no se renegocia con el cliente | D18: Oportunidad (ingreso expuesto) | E18: Ingreso expuesto | F18: € de pedidos / mes entregados tarde sin aviso | G18: H05 | H18: =INDEX(Hallazgos!$E$5:$E$15,MATCH(G18,Hallazgos!$A$5:$A$15,0)) -> Fecha al cliente no fiable | I18: D-PL11
A19: D-H18 | B19: S&OP y Plan Maestro | C19: Cálculos repetitivos a mano: reservas de capacidad (temporales), coberturas, cargas | D19: Ineficiencia (coste) | E19: Esfuerzo (ya contado dentro de personas) | F19: Horas / mes | G19: H03 | H19: =INDEX(Hallazgos!$E$5:$E$15,MATCH(G19,Hallazgos!$A$5:$A$15,0)) -> Demanda y capacidad sin equilibrar | I19: D-PL12 | J19: Es un cálculo fijo: mejor una regla automática que un agente.
A20: D-H19 | B20: S&OP y Plan Maestro | C20: Intercompany (opcional): la planta que suministra se entera por un pedido urgente, sin plan conjunto ni mín/máx | D20: Ineficiencia (coste) | E20: Transformación (horas de línea, mermas) | F20: Pedidos intercompany urgentes / mes | G20: H03 | H20: =INDEX(Hallazgos!$E$5:$E$15,MATCH(G20,Hallazgos!$A$5:$A$15,0)) -> Demanda y capacidad sin equilibrar | I20: D-PL06, D-PL13 | J20: Solo para las divisiones que se suministran entre sí.
A21: D-H21 | B21: Necesidades y Aprovisionamiento | C21: Parámetros de planificación desactualizados: lote mínimo y múltiplo, plazos, stock de seguridad | D21: Ineficiencia (coste) | E21: Circulante × CMPC | F21: % de materiales sin revisar en 12 meses | G21: H07 | H21: =INDEX(Hallazgos!$E$5:$E$15,MATCH(G21,Hallazgos!$A$5:$A$15,0)) -> Necesidades poco fiables | I21: D-PL15
A22: D-H22 | B22: Necesidades y Aprovisionamiento | C22: El MRP corre con poca frecuencia y las faltas se detectan tarde | D22: Ineficiencia (coste) | E22: Transformación (horas de línea, mermas) | F22: Faltas / mes detectadas con menos margen que el plazo del proveedor | G22: H06 | H22: =INDEX(Hallazgos!$E$5:$E$15,MATCH(G22,Hallazgos!$A$5:$A$15,0)) -> Faltas tardías y gestionadas a mano | I22: D-PL16
A23: D-H23 | B23: Necesidades y Aprovisionamiento | C23: Las faltas se revisan todas a mano, sin criticidad ni gestión por excepción | D23: Ineficiencia (coste) | E23: Esfuerzo (ya contado dentro de personas) | F23: Líneas de falta revisadas / semana | G23: H06 | H23: =INDEX(Hallazgos!$E$5:$E$15,MATCH(G23,Hallazgos!$A$5:$A$15,0)) -> Faltas tardías y gestionadas a mano | I23: D-PL14
A24: D-H24 | B24: Necesidades y Aprovisionamiento | C24: Compras y transportes urgentes por faltas no anticipadas | D24: Ineficiencia (coste) | E24: Fuga de P&L | F24: € de sobrecoste urgente / mes | G24: H06 | H24: =INDEX(Hallazgos!$E$5:$E$15,MATCH(G24,Hallazgos!$A$5:$A$15,0)) -> Faltas tardías y gestionadas a mano | I24: D-PL16
A25: D-H25 | B25: Necesidades y Aprovisionamiento | C25: Producto terminado y semielaborado se planifican por separado, sin sincronizar | D25: Ineficiencia (coste) | E25: Circulante × CMPC | F25: € de stock de semielaborado | G25: H07 | H25: =INDEX(Hallazgos!$E$5:$E$15,MATCH(G25,Hallazgos!$A$5:$A$15,0)) -> Necesidades poco fiables | I25: D-PL17
A26: D-H26 | B26: Necesidades y Aprovisionamiento | C26: La agrupación de necesidades en lotes o combinaciones se hace a mano | D26: Ineficiencia (coste) | E26: Transformación (horas de línea, mermas) | F26: % de merma de combinación | G26: H07 | H26: =INDEX(Hallazgos!$E$5:$E$15,MATCH(G26,Hallazgos!$A$5:$A$15,0)) -> Necesidades poco fiables | I26: D-PL18
A27: D-H27 | B27: Necesidades y Aprovisionamiento | C27: Materias primas y auxiliares sin política de stock: se compra a ojo o por el mínimo del proveedor | D27: Ineficiencia (coste) | E27: Circulante × CMPC | F27: € de materia prima sin consumo > 6 meses | G27: H04 | H27: =INDEX(Hallazgos!$E$5:$E$15,MATCH(G27,Hallazgos!$A$5:$A$15,0)) -> Stock sin política | I27: D-PL09
A28: D-H28 | B28: Programación | C28: La secuencia se hace a mano, sin optimizar los cambios (molde, formato, altura, color) | D28: Ineficiencia (coste) | E28: Transformación (horas de línea, mermas) | F28: Horas de cambio / semana | G28: H08 | H28: =INDEX(Hallazgos!$E$5:$E$15,MATCH(G28,Hallazgos!$A$5:$A$15,0)) -> Secuencia sin optimizar | I28: D-PL19
A29: D-H29 | B29: Programación | C29: Se programa sin capacidad finita: se carga más de lo que cabe | D29: Ineficiencia (coste) | E29: Transformación (horas de línea, mermas) | F29: Horas cargadas por encima de la capacidad / semana | G29: H08 | H29: =INDEX(Hallazgos!$E$5:$E$15,MATCH(G29,Hallazgos!$A$5:$A$15,0)) -> Secuencia sin optimizar | I29: D-PL19
A30: D-H30 | B30: Programación | C30: El programa no tiene zona congelada y los cambios de última hora obligan a resecuenciar | D30: Ineficiencia (coste) | E30: Transformación (horas de línea, mermas) | F30: Resecuenciaciones / semana | G30: H09 | H30: =INDEX(Hallazgos!$E$5:$E$15,MATCH(G30,Hallazgos!$A$5:$A$15,0)) -> Programa inestable | I30: D-PL08
A31: D-H31 | B31: Programación | C31: Urgencias y prioridades sin reglas: se decide por llamada o se escala a dirección | D31: Ineficiencia (coste) | E31: Esfuerzo (ya contado dentro de personas) | F31: Escalados / semana | G31: H09 | H31: =INDEX(Hallazgos!$E$5:$E$15,MATCH(G31,Hallazgos!$A$5:$A$15,0)) -> Programa inestable | I31: D-PL20
A32: D-H32 | B32: Programación | C32: Se usa siempre la ruta por defecto, sin reequilibrar con la carga | D32: Ineficiencia (coste) | E32: Transformación (horas de línea, mermas) | F32: Horas en ruta no óptima / mes | G32: H08 | H32: =INDEX(Hallazgos!$E$5:$E$15,MATCH(G32,Hallazgos!$A$5:$A$15,0)) -> Secuencia sin optimizar | I32: D-PL19
... A35: D-H36 | B35: Liberación | C35: El aprovisionamiento a línea no va sincronizado con la secuencia | D35: Ineficiencia (coste) | E35: Transformación (horas de línea, mermas) | F35: Minutos de espera de material por orden | G35: H10 | H35: =INDEX(Hallazgos!$E$5:$E$15,MATCH(G35,Hallazgos!$A$5:$A$15,0)) -> Liberación sin control | I35: D-PL22
A36: D-H38 | B36: Seguimiento y Control | C36: No hay KPIs formales de servicio (OTIF a fecha confirmada) ni de adherencia al programa | D36: Oportunidad (ingreso expuesto) | E36: Ingreso expuesto | F36: Pedidos / mes sin medir | G36: H11 | H36: =INDEX(Hallazgos!$E$5:$E$15,MATCH(G36,Hallazgos!$A$5:$A$15,0)) -> Servicio sin control | I36: D-PL23 | J36: Habilitador: no suma € por sí solo. Piso «sin declarar».
A37: D-H39 | B37: Seguimiento y Control | C37: Los atrasos se detectan cuando ya han ocurrido, sin aviso de pedidos en riesgo | D37: Oportunidad (ingreso expuesto) | E37: Ingreso expuesto | F37: € de pedidos atrasados / mes | G37: H11 | H37: =INDEX(Hallazgos!$E$5:$E$15,MATCH(G37,Hallazgos!$A$5:$A$15,0)) -> Servicio sin control | I37: D-PL23, D-PL25
A38: D-H40 | B38: Seguimiento y Control | C38: Las desviaciones del plan no tienen análisis de causa y lo aprendido no vuelve a la previsión ni a los parámetros | D38: Ineficiencia (coste) | E38: Transformación (horas de línea, mermas) | F38: Desviaciones sin causa / mes | G38: H12 | H38: =INDEX(Hallazgos!$E$5:$E$15,MATCH(G38,Hallazgos!$A$5:$A$15,0)) -> Ciclo sin aprendizaje | I38: D-PL24
A39: D-H41 | B39: Seguimiento y Control | C39: Los informes de seguimiento se hacen a mano | D39: Ineficiencia (coste) | E39: Esfuerzo (ya contado dentro de personas) | F39: Horas / semana | G39: H12 | H39: =INDEX(Hallazgos!$E$5:$E$15,MATCH(G39,Hallazgos!$A$5:$A$15,0)) -> Ciclo sin aprendizaje | I39: D-PL12

Sheet Detalle palancas
A1: Detalle de palancas (para intervenciones)
A2: Punto de partida para traducir cada palanca en acciones, automatizaciones y agentes.
A4: ID detalle | B4: Palanca (detalle) | C4: Tipo principal | D4: Tipo secundario | E4: Evoluciona a IA | F4: Hallazgos de detalle | G4: KPI | H4: Intervención tipo (cómo) | I4: Nivel alto | J4: Palanca de nivel alto | K4: Notas
A5: D-PL01 | B5: Previsión estadística por familia y material, a 12–18 meses | C5: Auto | E5: Sí | F5: D-H08, D-H45 | G5: Precisión (1–WMAPE) | H5: Modelo por familia y material con histórico limpio (incluida la demanda perdida) y estacionalidad; Comercial solo revisa las excepciones antes del cierre. | I5: PL01 | J5: =INDEX(Palancas!$C$5:$C$12,MATCH(I5,Palancas!$A$5:$A$12,0)) -> Gestión de la demanda
A6: D-PL02 | B6: Calendario de demanda con día de cierre y mes en curso congelado | C6: Política | E6: No | F6: D-H02 | G6: Cambios tras el cierre | H6: Publicar el calendario anual con el día de cierre y bloquear en el sistema la previsión del mes en curso; los cambios posteriores, solo con aprobación y motivo. | I6: PL01 | J6: =INDEX(Palancas!$C$5:$C$12,MATCH(I6,Palancas!$A$5:$A$12,0)) -> Gestión de la demanda
A7: D-PL03 | B7: Revisión mensual de demanda con consenso | C7: Política | E7: No | F7: D-H03 | G7: Consenso en fecha | H7: Reunión mensual Comercial–Planificación con orden del día fijo, acta y decisiones. | I7: PL01 | J7: =INDEX(Palancas!$C$5:$C$12,MATCH(I7,Palancas!$A$5:$A$12,0)) -> Gestión de la demanda
A8: D-PL04 | B8: Registro de la demanda perdida con su motivo | C8: Dato | E8: No | F8: D-H05 | G8: % de agotados registrados | H8: Definir qué es un agotado o un rechazo y registrarlo a diario en el sistema, con su motivo. | I8: PL01 | J8: =INDEX(Palancas!$C$5:$C$12,MATCH(I8,Palancas!$A$5:$A$12,0)) -> Gestión de la demanda
A9: D-PL05 | B9: KPI de precisión y sesgo por familia, con umbral y plan de acción | C9: Auto | E9: No | F9: D-H06, D-H07 | G9: Familias fuera de umbral con acción | H9: Cálculo automático mensual por familia, umbral por segmento y plan de acción para cada familia fuera de umbral. | I9: PL01 | J9: =INDEX(Palancas!$C$5:$C$12,MATCH(I9,Palancas!$A$5:$A$12,0)) -> Gestión de la demanda
A10: D-PL06 | B10: S&OP mensual con escenarios valorados en € y reunión ejecutiva | C10: Política | E10: No | F10: D-H09, D-H19 | G10: Horas extra no planificadas · cumplimiento del plan | H10: Ciclo mensual: revisión de demanda, revisión de suministro y reunión ejecutiva; cada escenario (turnos, stock, subcontratación, intercompany) valorado en €. | I10: PL02 | J10: =INDEX(Palancas!$C$5:$C$12,MATCH(I10,Palancas!$A$5:$A$12,0)) -> S&OP y plan de capacidad
A11: D-PL07 | B11: Plan de capacidad: carga frente a capacidad por línea, con regla de turnos | C11: Auto | E11: Sí | F11: D-H10 | G11: Ocupación real frente a la planificada | H11: Cruce automático de previsión cerrada × rutas × tiempos de ciclo contra el calendario; umbrales de ocupación para abrir o cerrar turnos. | I11: PL02 | J11: =INDEX(Palancas!$C$5:$C$12,MATCH(I11,Palancas!$A$5:$A$12,0)) -> S&OP y plan de capacidad
A12: D-PL08 | B12: Zona congelada en el programa | C12: Política | E12: No | F12: D-H30 | G12: Cambios en zona congelada | H12: Definir el horizonte congelado del programa; las excepciones se aprueban y quedan registradas. | I12: PL06 | J12: =INDEX(Palancas!$C$5:$C$12,MATCH(I12,Palancas!$A$5:$A$12,0)) -> Programación estable y optimizada
A13: D-PL09 | B13: Segmentación ABC/XYZ y política de stock por segmento, revisada cada trimestre | C13: Política | D13: Auto | E13: No | F13: D-H12, D-H13, D-H14, D-H27 | G13: Cobertura · roturas · stock obsoleto | H13: Criterios ABC por valor y XYZ por variabilidad, matriz que asigna MTS/MTO y stock de seguridad, y recálculo trimestral automático. | I13: PL03 | J13: =INDEX(Palancas!$C$5:$C$12,MATCH(I13,Palancas!$A$5:$A$12,0)) -> Política de inventario por segmento
A14: D-PL10 | B14: Promesa de fecha con disponibilidad real: stock y capacidad libre (ATP/CTP) | C14: Auto | E14: No | F14: D-H15 | G14: % de pedidos confirmados con fecha viable | H14: Consulta de disponibilidad (stock y capacidad libre) al confirmar el pedido: la fecha la propone el sistema, no se teclea. | I14: PL04 | J14: =INDEX(Palancas!$C$5:$C$12,MATCH(I14,Palancas!$A$5:$A$12,0)) -> Promesa de fecha fiable
A15: D-PL11 | B15: Política de fecha: dos fechas en el pedido, plazo de confirmación y aviso al cliente | C15: Política | E15: No | F15: D-H16 | G15: OTIF a fecha confirmada | H15: Fecha solicitada y fecha confirmada en cada pedido; plazo fijo de confirmación y aviso al cliente si no se llega. | I15: PL04 | J15: =INDEX(Palancas!$C$5:$C$12,MATCH(I15,Palancas!$A$5:$A$12,0)) -> Promesa de fecha fiable
A16: D-PL12 | B16: Automatizar cálculos e informes repetitivos | C16: Auto | E16: No | F16: D-H18, D-H41 | G16: Horas liberadas | H16: Pasar a reglas del sistema los cálculos e informes que hoy se hacen en Excel cada día, semana o mes. | I16: PL02 | J16: =INDEX(Palancas!$C$5:$C$12,MATCH(I16,Palancas!$A$5:$A$12,0)) -> S&OP y plan de capacidad | K16: Los informes de seguimiento (D-H41) van con la palanca de nivel alto PL08.
A17: D-PL13 | B17: Plan intercompany con mín/máx y pedidos programados | C17: Política | E17: No | F17: D-H19 | G17: Pedidos intercompany urgentes | H17: Mín/máx por material entre plantas, pedidos programados y revisión semanal conjunta. | I17: PL02 | J17: =INDEX(Palancas!$C$5:$C$12,MATCH(I17,Palancas!$A$5:$A$12,0)) -> S&OP y plan de capacidad
A18: D-PL14 | B18: Necesidades por excepción: alertas por criticidad | C18: Auto | E18: Sí | F18: D-H23 | G18: Líneas de falta revisadas | H18: El sistema marca solo las excepciones, ordenadas por criticidad. | I18: PL05 | J18: =INDEX(Palancas!$C$5:$C$12,MATCH(I18,Palancas!$A$5:$A$12,0)) -> Planificación de materiales por excepción
A19: D-PL15 | B19: Revisión periódica de los parámetros de planificación contra la realidad | C19: Dato | E19: No | F19: D-H21 | G19: % de parámetros vigentes | H19: Revisión semestral de lotes, plazos y stock de seguridad contra los datos reales, con un responsable por parámetro. | I19: PL05 | J19: =INDEX(Palancas!$C$5:$C$12,MATCH(I19,Palancas!$A$5:$A$12,0)) -> Planificación de materiales por excepción
A20: D-PL16 | B20: MRP diario con alertas tempranas de faltas | C20: Auto | E20: No | F20: D-H22, D-H24 | G20: Faltas detectadas a tiempo · € urgentes | H20: MRP diario (nocturno) con alerta de faltas priorizada por fecha de necesidad y por pedido de cliente. | I20: PL05 | J20: =INDEX(Palancas!$C$5:$C$12,MATCH(I20,Palancas!$A$5:$A$12,0)) -> Planificación de materiales por excepción
A21: D-PL17 | B21: Planificación multinivel sincronizada: producto terminado, semielaborado y materias primas | C21: Sistema | E21: No | F21: D-H25 | G21: Stock de semielaborado | H21: Planificar los tres niveles en el mismo cálculo, con trazabilidad de cada necesidad hasta su origen. | I21: PL05 | J21: =INDEX(Palancas!$C$5:$C$12,MATCH(I21,Palancas!$A$5:$A$12,0)) -> Planificación de materiales por excepción
A22: D-PL18 | B22: Optimizador de agrupación y combinación | C22: Algoritmo | E22: No | F22: D-H26 | G22: % de merma | H22: Algoritmo de agrupación por reglas de lote y combinación que minimiza la merma y los cambios. | I22: PL05 | J22: =INDEX(Palancas!$C$5:$C$12,MATCH(I22,Palancas!$A$5:$A$12,0)) -> Planificación de materiales por excepción
A23: D-PL19 | B23: Secuenciador con capacidad finita, matriz de cambios y rutas alternativas | C23: Algoritmo | E23: Sí | F23: D-H28, D-H29, D-H32 | G23: Horas de cambio · adherencia | H23: Matriz de tiempos de cambio por línea y capacidad finita; propone la secuencia y las rutas alternativas, y el programador la aprueba. | I23: PL06 | J23: =INDEX(Palancas!$C$5:$C$12,MATCH(I23,Palancas!$A$5:$A$12,0)) -> Programación estable y optimizada
A24: D-PL20 | B24: Reglas de prioridad y de escalado | C24: Política | E24: No | F24: D-H31 | G24: Escalados / semana | H24: Criterios escritos (cliente, fecha, margen, penalización) y un árbitro definido para los conflictos. | I24: PL06 | J24: =INDEX(Palancas!$C$5:$C$12,MATCH(I24,Palancas!$A$5:$A$12,0)) -> Programación estable y optimizada
A25: D-PL22 | B25: Semáforo de liberación 24–72 h antes, con ventana de liberación | C25: Auto | E25: No | F25: D-H34, D-H35, D-H36 | G25: Arranques fallidos | H25: Comprobación automática de material en línea, utillaje y personal; la orden se libera en verde y dentro de su ventana. | I25: PL07 | J25: =INDEX(Palancas!$C$5:$C$12,MATCH(I25,Palancas!$A$5:$A$12,0)) -> Liberación controlada
A26: D-PL23 | B26: Cuadro de mando de servicio y adherencia, con alertas de pedidos en riesgo | C26: Auto | E26: No | F26: D-H38, D-H39 | G26: OTIF · avisos anticipados | H26: OTIF a fecha confirmada y adherencia al programa calculados solos, con alerta de los pedidos en riesgo antes de que se retrasen. | I26: PL08 | J26: =INDEX(Palancas!$C$5:$C$12,MATCH(I26,Palancas!$A$5:$A$12,0)) -> Control del servicio y mejora continua
A27: D-PL24 | B27: Análisis de causa raíz de las desviaciones, que vuelve a la previsión y a los parámetros | C27: Política | E27: Sí | F27: D-H07, D-H40 | G27: Desviaciones con causa | H27: Clasificar cada desviación por causa (lista cerrada), asignar una acción con responsable y devolver lo aprendido a la previsión y a los parámetros. | I27: PL08 | J27: =INDEX(Palancas!$C$5:$C$12,MATCH(I27,Palancas!$A$5:$A$12,0)) -> Control del servicio y mejora continua
A28: D-PL25 | B28: Copiloto de consulta: «¿cuándo sirvo X?», «¿por qué va tarde X?» | C28: Consulta | E28: No | F28: D-H15, D-H39 | G28: Consultas resueltas sin llamada | H28: Asistente que responde sobre plazos y estado de pedidos con los datos del sistema, sin modificar nada. | I28: PL04 | J28: =INDEX(Palancas!$C$5:$C$12,MATCH(I28,Palancas!$A$5:$A$12,0)) -> Promesa de fecha fiable | K28: «¿Por qué va tarde X?» también sirve a la palanca de nivel alto PL08.

Sheet Otros procesos
A1: Detectados en P2R, pero van al maestro de otro proceso
A2: Créalos en el proceso destino con «Detectado en: P2R»: el coste suma donde se arregla.
A4: ID | B4: Proceso destino | C4: Detectado en | D4: Hallazgo | E4: Familia | F4: Naturaleza | G4: Métrica (volumen expuesto) | H4: Palanca en ese proceso
A5: X01 | B5: R2M | C5: P2R | D5: El alta de material no pasa por Planificación (estrategia, ruta, parámetros) | E5: Ineficiencia (coste) | F5: Circulante × CMPC | G5: Altas / mes sin validar por Planificación | H5: Validación de Planificación en el alta de material
A6: X02 | B6: R2M | C6: P2R | D6: Duplicados en el maestro, sin criterio de qué es un material | E6: Ineficiencia (coste) | F6: Esfuerzo (ya contado dentro de personas) | G6: Materiales duplicados | H6: Criterio de material y auditoría de duplicados
A7: X03 | B7: R2M | C7: P2R | D7: El calendario de turnos y paradas, las velocidades y los tiempos de cambio no coinciden con la realidad | E7: Ineficiencia (coste) | F7: Transformación (horas de línea, mermas) | G7: % de recursos con datos sin revisar | H7: Maestro de recursos de fabricación mantenido
A8: X04 | B8: P2P | C8: P2R | D8: Plazos de proveedor desactualizados y confirmaciones sin registrar | E8: Ineficiencia (coste) | F8: Circulante × CMPC | G8: % de líneas con fecha confirmada distinta de la prevista | H8: Seguimiento de confirmaciones de proveedor
A9: X05 | B9: O2C | C9: P2R | D9: Cartera con errores (cantidades mayores que el pedido, fechas imposibles) y pedidos servidos sin saldar | E9: Ineficiencia (coste) | F9: Circulante × CMPC | G9: Líneas de cartera erróneas o servidas sin saldar | H9: Validación de cargas y saldado por regla

Sheet Ondupet
A1: Ondupet · dónde cae lo que ya está creado
A2: Para re-vincular los hallazgos y palancas creados directamente en la celda P2R × Ondupet.
A4: Nº | B4: Hallazgo creado | C4: Nivel alto | D4: Hallazgo de nivel alto | E4: Detalle | F4: Nota
A5: 1 | B5: Sin cierre de previsiones: se modifica a mitad de mes | C5: H01 | D5: =IFERROR(INDEX(Hallazgos!$E$5:$E$15,MATCH(C5,Hallazgos!$A$5:$A$15,0)),INDEX('Otros procesos'!$D$5:$D$9,MATCH(C5,'Otros procesos'!$A$5:$A$9,0))) -> Demanda sin previsión fiable | E5: D-H02
A6: 2 | B6: No se hace carga de capacidad (se decide por sensaciones) | C6: H03 | D6: =IFERROR(INDEX(Hallazgos!$E$5:$E$15,MATCH(C6,Hallazgos!$A$5:$A$15,0)),INDEX('Otros procesos'!$D$5:$D$9,MATCH(C6,'Otros procesos'!$A$5:$A$9,0))) -> Demanda y capacidad sin equilibrar | E6: D-H10 | F6: 2 y 4 caen en el mismo hallazgo de nivel alto.
A7: 3 | B7: No se calculan ABC ni estrategias | C7: H04 | D7: =IFERROR(INDEX(Hallazgos!$E$5:$E$15,MATCH(C7,Hallazgos!$A$5:$A$15,0)),INDEX('Otros procesos'!$D$5:$D$9,MATCH(C7,'Otros procesos'!$A$5:$A$9,0))) -> Stock sin política | E7: D-H12
A8: 4 | B8: Temporales calculados a mano cada mes | C8: H03 | D8: =IFERROR(INDEX(Hallazgos!$E$5:$E$15,MATCH(C8,Hallazgos!$A$5:$A$15,0)),INDEX('Otros procesos'!$D$5:$D$9,MATCH(C8,'Otros procesos'!$A$5:$A$9,0))) -> Demanda y capacidad sin equilibrar | E8: D-H18 | F8: 2 y 4 caen en el mismo hallazgo de nivel alto.
A9: 5 | B9: No se modifican las fechas al cliente aunque se sepa que no se llega | C9: H05 | D9: =IFERROR(INDEX(Hallazgos!$E$5:$E$15,MATCH(C9,Hallazgos!$A$5:$A$15,0)),INDEX('Otros procesos'!$D$5:$D$9,MATCH(C9,'Otros procesos'!$A$5:$A$9,0))) -> Fecha al cliente no fiable | E9: D-H16 | F9: Familia: Oportunidad (ingreso expuesto).
A10: 6 | B10: Saldado de pedidos manual; a veces no se hace | C10: X05 | D10: =IFERROR(INDEX(Hallazgos!$E$5:$E$15,MATCH(C10,Hallazgos!$A$5:$A$15,0)),INDEX('Otros procesos'!$D$5:$D$9,MATCH(C10,'Otros procesos'!$A$5:$A$9,0))) -> Cartera con errores (cantidades mayores que el pedido, fechas imposibles) y pedidos servidos sin saldar | F10: Va a O2C × Ondupet con «Detectado en: P2R».
A11: 7 | B11: Corrección manual de desviaciones de demanda | C11: H01 | D11: =IFERROR(INDEX(Hallazgos!$E$5:$E$15,MATCH(C11,Hallazgos!$A$5:$A$15,0)),INDEX('Otros procesos'!$D$5:$D$9,MATCH(C11,'Otros procesos'!$A$5:$A$9,0))) -> Demanda sin previsión fiable | F11: A confirmar: su detalle (antiguo H20) lo borraste; lo más cercano es H01.
A12: 8 | B12: Revisión de faltas manual | C12: H06 | D12: =IFERROR(INDEX(Hallazgos!$E$5:$E$15,MATCH(C12,Hallazgos!$A$5:$A$15,0)),INDEX('Otros procesos'!$D$5:$D$9,MATCH(C12,'Otros procesos'!$A$5:$A$9,0))) -> Faltas tardías y gestionadas a mano | E12: D-H23
A13: 9 | B13: Secuenciación a mano | C13: H08 | D13: =IFERROR(INDEX(Hallazgos!$E$5:$E$15,MATCH(C13,Hallazgos!$A$5:$A$15,0)),INDEX('Otros procesos'!$D$5:$D$9,MATCH(C13,'Otros procesos'!$A$5:$A$9,0))) -> Secuencia sin optimizar | E13: D-H28
A15: Palancas
A16: Nº | B16: Palanca creada | C16: Nivel alto | D16: Palanca de nivel alto | E16: Detalle | F16: Nota
A17: P1 | B17: Previsión cerrada y congelada | C17: PL01 | D17: =IFERROR(INDEX(Palancas!$C$5:$C$12,MATCH(C17,Palancas!$A$5:$A$12,0)),INDEX('Otros procesos'!$H$5:$H$9,MATCH(C17,'Otros procesos'!$A$5:$A$9,0))) -> Gestión de la demanda | E17: D-PL02, D-PL05
A18: P2 | B18: Capacidad decidida con datos | C18: PL02 | D18: =IFERROR(INDEX(Palancas!$C$5:$C$12,MATCH(C18,Palancas!$A$5:$A$12,0)),INDEX('Otros procesos'!$H$5:$H$9,MATCH(C18,'Otros procesos'!$A$5:$A$9,0))) -> S&OP y plan de capacidad | E18: D-PL07, D-PL12
A19: P3 | B19: Segmentación y estrategias al día | C19: PL03 | D19: =IFERROR(INDEX(Palancas!$C$5:$C$12,MATCH(C19,Palancas!$A$5:$A$12,0)),INDEX('Otros procesos'!$H$5:$H$9,MATCH(C19,'Otros procesos'!$A$5:$A$9,0))) -> Política de inventario por segmento | E19: D-PL09
A20: P4 | B20: Fecha comprometida viable | C20: PL04 | D20: =IFERROR(INDEX(Palancas!$C$5:$C$12,MATCH(C20,Palancas!$A$5:$A$12,0)),INDEX('Otros procesos'!$H$5:$H$9,MATCH(C20,'Otros procesos'!$A$5:$A$9,0))) -> Promesa de fecha fiable | E20: D-PL11, D-PL10
A21: P5 | B21: Saldado por regla | C21: X05 | D21: =IFERROR(INDEX(Palancas!$C$5:$C$12,MATCH(C21,Palancas!$A$5:$A$12,0)),INDEX('Otros procesos'!$H$5:$H$9,MATCH(C21,'Otros procesos'!$A$5:$A$9,0))) -> Validación de cargas y saldado por regla
A22: P6 | B22: Necesidades y faltas por excepción | C22: PL05 | D22: =IFERROR(INDEX(Palancas!$C$5:$C$12,MATCH(C22,Palancas!$A$5:$A$12,0)),INDEX('Otros procesos'!$H$5:$H$9,MATCH(C22,'Otros procesos'!$A$5:$A$9,0))) -> Planificación de materiales por excepción | E22: D-PL14, D-PL16
A23: P7 | B23: Secuencia optimizada | C23: PL06 | D23: =IFERROR(INDEX(Palancas!$C$5:$C$12,MATCH(C23,Palancas!$A$5:$A$12,0)),INDEX('Otros procesos'!$H$5:$H$9,MATCH(C23,'Otros procesos'!$A$5:$A$9,0))) -> Programación estable y optimizada | E23: D-PL19, D-PL08, D-PL20
