Workbook

Sheet Fases
A1: Esqueleto estándar · P2R · Plan to Release
A2: Transcrito de la aplicación el 29/10/2026. Repositorio: sin repositorio · 8 palancas lo usan · 0 con uno propio. Variantes de P2R: 0 (todas las celdas usan el esqueleto estándar).
A4: Orden | B4: Fase | C4: Tramo | D4: Descripción (de → a) | E4: Opcional | F4: Áreas de negocio | G4: Actividades | H4: Hallazgos del catálogo | I4: Palancas del catálogo
A5: 1 | B5: Demanda y previsión (Forecast to Plan) | C5: Forecast to Plan | D5: De Histórico y Señal de Mercado --> Demanda Consensuada | E5: — | F5: todas | G5: 7 | H5: =COUNTIF(Hallazgos!$C$5:$C$15,B5) -> 1 | I5: =COUNTIF(Palancas!$F$5:$F$12,B5) -> 1
A6: 3 | B6: S&OP y Plan Maestro (Forecast to Plan) | C6: Forecast to Plan | D6: De Demanda Global --> Equilibrio Demanda, Capacidad y Recursos | E6: — | F6: todas | G6: 7 | H6: =COUNTIF(Hallazgos!$C$5:$C$15,B6) -> 3 | I6: =COUNTIF(Palancas!$F$5:$F$12,B6) -> 3
A7: 5 | B7: Necesidades de Fabricación y MRP | C7: Plan to Produce | D7: De Plan Maestro --> Órdenes Previsionales de Fabricación y Solicitudes de Compra | E7: — | F7: todas | G7: 8 | H7: =COUNTIF(Hallazgos!$C$5:$C$15,B7) -> 2 | I7: =COUNTIF(Palancas!$F$5:$F$12,B7) -> 1
A8: 6 | B8: Programación | C8: Plan to Produce | D8: De Orden Previsional --> Secuencia por Línea y Turno | E8: — | F8: todas | G8: 6 | H8: =COUNTIF(Hallazgos!$C$5:$C$15,B8) -> 2 | I8: =COUNTIF(Palancas!$F$5:$F$12,B8) -> 1
A9: 7 | B9: Liberación | C9: Plan to Produce | D9: De Orden Programada --> Orden Liberada Ejecutable | E9: — | F9: todas | G9: 4 | H9: =COUNTIF(Hallazgos!$C$5:$C$15,B9) -> 1 | I9: =COUNTIF(Palancas!$F$5:$F$12,B9) -> 1
A10: 8 | B10: Seguimiento y Control | C10: Plan to Produce | D10: De Plan Ejecutado --> Desviaciones Explicadas con Acción | E10: — | F10: todas | G10: 9 | H10: =COUNTIF(Hallazgos!$C$5:$C$15,B10) -> 2 | I10: =COUNTIF(Palancas!$F$5:$F$12,B10) -> 1
A11: Total | G11: =SUM(G5:G10) -> 41 | H11: =SUM(H5:H10) -> 11 | I11: =SUM(I5:I10) -> 8

Sheet Personas
A1: Personas por empresa
A2: Transcrito de la aplicación el 29/10/2026 (área de negocio Packaging, 14 personas). Coste anual estimado. «Σ dedicación» es el dato de la aplicación; «Dedicación detallada» suma la hoja Dedicación.
A4: Persona | B4: ID | C4: Email | D4: Categoría | E4: Roles | F4: Censo en | G4: Área de negocio | H4: Jornada h/año | I4: Coste anual (k€) | J4: Σ Dedicación | K4: Coste imputado (k€) | L4: Dedicación detallada | M4: Sin detallar | N4: Licencias
A5: Victoriano Pérez Carrasco | B5: ID-20 | C5: vperez@clgrupoindustrial.com | D5: Técnico especialista | E5: Planificación · Planificador de la producción | F5: Ondupet | G5: Packaging | H5: 1720 | I5: 60.2 | J5: 1 | K5: =I5*J5 -> 60.2 | L5: =SUMIF(Dedicación!$A$5:$A$12,A5,Dedicación!$E$5:$E$12) -> 1 | M5: =J5-L5 -> 0 | N5: sin licencias
A6: Bárbara Ayuste Tejera | B6: ID-22 | C6: bayuste@ondupet.es | D6: Administrativo | E6: Compras · Category Manager; Compras · Tramitadores de compras | F6: Ondupet | G6: Packaging | H6: 1720 | I6: 37.8 | J6: 0.25 | K6: =I6*J6 -> 9.45 | L6: =SUMIF(Dedicación!$A$5:$A$12,A6,Dedicación!$E$5:$E$12) -> 0.25 | M6: =J6-L6 -> 0 | N6: SAP ECC · usuario
A7: Manuel Jesús Trinidad Montero | B7: ID-24 | C7: mjtrinidad@ondupet.es | D7: Responsable / mando intermedio | E7: Comercial · Comercial con potestad | F7: Ondupet | G7: Packaging | H7: 1720 | I7: 82.6 | J7: 0.15 | K7: =I7*J7 -> 12.39 | L7: =SUMIF(Dedicación!$A$5:$A$12,A7,Dedicación!$E$5:$E$12) -> 0.15 | M7: =J7-L7 -> 0 | N7: sin licencias
A8: Monica Gordillo Guerrero | B8: ID-21 | C8: mgordillo@ondupet.es | D8: Administrativo | E8: Comercial · Comercial con potestad; Comercial · Administración de ventas | F8: Ondupet | G8: Packaging | H8: 1720 | I8: 37.8 | J8: 0.2 | K8: =I8*J8 -> 7.56 | L8: =SUMIF(Dedicación!$A$5:$A$12,A8,Dedicación!$E$5:$E$12) -> 0.2 | M8: =J8-L8 -> 0 | N8: sin licencias
A9: Antonio Nogales Carrión | B9: ID-23 | C9: anogales@ondupet.es | D9: Responsable / mando intermedio | E9: Compras · Category Manager; Compras · Tramitadores de compras | F9: Ondupet | G9: Packaging | H9: 1720 | I9: 82.6 | J9: 0 | K9: =I9*J9 -> 0 | L9: =SUMIF(Dedicación!$A$5:$A$12,A9,Dedicación!$E$5:$E$12) -> 0 | M9: =J9-L9 -> 0
A10: Miguel Ángel Rosado Martínez | B10: sin ID | C10: planificacion@ondupack.com | D10: Técnico especialista | E10: Planificación · Planificador de la producción; Logística · Responsable Expediciones | F10: Ondupack | G10: Cartón | H10: 1720 | I10: 60.2 | J10: 0 | K10: =I10*J10 -> 0 | L10: =SUMIF(Dedicación!$A$5:$A$12,A10,Dedicación!$E$5:$E$12) -> 0 | M10: =J10-L10 -> 0
A11: Tomás Buenavida Santiago | B11: sin ID | C11: tbuenavida@ondupack.com | D11: Administrativo | E11: Planificación · Planificador de la producción | F11: Ondupack | G11: Cartón | H11: 1720 | I11: 37.8 | J11: 0 | K11: =I11*J11 -> 0 | L11: =SUMIF(Dedicación!$A$5:$A$12,A11,Dedicación!$E$5:$E$12) -> 0 | M11: =J11-L11 -> 0
A12: Maria Teresa Espinosa Paredes | B12: sin ID | C12: tere_att@ondupack.com | D12: Técnico especialista | E12: Comercial | F12: Ondupack | G12: Cartón | H12: 1720 | I12: 60.2 | J12: 0.1 | K12: =I12*J12 -> 6.02 | L12: =SUMIF(Dedicación!$A$5:$A$12,A12,Dedicación!$E$5:$E$12) -> 0 | M12: =J12-L12 -> 0.1
A13: José María Baquero Jaen | B13: sin ID | C13: jbaquero@ondupack.com | D13: Responsable / mando intermedio | E13: Producción · Responsable Producción | F13: Ondupack | G13: Cartón | H13: 1720 | I13: 82.6 | J13: 0 | K13: =I13*J13 -> 0 | L13: =SUMIF(Dedicación!$A$5:$A$12,A13,Dedicación!$E$5:$E$12) -> 0 | M13: =J13-L13 -> 0
A14: Angélica Lemus Fernández | B14: sin ID | C14: alemus@ondupack.com | D14: Responsable / mando intermedio | E14: Compras · Category Manager | F14: Ondupack | G14: Cartón | H14: 1720 | I14: 82.6 | J14: 0 | K14: =I14*J14 -> 0 | L14: =SUMIF(Dedicación!$A$5:$A$12,A14,Dedicación!$E$5:$E$12) -> 0 | M14: =J14-L14 -> 0
A15: Karim Karach Boujtat | B15: sin ID | C15: kkarach@ondupack.com | D15: Responsable / mando intermedio | E15: Producción · Responsable Producción | F15: Navalmoral | G15: Cartón | H15: 1720 | I15: 82.6 | J15: 0 | K15: =I15*J15 -> 0 | L15: =SUMIF(Dedicación!$A$5:$A$12,A15,Dedicación!$E$5:$E$12) -> 0 | M15: =J15-L15 -> 0
A16: Joan Carles Girones Campaña | B16: sin ID | C16: jc.girones@matiasgomatomas.com | D16: Técnico especialista | E16: Planificación · Planificador de la producción | F16: MGT | G16: Papel | H16: 1720 | I16: 60.2 | J16: 0 | K16: =I16*J16 -> 0 | L16: =SUMIF(Dedicación!$A$5:$A$12,A16,Dedicación!$E$5:$E$12) -> 0 | M16: =J16-L16 -> 0
A17: Marta Boyo Martinez | B17: sin ID | C17: m.boyo@matiasgomatomas.com | D17: Técnico especialista | E17: Compras · Category Manager | F17: MGT | G17: Papel | H17: 1720 | I17: 60.2 | J17: 0 | K17: =I17*J17 -> 0 | L17: =SUMIF(Dedicación!$A$5:$A$12,A17,Dedicación!$E$5:$E$12) -> 0 | M17: =J17-L17 -> 0
A18: Albert Fontanet Lopez | B18: sin ID | C18: a.fontanet@matiasgomatomas.com | D18: Responsable / mando intermedio | E18: Comercial | F18: MGT | G18: Papel | H18: 1720 | I18: 82.6 | J18: 0 | K18: =I18*J18 -> 0 | L18: =SUMIF(Dedicación!$A$5:$A$12,A18,Dedicación!$E$5:$E$12) -> 0 | M18: =J18-L18 -> 0
A19: Σ 14 personas | H19: =SUM(H5:H18) -> 24080 | I19: =SUM(I5:I18) -> 910 | K19: =SUM(K5:K18) -> 95.62

Sheet Dedicación
A1: Dedicación por celda y fase
A2: Una fila por persona, celda (proceso × empresa) y fase. Por ahora solo está el detalle de P2R × Ondupet.
A4: Persona | B4: Censo en | C4: Celda | D4: Fase | E4: % dedicación | F4: Coste imputado (k€)
A5: Bárbara Ayuste Tejera | B5: =INDEX(Personas!$F$5:$F$18,MATCH(A5,Personas!$A$5:$A$18,0)) -> Ondupet | C5: P2R × Ondupet | D5: Necesidades de Fabricación y MRP | E5: 0.25 | F5: =E5*INDEX(Personas!$I$5:$I$18,MATCH(A5,Personas!$A$5:$A$18,0)) -> 9.45
A6: Manuel Jesús Trinidad Montero | B6: =INDEX(Personas!$F$5:$F$18,MATCH(A6,Personas!$A$5:$A$18,0)) -> Ondupet | C6: P2R × Ondupet | D6: S&OP y Plan Maestro (Forecast to Plan) | E6: 0.15 | F6: =E6*INDEX(Personas!$I$5:$I$18,MATCH(A6,Personas!$A$5:$A$18,0)) -> 12.39
A7: Monica Gordillo Guerrero | B7: =INDEX(Personas!$F$5:$F$18,MATCH(A7,Personas!$A$5:$A$18,0)) -> Ondupet | C7: P2R × Ondupet | D7: S&OP y Plan Maestro (Forecast to Plan) | E7: 0.2 | F7: =E7*INDEX(Personas!$I$5:$I$18,MATCH(A7,Personas!$A$5:$A$18,0)) -> 7.56
A8: Victoriano Pérez Carrasco | B8: =INDEX(Personas!$F$5:$F$18,MATCH(A8,Personas!$A$5:$A$18,0)) -> Ondupet | C8: P2R × Ondupet | D8: Necesidades de Fabricación y MRP | E8: 0.3 | F8: =E8*INDEX(Personas!$I$5:$I$18,MATCH(A8,Personas!$A$5:$A$18,0)) -> 18.06
A9: Victoriano Pérez Carrasco | B9: =INDEX(Personas!$F$5:$F$18,MATCH(A9,Personas!$A$5:$A$18,0)) -> Ondupet | C9: P2R × Ondupet | D9: Liberación | E9: 0.25 | F9: =E9*INDEX(Personas!$I$5:$I$18,MATCH(A9,Personas!$A$5:$A$18,0)) -> 15.05
A10: Victoriano Pérez Carrasco | B10: =INDEX(Personas!$F$5:$F$18,MATCH(A10,Personas!$A$5:$A$18,0)) -> Ondupet | C10: P2R × Ondupet | D10: Programación | E10: 0.25 | F10: =E10*INDEX(Personas!$I$5:$I$18,MATCH(A10,Personas!$A$5:$A$18,0)) -> 15.05
A11: Victoriano Pérez Carrasco | B11: =INDEX(Personas!$F$5:$F$18,MATCH(A11,Personas!$A$5:$A$18,0)) -> Ondupet | C11: P2R × Ondupet | D11: Seguimiento y Control | E11: 0.15 | F11: =E11*INDEX(Personas!$I$5:$I$18,MATCH(A11,Personas!$A$5:$A$18,0)) -> 9.03
A12: Victoriano Pérez Carrasco | B12: =INDEX(Personas!$F$5:$F$18,MATCH(A12,Personas!$A$5:$A$18,0)) -> Ondupet | C12: P2R × Ondupet | D12: Demanda y previsión (Forecast to Plan) | E12: 0.05 | F12: =E12*INDEX(Personas!$I$5:$I$18,MATCH(A12,Personas!$A$5:$A$18,0)) -> 3.01
A15: Resumen por celda | B15: Personas | C15: Coste imputado (k€)
A16: P2R × Ondupet | B16: =SUMPRODUCT((Dedicación!$C$5:$C$12=A16)/COUNTIFS(Dedicación!$A$5:$A$12,Dedicación!$A$5:$A$12,Dedicación!$C$5:$C$12,Dedicación!$C$5:$C$12)) -> 4 | C16: =SUMIF(Dedicación!$C$5:$C$12,A16,Dedicación!$F$5:$F$12) -> 89.6
A17: P2R × Ondupack | B17: =SUMPRODUCT((Dedicación!$C$5:$C$12=A17)/COUNTIFS(Dedicación!$A$5:$A$12,Dedicación!$A$5:$A$12,Dedicación!$C$5:$C$12,Dedicación!$C$5:$C$12)) -> 0 | C17: =SUMIF(Dedicación!$C$5:$C$12,A17,Dedicación!$F$5:$F$12) -> 0
A18: P2R × MGT | B18: =SUMPRODUCT((Dedicación!$C$5:$C$12=A18)/COUNTIFS(Dedicación!$A$5:$A$12,Dedicación!$A$5:$A$12,Dedicación!$C$5:$C$12,Dedicación!$C$5:$C$12)) -> 0 | C18: =SUMIF(Dedicación!$C$5:$C$12,A18,Dedicación!$F$5:$F$12) -> 0

Sheet Hallazgos
A1: Catálogo de tipos de hallazgo · P2R
A2: Transcrito de la aplicación el 29/10/2026 (11 tipos). Descripción, métrica, KPI y fórmula del maestro; en la fórmula, valor y obj son los tokens de la aplicación y las constantes son de ejemplo. «Empresas» se calcula con las columnas de cada empresa.
A4: ID | B4: Nombre | C4: Fase | D4: Descripción | E4: Familia | F4: Naturaleza | G4: Métrica (volumen expuesto) | H4: KPI sugerido | I4: Fórmula sugerida (€/año) | J4: Se cura con | K4: Ondupet | L4: Ondupack | M4: MGT | N4: Empresas | O4: Caza inversa
A5: HT-P2R-01 | B5: Demanda sin previsión fiable | C5: Demanda y previsión (Forecast to Plan) | D5: No hay previsión, o la que hay no se cierra, no se consensúa ni se mide: el plan trabaja con una demanda que cambia o que no se conoce, y la demanda perdida no se registra. | E5: Ineficiencia | F5: Circulante | G5: € de demanda mensual planificada sin previsión cerrada y consensuada | H5: Precisión de la previsión (1 − WMAPE, %) ↑ | I5: (obj-valor)/100*2000000*0.08 | J5: P2R-01 | K5: ✓ | L5: ✓ | M5: ✓ | N5: =COUNTIF(K5:M5,"✓") -> 3 | O5: —
A6: HT-P2R-03 | B6: Demanda y capacidad sin equilibrar | C6: S&OP y Plan Maestro (Forecast to Plan) | D6: Sin S&OP, la capacidad (turnos, reservas, intercompany) se decide por intuición y a mano, y el desequilibrio se arregla con urgencias. | E6: Ineficiencia | F6: Transformación | G6: Horas de línea y turnos no ajustados a la carga / mes | H6: Horas de turno no ajustadas a la carga (h/mes) ↓ | I6: (valor-obj)*12*150 | J6: P2R-02 | K6: ✓ | L6: ✓ | M6: ✓ | N6: =COUNTIF(K6:M6,"✓") -> 3 | O6: —
A7: HT-P2R-04 | B7: Stock sin política clara | C7: S&OP y Plan Maestro (Forecast to Plan) | D7: Sin segmentación ni estrategia por material, sobra stock de unos y falta de otros, en producto terminado y en materias primas. | E7: Ineficiencia | F7: Circulante | G7: € de stock fuera de política (exceso y obsoleto) | H7: Cobertura de producto terminado (días) ↓ | I7: (valor-obj)*20000*0.08 | J7: P2R-03 | K7: ✓ | M7: ✓ | N7: =COUNTIF(K7:M7,"✓") -> 2 | O7: Ondupack
A8: HT-P2R-05 | B8: Fecha al cliente no fiable | C8: S&OP y Plan Maestro (Forecast to Plan) | D8: La fecha se promete sin comprobar disponibilidad, no se renegocia cuando no se llega y hay roturas en lo que debería estar en stock. | E8: Oportunidad | F8: — | G8: € de pedidos / mes entregados tarde o no servidos | H8: Pedidos entregados en la primera fecha confirmada (%) ↑ | I8: (obj-valor)/100*10000000 | J8: P2R-03, P2R-04 | K8: ✓ | M8: ✓ | N8: =COUNTIF(K8:M8,"✓") -> 2 | O8: Ondupack
A9: HT-P2R-06 | B9: Faltas tardías y gestionadas a mano | C9: Necesidades de Fabricación y MRP | D9: El MRP corre con poca frecuencia, las faltas se revisan todas a mano y acaban en compras y transportes urgentes. | E9: Ineficiencia | F9: Fuga de P&L | G9: € de sobrecoste urgente por faltas / mes | H9: Compras y transportes urgentes por faltas (nº/mes) ↓ | I9: (valor-obj)*12*400 | J9: P2R-05 | L9: ✓ | N9: =COUNTIF(K9:M9,"✓") -> 1 | O9: —
A10: HT-P2R-07 | B10: Necesidades poco fiables | C10: Necesidades de Fabricación y MRP | D10: Parámetros desactualizados, producto terminado y semielaborado sin sincronizar y agrupación de lotes a mano. | E10: Ineficiencia | F10: Circulante | G10: € de stock de semielaborado y materia prima por encima de la necesidad | H10: Cobertura de materias primas y semielaborado (días) ↓ | I10: (valor-obj)*8000*0.08 | J10: P2R-05 | L10: ✓ | M10: ✓ | N10: =COUNTIF(K10:M10,"✓") -> 2 | O10: —
A11: HT-P2R-08 | B11: Secuencia sin optimizar | C11: Programación | D11: Se secuencia a mano, sin capacidad finita y con la ruta por defecto. | E11: Ineficiencia | F11: Transformación | G11: Horas de cambio y de sobrecarga / semana | H11: Horas de cambio (h/semana) ↓ | I11: (valor-obj)*52*150 | J11: P2R-06 | K11: ✓ | L11: ✓ | M11: ✓ | N11: =COUNTIF(K11:M11,"✓") -> 3 | O11: —
A12: HT-P2R-09 | B12: Programa inestable | C12: Programación | D12: Sin zona congelada ni reglas de prioridad, las urgencias obligan a resecuenciar. | E12: Ineficiencia | F12: Transformación | G12: Resecuenciaciones / semana | H12: Resecuenciaciones dentro de la zona congelada (nº/semana) ↓ | I12: (valor-obj)*52*0.5*150 | J12: P2R-06 | K12: ✓ | L12: ✓ | M12: ✓ | N12: =COUNTIF(K12:M12,"✓") -> 3 | O12: —
A13: HT-P2R-10 | B13: Liberación sin control | C13: Liberación | D13: Se libera sin confirmar material, utillaje y aprovisionamiento a línea, y sin ventana de liberación. | E13: Ineficiencia | F13: Transformación | G13: Arranques fallidos / mes | H13: Arranques fallidos (nº/mes) ↓ | I13: (valor-obj)*12*2*150 | J13: P2R-07 | M13: ✓ | N13: =COUNTIF(K13:M13,"✓") -> 1 | O13: Ondupack
A14: HT-P2R-11 | B14: Servicio sin control | C14: Seguimiento y Control | D14: No hay KPIs formales de servicio ni de adherencia al programa, y los atrasos se ven cuando ya han ocurrido. | E14: Oportunidad | F14: — | G14: € de pedidos atrasados sin aviso / mes | H14: OTIF a fecha confirmada (%) ↑ | I14: (obj-valor)/100*10000000 | J14: P2R-08 | K14: ✓ | L14: ✓ | M14: ✓ | N14: =COUNTIF(K14:M14,"✓") -> 3 | O14: —
A15: HT-P2R-12 | B15: Ciclo sin aprendizaje | C15: Seguimiento y Control | D15: Las desviaciones no tienen análisis de causa ni vuelven a la previsión ni a los parámetros, y el seguimiento se hace a mano. | E15: Ineficiencia | F15: Transformación | G15: Desviaciones repetidas sin causa / mes | H15: Desviaciones repetidas sin causa (nº/mes) ↓ | I15: (valor-obj)*12*1*150 | J15: P2R-08 | K15: ✓ | M15: ✓ | N15: =COUNTIF(K15:M15,"✓") -> 2 | O15: Ondupack

Sheet Palancas
A1: Catálogo de palancas · P2R
A2: Transcrito de la aplicación el 29/10/2026 (8 palancas). €/año de referencia: vacío (el € sale de cada empresa) · confianza: por cuantificar. «Qué cambia», KPI y base expuesta del maestro.
A4: Código | B4: Palanca | C4: Qué cambia | D4: KPI | E4: Base expuesta | F4: Fase as-is | G4: €/año ref. | H4: Confianza | I4: Cura tipos | J4: Ondupet | K4: Ondupack | L4: MGT | M4: Aplicada en
A5: P2R-01 | B5: Gestión de la demanda | C5: Hay previsión, al menos de la demanda repetitiva; se cierra en fecha, se consensúa cada mes entre Comercial y Planificación, cubre el horizonte de las decisiones y se mide y corrige. | D5: Precisión y sesgo por familia · cambios tras el cierre | E5: € de stock medio de producto terminado expuesto al error de previsión | F5: Demanda y previsión (Forecast to Plan) | G5: — | H5: Por cuantificar | I5: HT-P2R-01 | J5: ✓ | K5: ✓ | L5: ✓ | M5: =COUNTIF(J5:L5,"✓") -> 3
A6: P2R-02 | B6: S&OP y plan de capacidad | C6: Demanda y capacidad se equilibran cada mes, con datos y con dirección: turnos, reservas de capacidad e intercompany se deciden con escenarios, no con urgencias. | D6: Ocupación real frente a planificada · horas extra no planificadas | E6: Horas de línea / año de turnos no ajustados a la carga | F6: S&OP y Plan Maestro (Forecast to Plan) | G6: — | H6: Por cuantificar | I6: HT-P2R-03 | J6: ✓ | K6: ✓ | L6: ✓ | M6: =COUNTIF(J6:L6,"✓") -> 3
A7: P2R-03 | B7: Política de inventario por segmento | C7: Cada material, de producto terminado y de materia prima, tiene segmento, estrategia y stock objetivo, revisados periódicamente. | D7: € de stock fuera de política · roturas | E7: € de stock de producto terminado por encima de la cobertura objetivo | F7: S&OP y Plan Maestro (Forecast to Plan) | G7: — | H7: Por cuantificar | I7: HT-P2R-04, HT-P2R-05 (×2) | J7: ✓ | L7: ✓ | M7: =COUNTIF(J7:L7,"✓") -> 2
A8: P2R-04 | B8: Promesa de fecha fiable | C8: La fecha al cliente se confirma con disponibilidad real y se renegocia en cuanto se sabe que no se llega. | D8: OTIF a fecha confirmada | E8: € de ventas / año en pedidos no entregados en la primera fecha confirmada | F8: S&OP y Plan Maestro (Forecast to Plan) | G8: — | H8: Por cuantificar | I8: HT-P2R-05 (×2) | J8: ✓ | L8: ✓ | M8: =COUNTIF(J8:L8,"✓") -> 2
A9: P2R-05 | B9: Planificación de materiales por excepción | C9: Las necesidades se calculan a tiempo, con parámetros vigentes y en todos los niveles, y el planificador solo atiende las excepciones críticas. | D9: € urgentes por faltas · faltas detectadas a tiempo | E9: € / año de compras y transportes urgentes por faltas · € de stock de materias primas y semielaborado por encima de la cobertura objetivo | F9: Necesidades de Fabricación y MRP | G9: — | H9: Por cuantificar | I9: HT-P2R-06, HT-P2R-07 | K9: ✓ | L9: ✓ | M9: =COUNTIF(J9:L9,"✓") -> 2
A10: P2R-06 | B10: Programación estable y optimizada | C10: El programa respeta la capacidad, minimiza los cambios y solo se modifica dentro de reglas: zona congelada y prioridades. | D10: Horas de cambio · adherencia al programa | E10: Horas de línea / año en cambios y resecuenciaciones evitables | F10: Programación | G10: — | H10: Por cuantificar | I10: HT-P2R-08, HT-P2R-09 | J10: ✓ | K10: ✓ | L10: ✓ | M10: =COUNTIF(J10:L10,"✓") -> 3
A11: P2R-07 | B11: Liberación controlada | C11: Una orden solo se libera con material, utillaje y aprovisionamiento a línea confirmados, y dentro de su ventana. | D11: Arranques fallidos | E11: Horas de línea / año perdidas en arranques fallidos | F11: Liberación | G11: — | H11: Por cuantificar | I11: HT-P2R-10 | L11: ✓ | M11: =COUNTIF(J11:L11,"✓") -> 1
A12: P2R-08 | B12: Control del servicio y mejora continua | C12: Servicio y adherencia se miden solos, los riesgos se avisan antes y cada desviación tiene causa y una acción que vuelve a la planificación. | D12: OTIF · desviaciones con causa | E12: € de ventas / año en pedidos fuera de OTIF · horas de línea / año perdidas en desviaciones repetidas | F12: Seguimiento y Control | G12: — | H12: Por cuantificar | I12: HT-P2R-11, HT-P2R-12 | J12: ✓ | K12: ✓ | L12: ✓ | M12: =COUNTIF(J12:L12,"✓") -> 3

Sheet Ondupet
A1: P2R × Ondupet · hallazgos, palancas e intervenciones
A2: Process owner: celda sin activar. Capacidad liberada que calcula la aplicación: 17,4 k€.
A4: Hallazgos | B4: =SUMPRODUCT((C7:C22<>"")/COUNTIF(C7:C22,C7:C22&"")) -> 9 | C4: Palancas | D4: =COUNTA(A7:A22) -> 6 | E4: Intervenciones | F4: =COUNTA(G7:G22) -> 15 | G4: De ellas, agentes | H4: =COUNTIF(H7:H22,"agente") -> 4 | I4: Capacidad (est.) | J4: =SUM(K7:K22) -> 17403
A6: Palanca | B6: Qué cambia | C6: Hallazgo | D6: Familia · naturaleza | E6: Anclaje (actividad · fase) | F6: Descripción del hallazgo | G6: Intervención | H6: De qué es | I6: Qué hay que hacer | J6: Caja que cambia | K6: Capacidad (est.)
A7: P2R-01 Gestión de la demanda | B7: Hay previsión, al menos de la demanda repetitiva; se cierra en fecha, se consensúa cada mes entre Comercial y Planificación, cubre el horizonte de las decisiones y se mide y corrige. | C7: INF-10 HT-P2R-01 · Demanda sin previsión fiable | D7: Ineficiencia · Circulante | E7: Previsión y Precisión · Demanda y previsión | F7: Previsión inestable: Comercial modifica la previsión a comienzo de mes, incluso con el material ya fabricado, sin comunicación formal ni cierre ni consenso, y nadie responde del stock que queda fabricado. | G7: ACC-01 · Calendario de previsión con día de cierre | H7: negocio | I7: Fijar un día de cierre mensual de la previsión y congelar el mes en curso. Después del cierre, cualquier cambio necesita la aprobación de Planificación y queda registrado con su motivo. Publicar el calendario del año. | J7: no cambia caja | K7: —
C8: INF-16 HT-P2R-01 · Demanda sin previsión fiable | D8: Ineficiencia · Circulante | E8: Previsión y Precisión · Demanda y previsión | F8: Previsión sin medición ni aprendizaje: la reunión mensual de accuracy existe pero no genera acciones, hay desviaciones grandes sin causa ni corrección y los agotados se registran de forma irregular. | G8: ACC-02 · Registro diario de agotados | H8: negocio | I8: Definir qué es un agotado y qué es un pedido rechazado, y registrarlos cada día en el sistema con su motivo, para que el histórico de demanda deje de estar distorsionado. | J8: no cambia caja | K8: —
G9: INT-01 · Análisis de las desviaciones de la demanda | H9: agente | I9: Cada mes analiza las familias fuera de umbral, explica la causa probable (agotado, pedido puntual, cliente nuevo, cambio de Comercial) y propone la corrección de los meses siguientes. Planificación y Comercial la aprueban en la reunión de consenso. | J9: Previsión y Precisión | K9: 903
A10: P2R-02 S&OP y plan de capacidad | B10: Demanda y capacidad se equilibran cada mes, con datos y con dirección: turnos, reservas de capacidad e intercompany se deciden con escenarios, no con urgencias. | C10: INF-11 HT-P2R-03 · Demanda y capacidad sin equilibrar | D10: Ineficiencia · Transformación | E10: Plan Maestro · S&OP y Plan Maestro | F10: Las necesidades se cargan sin comprobar la capacidad de extrusión y termoformado ni balancear entre líneas, y los temporales se calculan a mano. | G10: ACC-03 · Cálculo de % de saturación | H10: software | I10: Al cerrar la previsión, el sistema calcula el % de saturación de cada línea de extrusión y termoformado (previsión × rutas × tiempos de ciclo frente al calendario) y marca las que pasan del umbral. | J10: no cambia caja | K10: —
G11: ACC-04 · Revisión mensual de la capacidad de la planta | H11: negocio | I11: Tras el cierre de la previsión, Planificación presenta la carga frente a la capacidad y la dirección de planta decide turnos y balanceo con umbrales de ocupación acordados. Es el S&OP de planta mientras llega el de grupo. | J11: no cambia caja | K11: —
G12: ACC-05 · Cálculo automático de temporales | H12: software | I12: La reserva de ciclo por familia se calcula sola en cada cierre a partir de la previsión cerrada y los tiempos de ciclo. Planificación solo revisa los cambios en la reunión de consenso. | J12: no cambia caja | K12: —
G13: INT-02 · Propuestas de balanceo | H13: agente | I13: Agente que propone el reparto de turnos y de carga entre las líneas de extrusión y termoformado, con su impacto en horas y €. Planificación lo aprueba en la revisión mensual de capacidad. | J13: Plan Maestro | K13: 6000
A14: P2R-03 Política de inventario por segmento | B14: Cada material, de producto terminado y de materia prima, tiene segmento, estrategia y stock objetivo, revisados periódicamente. | C14: INF-13 HT-P2R-04 · Stock sin política clara | D14: Ineficiencia · Circulante | E14: Plan Maestro · S&OP y Plan Maestro | F14: No se calculan ABC ni estrategias MTS/MTO aunque GIO tiene la transacción, y el stock fabricado por cambios de previsión queda sin dueño. | G14: ACC-06 · Definir criterios ABC / estrategia | H14: negocio | I14: Definir ABC por valor, XYZ por variabilidad y la matriz que asigna a cada segmento MTS o MTO y su stock de seguridad. Comercial valida las estrategias. | J14: no cambia caja | K14: —
C15: OPP-02 HT-P2R-05 · Fecha al cliente no fiable | D15: Oportunidad · — | E15: Plan Maestro · S&OP y Plan Maestro | F15: Se mantiene la fecha del cliente aunque se sabe desde el principio que no se llega, y las dos fechas del pedido no se usan. (también en P2R-04) | G15: ACC-07 · Definir acciones para el stock sin rotación | H15: negocio | I15: Revisión mensual con Comercial del producto terminado sin movimiento: se decide venderlo, reprocesarlo o depreciarlo, y se imputa a quien lo originó cuando viene de un cambio de previsión fuera de plazo. | J15: no cambia caja | K15: —
G16: ACC-08 · Cálculo automático de días de stock | H16: software | I16: El sistema calcula la cobertura en días de stock de cada referencia y avisa de las que superan el objetivo de su segmento, para decidir a tiempo qué se deja de fabricar o se liquida. | J16: no cambia caja | K16: —
A17: P2R-04 Promesa de fecha fiable | B17: La fecha al cliente se confirma con disponibilidad real y se renegocia en cuanto se sabe que no se llega. | C17: OPP-02 HT-P2R-05 · Fecha al cliente no fiable | D17: Oportunidad · — | E17: Plan Maestro · S&OP y Plan Maestro | F17: Se mantiene la fecha del cliente aunque se sabe desde el principio que no se llega, y las dos fechas del pedido no se usan. (también en P2R-03) | G17: ACC-09 · Definir política de fecha confirmada | H17: negocio | I17: Cada pedido lleva fecha solicitada y fecha confirmada. Planificación confirma en un plazo fijo y, si sabe que no se llega, Comercial avisa al cliente con la nueva fecha; el aviso lo ejecuta O2C. | J17: no cambia caja | K17: —
G18: INT-03 · Propuesta de fechas de entrega viables para los pedidos y notas de carga | H18: agente | I18: Agente que calcula una fecha de entrega viable para cada pedido con la capacidad y los temporales, y propone las notas de carga. Comercial confirma la fecha al cliente por O2C. | J18: Plan Maestro | K18: 6000
A19: P2R-06 Programación estable y optimizada | B19: El programa respeta la capacidad, minimiza los cambios y solo se modifica dentro de reglas: zona congelada y prioridades. | C19: INF-12 HT-P2R-08 · Secuencia sin optimizar | D19: Ineficiencia · Transformación | E19: Programación | F19: La secuencia se hace totalmente a mano en GIO, sin optimizar los cambios de molde y altura y con la ruta por defecto sin reequilibrar. | G19: INT-04 · Determinación de urgencias | H19: agente | I19: Ante una petición de cambio, calcula el impacto (qué pedidos se retrasan y cuántos cambios extra supone), aplica las reglas de prioridad y propone la decisión. Si hay conflicto, la escala al árbitro con el impacto calculado. | J19: Programación | K19: 4500
C20: INF-14 HT-P2R-09 · Programa inestable | D20: Ineficiencia · Transformación | E20: Programación | F20: No hay zona congelada: los cambios de última hora llegan por teléfono y las prioridades se resuelven a mano; sin acuerdo, decide el director de planta.
A21: P2R-08 Control del servicio y mejora continua | B21: Servicio y adherencia se miden solos, los riesgos se avisan antes y cada desviación tiene causa y una acción que vuelve a la planificación. | C21: OPP-03 HT-P2R-11 · Servicio sin control | D21: Oportunidad · — | E21: Seguimiento y control · Seguimiento y Control | F21: No se mide el % de cumplimiento del servicio: el reporte diario de cargas atrasadas no es un KPI de OTIF y la fecha pensada para medir retrasos no se usa. | G21: ACC-10 · Análisis de atrasos de entregas | H21: negocio | I21: Cada atraso se clasifica con una lista cerrada de causas (previsión, capacidad, material, secuencia o cambio del cliente). Cada mes se revisan las principales con una acción y un responsable, y lo aprendido vuelve a la previsión o a los parámetros. | J21: no cambia caja | K21: —
C22: INF-15 HT-P2R-12 · Ciclo sin aprendizaje | D22: Ineficiencia · Transformación | E22: Seguimiento y control · Seguimiento y Control | F22: El reporte de atrasos se envía sin análisis de causa y los ajustes se hacen pedido a pedido, sin volver a la previsión ni a los parámetros. | G22: ACC-11 · Informe automático de pedidos / cargas en riesgo | H22: software | I22: Informe automático diario de los pedidos y cargas en riesgo de llegar tarde: sustituye al reporte manual de cargas atrasadas y avisa a Comercial antes de que ocurra el atraso. | J22: no cambia caja | K22: —
A24: Notas
A25: · INF-10 e INF-16 son del mismo tipo (HT-P2R-01) desde que se agruparon los de previsión: conviene fusionarlos para no contar dos veces su valor.
A26: · OPP-02 cuelga de P2R-03 y de P2R-04 (aviso ⚠ en la aplicación); lo cura P2R-04, así que se puede quitar de P2R-03.
A27: · En la aplicación la descripción de cada hallazgo es solo el nombre del tipo; aquí van las descripciones acordadas, para copiarlas.

Sheet MGT
A1: P2R × MGT · hallazgos, palancas e intervenciones
A2: Process owner: celda sin activar. La capacidad de los agentes sale a 0 € porque la celda aún no tiene dedicación de personas por fase.
A4: Hallazgos | B4: =SUMPRODUCT((C7:C23<>"")/COUNTIF(C7:C23,C7:C23&"")) -> 10 | C4: Palancas | D4: =COUNTA(A7:A23) -> 8 | E4: Intervenciones | F4: =COUNTA(G7:G23) -> 17 | G4: De ellas, agentes | H4: =COUNTIF(H7:H23,"agente") -> 6 | I4: Capacidad (est.) | J4: =SUM(K7:K23) -> 0
A6: Palanca | B6: Qué cambia | C6: Hallazgo | D6: Familia · naturaleza | E6: Anclaje (actividad · fase) | F6: Descripción del hallazgo | G6: Intervención | H6: De qué es | I6: Qué hay que hacer | J6: Caja que cambia | K6: Capacidad (est.)
A7: P2R-01 Gestión de la demanda | B7: Hay previsión, al menos de la demanda repetitiva; se cierra en fecha, se consensúa cada mes entre Comercial y Planificación, cubre el horizonte de las decisiones y se mide y corrige. | C7: INF-01 HT-P2R-01 · Demanda sin previsión fiable | D7: Oportunidad · — | E7: Demanda Intercompany · Demanda y previsión | F7: No hay previsión de ningún tipo, ni externa ni intercompany: se planifica solo con la cartera, y no se sabe si se registran las ventas perdidas. | G7: ACC-01 · Previsión de papel de Ondupack | H7: negocio | I7: Acordar con Ondupack que, en cada ciclo, envíe la previsión de papel de los ciclos siguientes por calidad y ancho, además del pedido firme 10 días antes. Es la otra mitad de la intervención «Previsión de papel compartida con MGT/PDA» de Ondupack. | J7: no cambia caja | K7: —
G8: ACC-02 · Previsión de los clientes externos repetitivos | H8: negocio | I8: Identificar con Comercial los clientes externos con consumo repetitivo y acordar con ellos una previsión no vinculante por calidad y ancho, revisada en cada ciclo. | J8: no cambia caja | K8: —
A9: P2R-02 S&OP y plan de capacidad | B9: Demanda y capacidad se equilibran cada mes, con datos y con dirección: turnos, reservas de capacidad e intercompany se deciden con escenarios, no con urgencias. | C9: INF-02 HT-P2R-03 · Demanda y capacidad sin equilibrar | D9: Ineficiencia · Transformación | E9: Carga de Capacidad · S&OP y Plan Maestro | F9: Los pedidos se cargan a capacidad infinita y la máquina trabaja siempre a 3 turnos a velocidad máxima; la duración de cada calidad en el ciclo se ajusta sobre la marcha, sin propuesta. | G9: ACC-03 · Política de llenado de capacidad | H9: negocio | I9: Decidir con Dirección qué se fabrica cuando sobra capacidad (referencias repetitivas con mínimo y máximo, sobre todo las de Ondupack) y cuándo compensa parar, comparando el coste de parada con el coste del stock. Sustituye a la regla de «3 turnos siempre». | J9: no cambia caja | K9: —
G10: ACC-04 · Revisión mensual de capacidad y ciclos | H10: negocio | I10: Reunión mensual de Joan Carles con Comercial (Albert) y Dirección: carga frente a capacidad de los próximos ciclos, duración de cada calidad y pedidos que no caben. | J10: no cambia caja | K10: —
G11: INT-01 · Agente de escenarios de ciclo | H11: agente | I11: Simula alternativas de duración y orden de las calidades, paradas y stock, y propone el ciclo con su impacto en coste y servicio. Planificación lo aprueba en la revisión mensual. | J11: Carga de Capacidad | K11: 0
A12: P2R-03 Política de inventario por segmento | B12: Cada material, de producto terminado y de materia prima, tiene segmento, estrategia y stock objetivo, revisados periódicamente. | C12: INF-03 HT-P2R-04 · Stock sin política clara | D12: Ineficiencia · Circulante | E12: Plan Fabricación · S&OP y Plan Maestro | F12: Se acumula stock de Ondupack en MGT, que lo va retirando poco a poco; lo fabricado de más no se ajusta en el pedido y las 3 turnos generan stock aunque todo se fabrica bajo pedido. | G12: ACC-05 · Pull system con Ondupack, con mínimo y máximo por referencia | H12: negocio | I12: Definir con Ondupack qué referencias se reponen por pull, con un mínimo y un máximo en MGT. Ondupack retira cada día de ese stock y MGT lo repone al combinar sus ciclos. | J12: no cambia caja | K12: —
C13: OPP-02 HT-P2R-05 · Fecha al cliente no fiable | D13: Oportunidad · — | E13: Plan Fabricación · S&OP y Plan Maestro | F13: Al entrar el pedido no se propone fecha porque la planificación no está integrada con Comercial, y las fechas de Ondupack no son fiables: marcan el inicio del ciclo y después cambian. (también en P2R-04) | G13: INT-02 · Agente de stock intercompany | H13: agente | I13: Cada mes revisa la cobertura de las referencias de Ondupack en MGT, propone ajustar mínimos y máximos y avisa del stock que se queda sin salida. | J13: Plan Fabricación | K13: 0
A14: P2R-04 Promesa de fecha fiable | B14: La fecha al cliente se confirma con disponibilidad real y se renegocia en cuanto se sabe que no se llega. | C14: OPP-02 HT-P2R-05 · Fecha al cliente no fiable | D14: Oportunidad · — | E14: Plan Fabricación · S&OP y Plan Maestro | F14: Al entrar el pedido no se propone fecha porque la planificación no está integrada con Comercial, y las fechas de Ondupack no son fiables: marcan el inicio del ciclo y después cambian. (también en P2R-03) | G14: INT-04 · Copiloto de plazos para Comercial | H14: agente | I14: Comercial pregunta «¿cuándo sale la próxima tirada de esta calidad y ancho?» y el copiloto responde con el plan de ciclos y la capacidad libre, sin llamar a Planificación. | J14: Demanda Externa | K14: 0
A15: P2R-05 Planificación de materiales por excepción | B15: Las necesidades se calculan a tiempo, con parámetros vigentes y en todos los niveles, y el planificador solo atiende las excepciones críticas. | C15: INF-04 HT-P2R-07 · Necesidades poco fiables | D15: Ineficiencia · Circulante | E15: Propuesta de Fabricación · Necesidades de Fabricación y MRP | F15: El MRP de materias primas se hace en un Excel; el de auxiliares, en SAP, se descuadra porque la entrada de báscula se registra después del consumo, y no se sabe cómo se planifica la bobina madre. | G15: ACC-06 · MRP de materias primas en SAP | H15: software | I15: Pasar el MRP de materias primas del Excel a SAP, como ya se hace con los auxiliares, alimentado con el plan de ciclos y con lead time, lote mínimo y stock de seguridad completos. | J15: no cambia caja | K15: —
G16: INT-03 · Agente de compras de materiales | H16: agente | I16: Revisa cada día los mensajes del MRP, propone las solicitudes de compra y avisa cuando el consumo se separa del plan. Marta Boyo y Joan Carles aprueban; el pedido sigue en P2P. | J16: MRP | K16: 0
A17: P2R-06 Programación estable y optimizada | B17: El programa respeta la capacidad, minimiza los cambios y solo se modifica dentro de reglas: zona congelada y prioridades. | C17: INF-05 HT-P2R-08 · Secuencia sin optimizar | D17: Ineficiencia · Transformación | E17: Programación | F17: El algoritmo de combinación no tiene en cuenta lo ya fabricado ni hay fecha límite de cartera, y la agrupación por calidad y ancho es manual salvo que se use su salida. | G17: ACC-07 · Algoritmo con lo ya fabricado y fecha límite de cartera | H17: software | I17: El algoritmo tiene en cuenta lo ya fabricado y el stock pull, y una fecha límite de cartera por ciclo. Su salida pasa a ser el estándar y la agrupación manual por calidad y ancho desaparece. | J17: no cambia caja | K17: —
C18: INF-06 HT-P2R-09 · Programa inestable | D18: Ineficiencia · Transformación | E18: Programación | F18: Las urgencias, también las de Ondupack fuera del plazo de 10 días, se encajan a mano, sin alertas ni zona congelada, y las prioridades se negocian caso a caso. | G18: INT-05 · Agente de urgencias | H18: agente | I18: Ante una urgencia, comprueba si cabe en el ciclo y qué pedidos y combinaciones se ven afectados, aplica las reglas y propone la decisión. Si hay conflicto, la escala con el impacto calculado. | J18: Programación | K18: 0
A19: P2R-07 Liberación controlada | B19: Una orden solo se libera con material, utillaje y aprovisionamiento a línea confirmados, y dentro de su ventana. | C19: INF-08 HT-P2R-10 · Liberación sin control | D19: Ineficiencia · Transformación | E19: Liberación de la Orden · Liberación | F19: No hay faltas por orden: el planificador comprueba a mano, en varios sitios, que hay material, sin ver cuándo llega, y la orden se entrega impresa en papel. | G19: ACC-11 · Disponibilidad de material por orden | H19: software | I19: El sistema muestra en cada orden si el material está y cuándo llega, a partir del MRP y de los pedidos de compra. Sustituye la comprobación manual en varios sitios. | J19: no cambia caja | K19: —
A20: P2R-08 Control del servicio y mejora continua | B20: Servicio y adherencia se miden solos, los riesgos se avisan antes y cada desviación tiene causa y una acción que vuelve a la planificación. | C20: OPP-03 HT-P2R-11 · Servicio sin control | D20: Oportunidad · — | E20: Seguimiento del servicio · Seguimiento y Control | F20: No hay pilar de servicio ni KPI: las incidencias se resuelven por llamada y la coordinación de entregas con Ondupack lleva unos 16 correos al día. | G20: ACC-08 · Pilar de servicio semanal | H20: negocio | I20: Reunión semanal fija entre MGT, Ondupack y Comercial: servicio, pedidos pendientes, atrasos y sus causas, y restos de pedidos antiguos por cerrar. | J20: no cambia caja | K20: —
C21: INF-07 HT-P2R-12 · Ciclo sin aprendizaje | D21: Ineficiencia · Transformación | E21: Seguimiento del servicio · Seguimiento y Control | F21: No se analizan desviaciones ni atrasos y las incidencias no dejan causa registrada. | G21: ACC-09 · KPI de servicio | H21: negocio | I21: Definir el OTIF contra fecha confirmada para clientes externos y para Ondupack, y publicarlo cada semana. | J21: no cambia caja | K21: —
G22: ACC-10 · Visibilidad de stock y cargas para Ondupack | H22: software | I22: Ondupack ve en línea el stock de MGT y la producción prevista, y pide las cargas desde ahí, en lugar de los unos 16 correos diarios. La carga la sigue ejecutando T2D. | J22: no cambia caja | K22: —
G23: INT-06 · Agente de coordinación de cargas con Ondupack | H23: agente | I23: Lee las peticiones de Ondupack, comprueba stock y plan, y propone la carga del día siguiente dentro del mínimo y máximo acordados. Joan Carles aprueba. | J23: Entregas a Ondupack y Cierre | K23: 0
A25: Notas
A26: · OPP-02 cuelga de P2R-03 y de P2R-04 (aviso ⚠ en P2R-03); lo cura P2R-04, así que se puede quitar de P2R-03.
A27: · P2R-05 no cura HT-P2R-06 en MGT (no está asignado), solo HT-P2R-07.
A28: · P2R-04 solo tiene el copiloto de plazos: sin la «Fecha confirmada por Planificación» (negocio) nada cambia cómo se promete la fecha, que es lo que describe OPP-02.
A29: · INF-08 menciona las órdenes impresas en papel, pero P2R-07 no tiene la «Orden digital a producción»; y el descuadre de báscula de INF-04 depende del proceso de inventario.
A30: · En la aplicación la descripción de cada hallazgo es solo el nombre del tipo; aquí van las descripciones acordadas, para copiarlas.

Sheet Ondupack Almendralejo
A1: P2R × Ondupack Almendralejo · hallazgos, palancas e intervenciones
A2: Process owner: Enrique Tejada. La capacidad de los agentes sale a 0 € porque la celda aún no tiene dedicación de personas por fase.
A4: Hallazgos | B4: =SUMPRODUCT((C7:C20<>"")/COUNTIF(C7:C20,C7:C20&"")) -> 7 | C4: Palancas | D4: =COUNTA(A7:A20) -> 5 | E4: Intervenciones | F4: =COUNTA(G7:G20) -> 14 | G4: De ellas, agentes | H4: =COUNTIF(H7:H20,"agente") -> 4 | I4: Capacidad (est.) | J4: =SUM(K7:K20) -> 0
A6: Palanca | B6: Qué cambia | C6: Hallazgo | D6: Familia · naturaleza | E6: Anclaje (actividad · fase) | F6: Descripción del hallazgo | G6: Intervención | H6: De qué es | I6: Qué hay que hacer | J6: Caja que cambia | K6: Capacidad (est.)
A7: P2R-01 Gestión de la demanda | B7: Hay previsión, al menos de la demanda repetitiva; se cierra en fecha, se consensúa cada mes entre Comercial y Planificación, cubre el horizonte de las decisiones y se mide y corrige. | C7: INF-01 HT-P2R-01 · Demanda sin previsión fiable | D7: Ineficiencia · Circulante | E7: Entrada de Pedidos y Fecha · Demanda y previsión | F7: No se usa previsión aunque hay clientes con consumo repetitivo, no se sabe qué parte de la demanda es de pedido firme, de stock o intercompany, y la demanda perdida no se registra en el sistema. | G7: ACC-01 · Integración de las referencias/clientes que vayan por previsión en GIO | H7: negocio | I7: Identificar con Comercial los clientes y referencias con consumo repetitivo, acordar con ellos una previsión no vinculante y cargarla en GIO para que la carga-capacidad y el CTP la tengan en cuenta. | J7: no cambia caja | K7: —
G8: ACC-02 · Registro de la demanda perdida en GIO | H8: software | I8: Cuando el cliente no acepta la fecha que propone el CTP, reduce la cantidad o se rechaza un pedido por capacidad, GIO obliga a registrar el motivo. | J8: no cambia caja | K8: —
A9: P2R-02 S&OP y plan de capacidad | B9: Demanda y capacidad se equilibran cada mes, con datos y con dirección: turnos, reservas de capacidad e intercompany se deciden con escenarios, no con urgencias. | C9: INF-06 HT-P2R-03 · Demanda y capacidad sin equilibrar | D9: Ineficiencia · Transformación | E9: Carga Capacidad · S&OP y Plan Maestro | F9: La 924 no alcanza los metros planificados y arrastra pedidos lanzados. La sobresaturación se detecta tarde: por las fechas de entrega o porque se llena el almacén intermedio. | G9: ACC-03 · Revisión mensual de capacidad y cuellos de botella | H9: negocio | I9: Reunión mensual Planificación–Producción–Comercial con la carga de los próximos 2–3 meses por máquina: decide turnos con los escenarios de 2 a 5, qué entra en la 924 y qué se desvía por ruta alternativa. | J9: no cambia caja | K9: —
G10: INT-01 · Agente de escenarios de capacidad | H10: agente | I10: Simula turnos, rutas alternativas para descargar la 924 y agrupaciones, y propone el plan con su impacto en servicio y coste. Planificación lo aprueba en la revisión mensual. | J10: Carga Capacidad | K10: 0
A11: P2R-05 Planificación de materiales por excepción | B11: Las necesidades se calculan a tiempo, con parámetros vigentes y en todos los niveles, y el planificador solo atiende las excepciones críticas. | C11: INF-02 HT-P2R-06 · Faltas tardías y gestionadas a mano | D11: Ineficiencia · Fuga de P&L | E11: Papel y Auxiliares · Necesidades de Fabricación y MRP | F11: La falta de materia prima es su primer problema. El papel se pide por consumo pasado y los auxiliares se reponen a mano; no hay MRP ni aviso de faltas por orden, y GIO solo ve el stock de papel. | G11: ACC-04 · Necesidad de papel calculada desde el plan | H11: software | I11: Calcular cada día la necesidad neta de papel a partir de la cartera planificada, la previsión y la lista de materiales, en lugar del consumo pasado, y avisar de las faltas por orden y por fecha. | J11: no cambia caja | K11: —
C12: INF-03 HT-P2R-07 · Necesidades poco fiables | D12: Ineficiencia · Circulante | E12: Papel y Auxiliares · Necesidades de Fabricación y MRP | F12: La necesidad de papel no sale del plan, sale del histórico. Las sustituciones se hacen a mano, los consumos se dan por diferencia de inventario cada mes y el maestro está incompleto (sin lote mínimo ni calendario). | G12: ACC-05 · Stock de papel fiable sin esperar al inventario mensual | H12: software | I12: Declarar el consumo real de papel por orden, que ya se puede trazar en GPO, en lugar de calcularlo por diferencia en el inventario mensual. El registro lo hace el proceso de inventario; aquí se usa. | J12: no cambia caja | K12: —
G13: ACC-06 · Previsión de papel compartida con MGT/PDA/PAPRESA | H13: negocio | I13: En cada ciclo, Ondupack envía a MGT, PDA y Papresa la previsión de papel de los próximos ciclos por calidad y ancho, además del pedido firme 10 días antes. El pedido sigue yendo por P2P. | J13: no cambia caja | K13: —
G14: ACC-07 · Faltas de materia prima | H14: agente | I14: Cada día revisa las faltas por orden, propone la acción (adelantar el pedido a MGT, usar un sustituto aprobado o mover la orden) y prepara el aviso a Compras. Planificación aprueba. | J14: no cambia caja | K14: —
A15: P2R-06 Programación estable y optimizada | B15: El programa respeta la capacidad, minimiza los cambios y solo se modifica dentro de reglas: zona congelada y prioridades. | C15: INF-04 HT-P2R-08 · Secuencia sin optimizar | D15: Ineficiencia · Transformación | E15: Onduladora · Programación | F15: La combinación de onduladora y la secuencia de converting no se optimizan; la optimización está aplazada hasta estabilizar los datos. Se repiten maestros fabricados en la misma semana. | G15: ACC-11 · Algoritmo de combinación | H15: software | I15: Propone las combinaciones por canal minimizando trim y cambios, y agrupa las referencias que hoy se repiten en la misma semana. El planificador las revisa y aprueba. Ya está en el plan de sistemas. | J15: no cambia caja | K15: —
C16: INF-05 HT-P2R-09 · Programa inestable | D16: Ineficiencia · Transformación | E16: Onduladora · Programación | F16: No hay zona congelada: los cambios del cliente se aceptan por email mientras el pedido no esté fabricado, las urgencias se resuelven llamando y no se registra la causa de las reprogramaciones. | G16: INT-03 · Agente de urgencias y cambios | H16: agente | I16: Ante un cambio del cliente o una urgencia, calcula el impacto (pedidos desplazados, cambios extra y saturación del almacén intermedio), aplica el criterio de urgencia y propone la decisión; si hay conflicto, la escala. | J16: Converting | K16: 0
A17: P2R-08 Control del servicio y mejora continua | B17: Servicio y adherencia se miden solos, los riesgos se avisan antes y cada desviación tiene causa y una acción que vuelve a la planificación. | C17: OPP-01 HT-P2R-11 · Servicio sin control | D17: Oportunidad · — | E17: Revisión Semanal · Seguimiento y Control | F17: Falta un KPI oficial de servicio: Dirección y Comercial todavía no han decidido cuál usar ni contra qué fecha medirlo. | G17: ACC-08 · KPI oficial de servicio | H17: negocio | I17: Que Dirección y Comercial decidan el KPI oficial (recomendado: OTIF contra fecha confirmada por el CTP, pedido completo) y su objetivo, y publicarlo cada semana. | J17: no cambia caja | K17: —
G18: ACC-09 · Reunión semanal con KPIs y causas | H18: negocio | I18: La reunión semanal de planificación Ondupack/Navalmoral incorpora el OTIF, la adherencia y las principales causas de atraso y de reprogramación, cada una con su acción y su responsable. | J18: no cambia caja | K18: —
G19: ACC-10 · Copiloto de estado de pedidos | H19: software | I19: Responde a Call center y a Comercial «¿cuándo sale el pedido X?» y «¿por qué va tarde?» con los datos de GIO, sin cambiar nada. | J19: no cambia caja | K19: —
G20: INT-02 · Agente de causa raíz | H20: agente | I20: Clasifica cada atraso y desviación (velocidad, OEE, falta de papel, cambio del cliente o saturación), propone la acción y el ajuste de parámetros. Planificación aprueba. | J20: Seguimiento del Servicio | K20: 0
A22: Notas
A23: · El tipo HT-P2R-01 es ahora Oportunidad, pero INF-01 sigue como Ineficiencia · Circulante (igual que INF-10 e INF-16 en Ondupet).
A24: · ACC-07 es un agente que no cambia ninguna caja: si se marca sobre «Autorizar la liberación con material pendiente», aparecerá en el to-be y tendrá capacidad.
A25: · HT-P2R-12 no está asignado en esta celda, así que P2R-08 solo cura OPP-01.

Sheet Fichas de hallazgo
A1: Fichas de hallazgo por empresa · campos del formulario (sin cuantificación)
A2: Detectado en: «aquí mismo» en todos. La métrica es el volumen expuesto que hoy se puede medir en cada empresa (sustituye a la heredada del tipo antiguo). Esfuerzo e impacto de 1 (bajo) a 5 (alto), como en la aplicación. La última columna dice qué hay que cambiar en la aplicación.
A4: Empresa | B4: ID | C4: Tipo de hallazgo | D4: Familia | E4: Naturaleza | F4: Anclaje (bloque) | G4: Fase | H4: Descripción | I4: Métrica (volumen expuesto) | J4: Esfuerzo | K4: Impacto | L4: Qué cambiar en la aplicación
A5: Ondupet | B5: INF-10 | C5: HT-P2R-01 · Demanda sin previsión fiable | D5: Ineficiencia | E5: Circulante | F5: Previsión y Precisión | G5: Demanda y previsión | H5: Comercial modifica la previsión a comienzo de mes, incluso con el material ya fabricado, sin comunicación formal ni cierre ni consenso, y nadie responde del stock fabricado. Además, la reunión de accuracy no genera acciones y los agotados se registran de forma irregular. | I5: € / mes de previsión cambiada tras el inicio del mes o sin consensuar | J5: 2 | K5: 5 | L5: Pegar esta descripción, que ya incluye INF-16.
A6: Ondupet | B6: INF-16 | C6: HT-P2R-01 · Demanda sin previsión fiable | D6: Ineficiencia | E6: Circulante | F6: Previsión y Precisión | G6: Demanda y previsión | J6: — | K6: — | L6: Fusionar en INF-10 y desactivar en Ondupet: es el mismo tipo.
A7: Ondupet | B7: INF-11 | C7: HT-P2R-03 · Demanda y capacidad sin equilibrar | D7: Ineficiencia | E7: Transformación | F7: Plan Maestro | G7: S&OP y Plan Maestro | H7: Las necesidades se cargan sin comprobar la capacidad de extrusión y termoformado ni balancear entre líneas, y los temporales se calculan a mano. | I7: Horas de línea / año de extrusión y termoformado planificadas sin cruzar carga y capacidad | J7: 3 | K7: 4
A8: Ondupet | B8: INF-13 | C8: HT-P2R-04 · Stock sin política clara | D8: Ineficiencia | E8: Circulante | F8: Plan Maestro | G8: S&OP y Plan Maestro | H8: No se calculan ABC ni estrategias MTS/MTO aunque GIO tiene la transacción, y el stock fabricado por cambios de previsión queda sin dueño. | I8: € de stock medio de producto terminado sin ABC ni estrategia | J8: 2 | K8: 3
A9: Ondupet | B9: OPP-02 | C9: HT-P2R-05 · Fecha al cliente no fiable | D9: Oportunidad | E9: — | F9: Plan Maestro | G9: S&OP y Plan Maestro | H9: Se mantiene la fecha del cliente aunque se sabe desde el principio que no se llega, y las dos fechas del pedido no se usan. | I9: € de ventas / año en pedidos entregados después de la fecha del cliente | J9: 3 | K9: 4
A10: Ondupet | B10: INF-12 | C10: HT-P2R-08 · Secuencia sin optimizar | D10: Ineficiencia | E10: Transformación | F10: Programación | G10: Programación | H10: La secuencia se hace totalmente a mano en GIO, sin optimizar los cambios de molde y altura y con la ruta por defecto sin reequilibrar. | I10: Horas de línea / año en cambios de molde y altura | J10: 5 | K10: 4
A11: Ondupet | B11: INF-14 | C11: HT-P2R-09 · Programa inestable | D11: Ineficiencia | E11: Transformación | F11: Programación | G11: Programación | H11: No hay zona congelada: los cambios de última hora llegan por teléfono y las prioridades se resuelven a mano; sin acuerdo, decide el director de planta. | I11: Cambios de última hora / año dentro del programa | J11: 1 | K11: 3
A12: Ondupet | B12: OPP-03 | C12: HT-P2R-11 · Servicio sin control | D12: Oportunidad | E12: — | F12: Seguimiento y control | G12: Seguimiento y Control | H12: No se mide el % de cumplimiento del servicio: el reporte diario de cargas atrasadas no es un KPI de OTIF y la fecha pensada para medir retrasos no se usa. | I12: € de ventas / año en pedidos atrasados (reporte diario de cargas atrasadas) | J12: 2 | K12: 3
A13: Ondupet | B13: INF-15 | C13: HT-P2R-12 · Ciclo sin aprendizaje | D13: Ineficiencia | E13: Transformación | F13: Seguimiento y control | G13: Seguimiento y Control | H13: El reporte de atrasos se envía sin análisis de causa y los ajustes se hacen pedido a pedido, sin volver a la previsión ni a los parámetros. | I13: Atrasos / año sin análisis de causa | J13: 1 | K13: 2
A14: MGT | B14: INF-01 | C14: HT-P2R-01 · Demanda sin previsión fiable | D14: Ineficiencia | E14: Circulante | F14: Demanda Intercompany | G14: Demanda y previsión | H14: No hay previsión de ningún tipo, ni externa ni intercompany: se planifica solo con la cartera, y no se sabe si se registran las ventas perdidas. | I14: t / año de papel (Ondupack y clientes repetitivos) planificadas sin previsión | J14: 3 | K14: 4 | L14: Cambiar la familia a Ineficiencia · Circulante, como el tipo.
A15: MGT | B15: INF-02 | C15: HT-P2R-03 · Demanda y capacidad sin equilibrar | D15: Ineficiencia | E15: Transformación | F15: Carga de Capacidad | G15: S&OP y Plan Maestro | H15: Los pedidos se cargan a capacidad infinita y la máquina trabaja siempre a 3 turnos a velocidad máxima; la duración de cada calidad en el ciclo se ajusta sobre la marcha, sin propuesta. | I15: Horas / año de máquina a 3 turnos sin cartera que los llene | J15: 3 | K15: 4
A16: MGT | B16: INF-03 | C16: HT-P2R-04 · Stock sin política clara | D16: Ineficiencia | E16: Circulante | F16: Plan Fabricación | G16: S&OP y Plan Maestro | H16: Se acumula stock de Ondupack en MGT, que lo va retirando poco a poco; lo fabricado de más no se ajusta en el pedido y las 3 turnos generan stock aunque todo se fabrica bajo pedido. | I16: € de stock de Ondupack en MGT | J16: 3 | K16: 5
A17: MGT | B17: OPP-02 | C17: HT-P2R-05 · Fecha al cliente no fiable | D17: Oportunidad | E17: — | F17: Demanda Externa | G17: Demanda y previsión | H17: Al entrar el pedido no se propone fecha porque la planificación no está integrada con Comercial, y las fechas de Ondupack no son fiables: marcan el inicio del ciclo y después cambian. | I17: € de ventas / año en pedidos entregados después de la fecha pedida por el cliente | J17: 4 | K17: 3 | L17: Cambiar el anclaje a Demanda Externa: es donde se da (o no) la fecha.
A18: MGT | B18: INF-04 | C18: HT-P2R-07 · Necesidades poco fiables | D18: Ineficiencia | E18: Circulante | F18: MRP | G18: Necesidades de Fabricación y MRP | H18: El MRP de materias primas se hace en un Excel; el de auxiliares, en SAP, se descuadra porque la entrada de báscula se registra después del consumo, y no se sabe cómo se planifica la bobina madre. | I18: € de stock medio de materias primas y auxiliares | J18: 3 | K18: 3 | L18: Cambiar el anclaje a MRP: el problema es el MRP, no la propuesta de PT.
A19: MGT | B19: INF-05 | C19: HT-P2R-08 · Secuencia sin optimizar | D19: Ineficiencia | E19: Transformación | F19: Programación | G19: Programación | H19: El algoritmo de combinación no tiene en cuenta lo ya fabricado ni hay fecha límite de cartera, y la agrupación por calidad y ancho es manual salvo que se use su salida. | I19: Horas / año de máquina en cambios de calidad y ancho | J19: 3 | K19: 4
A20: MGT | B20: INF-06 | C20: HT-P2R-09 · Programa inestable | D20: Ineficiencia | E20: Transformación | F20: Programación | G20: Programación | H20: Las urgencias, también las de Ondupack fuera del plazo de 10 días, se encajan a mano, sin alertas ni zona congelada, y las prioridades se negocian caso a caso. | I20: Urgencias / año encajadas a mano en el ciclo | J20: 1 | K20: 3
A21: MGT | B21: INF-08 | C21: HT-P2R-10 · Liberación sin control | D21: Ineficiencia | E21: Transformación | F21: Liberación de la Orden | G21: Liberación | H21: No hay faltas por orden: el planificador comprueba a mano, en varios sitios, que hay material, sin ver cuándo llega, y la orden se entrega impresa en papel. | I21: Órdenes / año liberadas con comprobación manual de material | J21: 3 | K21: 2
A22: MGT | B22: OPP-03 | C22: HT-P2R-11 · Servicio sin control | D22: Oportunidad | E22: — | F22: Seguimiento del servicio | G22: Seguimiento y Control | H22: No hay pilar de servicio ni KPI: las incidencias se resuelven por llamada y la coordinación de entregas con Ondupack lleva unos 16 correos al día. | I22: € de ventas / año en pedidos entregados tarde (incluido Ondupack) | J22: 3 | K22: 3
A23: MGT | B23: INF-07 | C23: HT-P2R-12 · Ciclo sin aprendizaje | D23: Ineficiencia | E23: Transformación | F23: Seguimiento del servicio | G23: Seguimiento y Control | H23: No se analizan desviaciones ni atrasos y las incidencias no dejan causa registrada. | I23: Incidencias / año resueltas sin causa registrada | J23: 1 | K23: 2
A24: Ondupack Almendralejo | B24: INF-01 | C24: HT-P2R-01 · Demanda sin previsión fiable | D24: Ineficiencia | E24: Circulante | F24: Entrada de Pedidos y Fecha | G24: Demanda y previsión | H24: No se usa previsión aunque hay clientes con consumo repetitivo, no se sabe qué parte de la demanda es de pedido firme, de stock o intercompany, y la demanda perdida no se registra en el sistema. | I24: € de ventas / año de clientes y referencias repetitivas planificadas sin previsión | J24: 3 | K24: 3
A25: Ondupack Almendralejo | B25: INF-06 | C25: HT-P2R-03 · Demanda y capacidad sin equilibrar | D25: Ineficiencia | E25: Transformación | F25: Carga Capacidad | G25: S&OP y Plan Maestro | H25: La 924 no alcanza los metros planificados y arrastra pedidos lanzados. La sobresaturación se detecta tarde: por las fechas de entrega o porque se llena el almacén intermedio. | I25: Horas / año de la 924 planificadas por encima de lo que produce | J25: 2 | K25: 5
A26: Ondupack Almendralejo | B26: INF-02 | C26: HT-P2R-06 · Faltas tardías y gestionadas a mano | D26: Ineficiencia | E26: Fuga de P&L | F26: Papel y Auxiliares | G26: Necesidades de Fabricación y MRP | H26: La falta de materia prima es su primer problema. El papel se pide por consumo pasado y los auxiliares se reponen a mano; no hay MRP ni aviso de faltas por orden, y GIO solo ve el stock de papel. | I26: Órdenes / año liberadas con material pendiente | J26: 4 | K26: 5
A27: Ondupack Almendralejo | B27: INF-03 | C27: HT-P2R-07 · Necesidades poco fiables | D27: Ineficiencia | E27: Circulante | F27: Papel y Auxiliares | G27: Necesidades de Fabricación y MRP | H27: La necesidad de papel no sale del plan, sale del histórico. Las sustituciones se hacen a mano, los consumos se dan por diferencia de inventario cada mes y el maestro está incompleto (sin lote mínimo ni calendario). | I27: € de stock medio de papel | J27: 4 | K27: 3
A28: Ondupack Almendralejo | B28: INF-04 | C28: HT-P2R-08 · Secuencia sin optimizar | D28: Ineficiencia | E28: Transformación | F28: Onduladora | G28: Programación | H28: La combinación de onduladora y la secuencia de converting no se optimizan; la optimización está aplazada hasta estabilizar los datos. Se repiten maestros fabricados en la misma semana. | I28: Horas / año de onduladora y converting en cambios | J28: 4 | K28: 4
A29: Ondupack Almendralejo | B29: INF-05 | C29: HT-P2R-09 · Programa inestable | D29: Ineficiencia | E29: Transformación | F29: Converting | G29: Programación | H29: No hay zona congelada: los cambios del cliente se aceptan por email mientras el pedido no esté fabricado, las urgencias se resuelven llamando y no se registra la causa de las reprogramaciones. | I29: Cambios del cliente / año aceptados con el pedido ya programado | J29: 1 | K29: 3 | L29: Cambiar el anclaje a Converting: es donde se replanifica.
A30: Ondupack Almendralejo | B30: OPP-01 | C30: HT-P2R-11 · Servicio sin control | D30: Oportunidad | E30: — | F30: Seguimiento del servicio | G30: Seguimiento y Control | H30: Falta un KPI oficial de servicio: Dirección y Comercial todavía no han decidido cuál usar ni contra qué fecha medirlo. | I30: € de ventas / año en pedidos entregados después de la fecha propuesta por el CTP | J30: 1 | K30: 3 | L30: Cambiar el anclaje a Seguimiento del servicio: es donde falta el KPI.

Sheet Fichas de palanca
A1: Fichas de palanca por empresa · pestaña «Definición»
A2: El compromiso de valor (€ P&L, working capital) se deja para la cuantificación: confianza «por cuantificar» y estado «identificada». La ventana se calcula con las fechas de sus intervenciones.
A4: Empresa | B4: Palanca | C4: Nombre | D4: Qué ataca: líneas (tipo · hallazgo) | E4: Horas de personas (caja · quién · horas/año hoy) | F4: Responsable de la palanca | G4: Equipo de apoyo | H4: Ventana: desde | I4: Ventana: hasta | J4: Contador | K4: Proyecto | L4: Qué cambiar en la aplicación
A5: Ondupet | B5: P2R-01 | C5: Gestión de la demanda | D5: Circulante · INF-10 | E5: Previsión y Precisión · Victoriano Pérez · 86 h/año (5 % en Demanda y previsión); INT-01 le quita ≈ 26 h | F5: Manuel Jesús Trinidad Montero | G5: Victoriano Pérez Carrasco · Monica Gordillo Guerrero | H5: =MIN(IF(COUNTIFS('Interv. negocio y software'!$A$5:$A$36,$A5,'Interv. negocio y software'!$E$5:$E$36,$B5)>0,_xlfn.MINIFS('Interv. negocio y software'!$H$5:$H$36,'Interv. negocio y software'!$A$5:$A$36,$A5,'Interv. negocio y software'!$E$5:$E$36,$B5),2958465),IF(COUNTIFS('Interv. agentes'!$A$5:$A$18,$A5,'Interv. agentes'!$D$5:$D$18,$B5)>0,_xlfn.MINIFS('Interv. agentes'!$P$5:$P$18,'Interv. agentes'!$A$5:$A$18,$A5,'Interv. agentes'!$D$5:$D$18,$B5),2958465)) -> 46419 | I5: =MAX(_xlfn.MAXIFS('Interv. negocio y software'!$I$5:$I$36,'Interv. negocio y software'!$A$5:$A$36,$A5,'Interv. negocio y software'!$E$5:$E$36,$B5),_xlfn.MAXIFS('Interv. agentes'!$Q$5:$Q$18,'Interv. agentes'!$A$5:$A$18,$A5,'Interv. agentes'!$D$5:$D$18,$B5)) -> 46843 | J5: Precisión y sesgo por familia: previsión cerrada frente a expediciones, en GIO | K5: Piloto P2R Ondupet 2027 | L5: Quitar la línea de INF-16 (ya no está vivo) y añadir «+ Horas de personas» en Previsión y Precisión para que cuente la capacidad de INT-01 (903 €).
A6: Ondupet | B6: P2R-02 | C6: S&OP y plan de capacidad | D6: Transformación (capacidad de línea) · INF-11 | E6: Plan Maestro · Manuel Jesús Trinidad 258 h/año y Monica Gordillo 344 h/año (S&OP y Plan Maestro) | F6: Victoriano Pérez Carrasco | G6: Manuel Jesús Trinidad Montero · Sistemas / IT (dar de alta en el censo) | H6: =MIN(IF(COUNTIFS('Interv. negocio y software'!$A$5:$A$36,$A6,'Interv. negocio y software'!$E$5:$E$36,$B6)>0,_xlfn.MINIFS('Interv. negocio y software'!$H$5:$H$36,'Interv. negocio y software'!$A$5:$A$36,$A6,'Interv. negocio y software'!$E$5:$E$36,$B6),2958465),IF(COUNTIFS('Interv. agentes'!$A$5:$A$18,$A6,'Interv. agentes'!$D$5:$D$18,$B6)>0,_xlfn.MINIFS('Interv. agentes'!$P$5:$P$18,'Interv. agentes'!$A$5:$A$18,$A6,'Interv. agentes'!$D$5:$D$18,$B6),2958465)) -> 46510 | I6: =MAX(_xlfn.MAXIFS('Interv. negocio y software'!$I$5:$I$36,'Interv. negocio y software'!$A$5:$A$36,$A6,'Interv. negocio y software'!$E$5:$E$36,$B6),_xlfn.MAXIFS('Interv. agentes'!$Q$5:$Q$18,'Interv. agentes'!$A$5:$A$18,$A6,'Interv. agentes'!$D$5:$D$18,$B6)) -> 46843 | J6: % de saturación por línea de extrusión y termoformado, en GIO | K6: Piloto P2R Ondupet 2027 | L6: Añadir «+ Horas de personas» en Plan Maestro (INT-02). Revisar la dedicación de Victoriano: no tiene % en S&OP y Plan Maestro aunque hace el plan de fabricación y los temporales.
A7: Ondupet | B7: P2R-03 | C7: Política de inventario por segmento | D7: Circulante · INF-13 | E7: — (ninguna intervención cambia cajas) | F7: Monica Gordillo Guerrero | G7: Victoriano Pérez Carrasco · Manuel Jesús Trinidad Montero | H7: =MIN(IF(COUNTIFS('Interv. negocio y software'!$A$5:$A$36,$A7,'Interv. negocio y software'!$E$5:$E$36,$B7)>0,_xlfn.MINIFS('Interv. negocio y software'!$H$5:$H$36,'Interv. negocio y software'!$A$5:$A$36,$A7,'Interv. negocio y software'!$E$5:$E$36,$B7),2958465),IF(COUNTIFS('Interv. agentes'!$A$5:$A$18,$A7,'Interv. agentes'!$D$5:$D$18,$B7)>0,_xlfn.MINIFS('Interv. agentes'!$P$5:$P$18,'Interv. agentes'!$A$5:$A$18,$A7,'Interv. agentes'!$D$5:$D$18,$B7),2958465)) -> 46447 | I7: =MAX(_xlfn.MAXIFS('Interv. negocio y software'!$I$5:$I$36,'Interv. negocio y software'!$A$5:$A$36,$A7,'Interv. negocio y software'!$E$5:$E$36,$B7),_xlfn.MAXIFS('Interv. agentes'!$Q$5:$Q$18,'Interv. agentes'!$A$5:$A$18,$A7,'Interv. agentes'!$D$5:$D$18,$B7)) -> 46721 | J7: Cobertura en días de producto terminado por segmento, en GIO | K7: Piloto P2R Ondupet 2027 | L7: Quitar OPP-02 de «qué ataca»: lo cura P2R-04.
A8: Ondupet | B8: P2R-04 | C8: Promesa de fecha fiable | D8: Oportunidad (ingreso) · OPP-02 | E8: Plan Maestro (Cartera Pedidos) · Manuel Jesús Trinidad 258 h/año y Monica Gordillo 344 h/año | F8: Manuel Jesús Trinidad Montero | G8: Victoriano Pérez Carrasco · Monica Gordillo Guerrero | H8: =MIN(IF(COUNTIFS('Interv. negocio y software'!$A$5:$A$36,$A8,'Interv. negocio y software'!$E$5:$E$36,$B8)>0,_xlfn.MINIFS('Interv. negocio y software'!$H$5:$H$36,'Interv. negocio y software'!$A$5:$A$36,$A8,'Interv. negocio y software'!$E$5:$E$36,$B8),2958465),IF(COUNTIFS('Interv. agentes'!$A$5:$A$18,$A8,'Interv. agentes'!$D$5:$D$18,$B8)>0,_xlfn.MINIFS('Interv. agentes'!$P$5:$P$18,'Interv. agentes'!$A$5:$A$18,$A8,'Interv. agentes'!$D$5:$D$18,$B8),2958465)) -> 46447 | I8: =MAX(_xlfn.MAXIFS('Interv. negocio y software'!$I$5:$I$36,'Interv. negocio y software'!$A$5:$A$36,$A8,'Interv. negocio y software'!$E$5:$E$36,$B8),_xlfn.MAXIFS('Interv. agentes'!$Q$5:$Q$18,'Interv. agentes'!$A$5:$A$18,$A8,'Interv. agentes'!$D$5:$D$18,$B8)) -> 46812 | J8: % de pedidos entregados en la primera fecha confirmada: fecha confirmada frente a fecha de carga, en GIO | K8: Piloto P2R Ondupet 2027 | L8: Añadir «+ Horas de personas» en Plan Maestro (INT-03).
A9: Ondupet | B9: P2R-06 | C9: Programación estable y optimizada | D9: Transformación (capacidad de línea) · INF-12 Transformación (capacidad de línea) · INF-14 | E9: Programación · Victoriano Pérez · 430 h/año (25 %) | F9: Victoriano Pérez Carrasco | G9: Producción (dar de alta en el censo) · Sistemas / IT (dar de alta en el censo) | H9: =MIN(IF(COUNTIFS('Interv. negocio y software'!$A$5:$A$36,$A9,'Interv. negocio y software'!$E$5:$E$36,$B9)>0,_xlfn.MINIFS('Interv. negocio y software'!$H$5:$H$36,'Interv. negocio y software'!$A$5:$A$36,$A9,'Interv. negocio y software'!$E$5:$E$36,$B9),2958465),IF(COUNTIFS('Interv. agentes'!$A$5:$A$18,$A9,'Interv. agentes'!$D$5:$D$18,$B9)>0,_xlfn.MINIFS('Interv. agentes'!$P$5:$P$18,'Interv. agentes'!$A$5:$A$18,$A9,'Interv. agentes'!$D$5:$D$18,$B9),2958465)) -> 46844 | I9: =MAX(_xlfn.MAXIFS('Interv. negocio y software'!$I$5:$I$36,'Interv. negocio y software'!$A$5:$A$36,$A9,'Interv. negocio y software'!$E$5:$E$36,$B9),_xlfn.MAXIFS('Interv. agentes'!$Q$5:$Q$18,'Interv. agentes'!$A$5:$A$18,$A9,'Interv. agentes'!$D$5:$D$18,$B9)) -> 46934 | J9: Horas de cambio de molde y altura por semana, en los partes de producción | K9: Piloto P2R Ondupet 2027 | L9: Añadir «+ Horas de personas» en Programación (INT-04).
A10: Ondupet | B10: P2R-08 | C10: Control del servicio y mejora continua | D10: Oportunidad (ingreso) · OPP-03 Transformación (capacidad de línea) · INF-15 | E10: — (ninguna intervención cambia cajas; si ACC-11 marca su caja: Seguimiento y control · Victoriano · 258 h/año) | F10: Victoriano Pérez Carrasco | G10: Manuel Jesús Trinidad Montero | H10: =MIN(IF(COUNTIFS('Interv. negocio y software'!$A$5:$A$36,$A10,'Interv. negocio y software'!$E$5:$E$36,$B10)>0,_xlfn.MINIFS('Interv. negocio y software'!$H$5:$H$36,'Interv. negocio y software'!$A$5:$A$36,$A10,'Interv. negocio y software'!$E$5:$E$36,$B10),2958465),IF(COUNTIFS('Interv. agentes'!$A$5:$A$18,$A10,'Interv. agentes'!$D$5:$D$18,$B10)>0,_xlfn.MINIFS('Interv. agentes'!$P$5:$P$18,'Interv. agentes'!$A$5:$A$18,$A10,'Interv. agentes'!$D$5:$D$18,$B10),2958465)) -> 46478 | I10: =MAX(_xlfn.MAXIFS('Interv. negocio y software'!$I$5:$I$36,'Interv. negocio y software'!$A$5:$A$36,$A10,'Interv. negocio y software'!$E$5:$E$36,$B10),_xlfn.MAXIFS('Interv. agentes'!$Q$5:$Q$18,'Interv. agentes'!$A$5:$A$18,$A10,'Interv. agentes'!$D$5:$D$18,$B10)) -> 46568 | J10: OTIF contra la fecha del cliente: GIO y albaranes de SAP | K10: Piloto P2R Ondupet 2027
A11: MGT | B11: P2R-01 | C11: Gestión de la demanda | D11: Circulante · INF-01 | E11: — (ninguna intervención cambia cajas) | F11: Albert Fontanet Lopez | G11: Joan Carles Girones Campaña · Angélica Lemus Fernández (Ondupack) | H11: =MIN(IF(COUNTIFS('Interv. negocio y software'!$A$5:$A$36,$A11,'Interv. negocio y software'!$E$5:$E$36,$B11)>0,_xlfn.MINIFS('Interv. negocio y software'!$H$5:$H$36,'Interv. negocio y software'!$A$5:$A$36,$A11,'Interv. negocio y software'!$E$5:$E$36,$B11),2958465),IF(COUNTIFS('Interv. agentes'!$A$5:$A$18,$A11,'Interv. agentes'!$D$5:$D$18,$B11)>0,_xlfn.MINIFS('Interv. agentes'!$P$5:$P$18,'Interv. agentes'!$A$5:$A$18,$A11,'Interv. agentes'!$D$5:$D$18,$B11),2958465)) -> 46664 | I11: =MAX(_xlfn.MAXIFS('Interv. negocio y software'!$I$5:$I$36,'Interv. negocio y software'!$A$5:$A$36,$A11,'Interv. negocio y software'!$E$5:$E$36,$B11),_xlfn.MAXIFS('Interv. agentes'!$Q$5:$Q$18,'Interv. agentes'!$A$5:$A$18,$A11,'Interv. agentes'!$D$5:$D$18,$B11)) -> 46783 | J11: % de la demanda (Ondupack y clientes repetitivos) con previsión por calidad y ancho | K11: Despliegue P2R papeleras (MGT y PDA) 2027-28
A12: MGT | B12: P2R-02 | C12: S&OP y plan de capacidad | D12: Transformación (capacidad de línea) · INF-02 | E12: Carga de Capacidad · Joan Carles Girones (sin dedicación cargada: 0 h) | F12: Joan Carles Girones Campaña | G12: Albert Fontanet Lopez | H12: =MIN(IF(COUNTIFS('Interv. negocio y software'!$A$5:$A$36,$A12,'Interv. negocio y software'!$E$5:$E$36,$B12)>0,_xlfn.MINIFS('Interv. negocio y software'!$H$5:$H$36,'Interv. negocio y software'!$A$5:$A$36,$A12,'Interv. negocio y software'!$E$5:$E$36,$B12),2958465),IF(COUNTIFS('Interv. agentes'!$A$5:$A$18,$A12,'Interv. agentes'!$D$5:$D$18,$B12)>0,_xlfn.MINIFS('Interv. agentes'!$P$5:$P$18,'Interv. agentes'!$A$5:$A$18,$A12,'Interv. agentes'!$D$5:$D$18,$B12),2958465)) -> 46664 | I12: =MAX(_xlfn.MAXIFS('Interv. negocio y software'!$I$5:$I$36,'Interv. negocio y software'!$A$5:$A$36,$A12,'Interv. negocio y software'!$E$5:$E$36,$B12),_xlfn.MAXIFS('Interv. agentes'!$Q$5:$Q$18,'Interv. agentes'!$A$5:$A$18,$A12,'Interv. agentes'!$D$5:$D$18,$B12)) -> 47109 | J12: Horas de máquina a 3 turnos sin cartera, en GIO y en los partes de producción | K12: Despliegue P2R papeleras (MGT y PDA) 2027-28 | L12: Añadir «+ Horas de personas» en Carga de Capacidad (INT-01).
A13: MGT | B13: P2R-03 | C13: Política de inventario por segmento | D13: Circulante · INF-03 | E13: Plan Fabricación · Joan Carles Girones (sin dedicación cargada: 0 h) | F13: Joan Carles Girones Campaña | G13: Angélica Lemus Fernández (Ondupack) · Albert Fontanet Lopez | H13: =MIN(IF(COUNTIFS('Interv. negocio y software'!$A$5:$A$36,$A13,'Interv. negocio y software'!$E$5:$E$36,$B13)>0,_xlfn.MINIFS('Interv. negocio y software'!$H$5:$H$36,'Interv. negocio y software'!$A$5:$A$36,$A13,'Interv. negocio y software'!$E$5:$E$36,$B13),2958465),IF(COUNTIFS('Interv. agentes'!$A$5:$A$18,$A13,'Interv. agentes'!$D$5:$D$18,$B13)>0,_xlfn.MINIFS('Interv. agentes'!$P$5:$P$18,'Interv. agentes'!$A$5:$A$18,$A13,'Interv. agentes'!$D$5:$D$18,$B13),2958465)) -> 46664 | I13: =MAX(_xlfn.MAXIFS('Interv. negocio y software'!$I$5:$I$36,'Interv. negocio y software'!$A$5:$A$36,$A13,'Interv. negocio y software'!$E$5:$E$36,$B13),_xlfn.MAXIFS('Interv. agentes'!$Q$5:$Q$18,'Interv. agentes'!$A$5:$A$18,$A13,'Interv. agentes'!$D$5:$D$18,$B13)) -> 47109 | J13: € y días de cobertura del stock de Ondupack en MGT, en SAP | K13: Despliegue P2R papeleras (MGT y PDA) 2027-28 | L13: Quitar OPP-02 de «qué ataca» (lo cura P2R-04) y añadir «+ Horas de personas» en Plan Fabricación (INT-02).
A14: MGT | B14: P2R-04 | C14: Promesa de fecha fiable | D14: Oportunidad (ingreso) · OPP-02 | E14: Demanda Externa · Joan Carles Girones, que hace de atención al cliente (sin dedicación cargada: 0 h) | F14: Albert Fontanet Lopez | G14: Joan Carles Girones Campaña | H14: =MIN(IF(COUNTIFS('Interv. negocio y software'!$A$5:$A$36,$A14,'Interv. negocio y software'!$E$5:$E$36,$B14)>0,_xlfn.MINIFS('Interv. negocio y software'!$H$5:$H$36,'Interv. negocio y software'!$A$5:$A$36,$A14,'Interv. negocio y software'!$E$5:$E$36,$B14),2958465),IF(COUNTIFS('Interv. agentes'!$A$5:$A$18,$A14,'Interv. agentes'!$D$5:$D$18,$B14)>0,_xlfn.MINIFS('Interv. agentes'!$P$5:$P$18,'Interv. agentes'!$A$5:$A$18,$A14,'Interv. agentes'!$D$5:$D$18,$B14),2958465)) -> 46905 | I14: =MAX(_xlfn.MAXIFS('Interv. negocio y software'!$I$5:$I$36,'Interv. negocio y software'!$A$5:$A$36,$A14,'Interv. negocio y software'!$E$5:$E$36,$B14),_xlfn.MAXIFS('Interv. agentes'!$Q$5:$Q$18,'Interv. agentes'!$A$5:$A$18,$A14,'Interv. agentes'!$D$5:$D$18,$B14)) -> 47025 | J14: % de pedidos entregados en la fecha pedida, en SAP | K14: Despliegue P2R papeleras (MGT y PDA) 2027-28 | L14: Añadir «+ Horas de personas» en Demanda Externa (INT-04) y la intervención «Fecha confirmada por Planificación».
A15: MGT | B15: P2R-05 | C15: Planificación de materiales por excepción | D15: Circulante · INF-04 | E15: MRP · Marta Boyo y Joan Carles Girones (sin dedicación cargada: 0 h) | F15: Marta Boyo Martinez | G15: Joan Carles Girones Campaña · Sistemas / IT (dar de alta en el censo) | H15: =MIN(IF(COUNTIFS('Interv. negocio y software'!$A$5:$A$36,$A15,'Interv. negocio y software'!$E$5:$E$36,$B15)>0,_xlfn.MINIFS('Interv. negocio y software'!$H$5:$H$36,'Interv. negocio y software'!$A$5:$A$36,$A15,'Interv. negocio y software'!$E$5:$E$36,$B15),2958465),IF(COUNTIFS('Interv. agentes'!$A$5:$A$18,$A15,'Interv. agentes'!$D$5:$D$18,$B15)>0,_xlfn.MINIFS('Interv. agentes'!$P$5:$P$18,'Interv. agentes'!$A$5:$A$18,$A15,'Interv. agentes'!$D$5:$D$18,$B15),2958465)) -> 46722 | I15: =MAX(_xlfn.MAXIFS('Interv. negocio y software'!$I$5:$I$36,'Interv. negocio y software'!$A$5:$A$36,$A15,'Interv. negocio y software'!$E$5:$E$36,$B15),_xlfn.MAXIFS('Interv. agentes'!$Q$5:$Q$18,'Interv. agentes'!$A$5:$A$18,$A15,'Interv. agentes'!$D$5:$D$18,$B15)) -> 47109 | J15: Cobertura en días de materias primas y auxiliares, en SAP | K15: Despliegue P2R papeleras (MGT y PDA) 2027-28 | L15: Añadir «+ Horas de personas» en MRP (INT-03).
A16: MGT | B16: P2R-06 | C16: Programación estable y optimizada | D16: Transformación (capacidad de línea) · INF-05 Transformación (capacidad de línea) · INF-06 | E16: Programación · Joan Carles Girones (sin dedicación cargada: 0 h) | F16: Joan Carles Girones Campaña | G16: Ramón (algoritmo, dar de alta en el censo) | H16: =MIN(IF(COUNTIFS('Interv. negocio y software'!$A$5:$A$36,$A16,'Interv. negocio y software'!$E$5:$E$36,$B16)>0,_xlfn.MINIFS('Interv. negocio y software'!$H$5:$H$36,'Interv. negocio y software'!$A$5:$A$36,$A16,'Interv. negocio y software'!$E$5:$E$36,$B16),2958465),IF(COUNTIFS('Interv. agentes'!$A$5:$A$18,$A16,'Interv. agentes'!$D$5:$D$18,$B16)>0,_xlfn.MINIFS('Interv. agentes'!$P$5:$P$18,'Interv. agentes'!$A$5:$A$18,$A16,'Interv. agentes'!$D$5:$D$18,$B16),2958465)) -> 46693 | I16: =MAX(_xlfn.MAXIFS('Interv. negocio y software'!$I$5:$I$36,'Interv. negocio y software'!$A$5:$A$36,$A16,'Interv. negocio y software'!$E$5:$E$36,$B16),_xlfn.MAXIFS('Interv. agentes'!$Q$5:$Q$18,'Interv. agentes'!$A$5:$A$18,$A16,'Interv. agentes'!$D$5:$D$18,$B16)) -> 47109 | J16: Horas de cambio de calidad y ancho por semana, en los partes de producción | K16: Despliegue P2R papeleras (MGT y PDA) 2027-28 | L16: Añadir «+ Horas de personas» en Programación (INT-05).
A17: MGT | B17: P2R-07 | C17: Liberación controlada | D17: Transformación (capacidad de línea) · INF-08 | E17: — (si ACC-11 marca su caja: Liberación de la Orden · Joan Carles Girones) | F17: Joan Carles Girones Campaña | G17: Marta Boyo Martinez · Sistemas / IT (dar de alta en el censo) | H17: =MIN(IF(COUNTIFS('Interv. negocio y software'!$A$5:$A$36,$A17,'Interv. negocio y software'!$E$5:$E$36,$B17)>0,_xlfn.MINIFS('Interv. negocio y software'!$H$5:$H$36,'Interv. negocio y software'!$A$5:$A$36,$A17,'Interv. negocio y software'!$E$5:$E$36,$B17),2958465),IF(COUNTIFS('Interv. agentes'!$A$5:$A$18,$A17,'Interv. agentes'!$D$5:$D$18,$B17)>0,_xlfn.MINIFS('Interv. agentes'!$P$5:$P$18,'Interv. agentes'!$A$5:$A$18,$A17,'Interv. agentes'!$D$5:$D$18,$B17),2958465)) -> 46755 | I17: =MAX(_xlfn.MAXIFS('Interv. negocio y software'!$I$5:$I$36,'Interv. negocio y software'!$A$5:$A$36,$A17,'Interv. negocio y software'!$E$5:$E$36,$B17),_xlfn.MAXIFS('Interv. agentes'!$Q$5:$Q$18,'Interv. agentes'!$A$5:$A$18,$A17,'Interv. agentes'!$D$5:$D$18,$B17)) -> 46871 | J17: Órdenes liberadas con comprobación manual o en papel, en GIO | K17: Despliegue P2R papeleras (MGT y PDA) 2027-28 | L17: Añadir la intervención «Orden digital a producción»: INF-08 habla de las órdenes en papel.
A18: MGT | B18: P2R-08 | C18: Control del servicio y mejora continua | D18: Oportunidad (ingreso) · OPP-03 Transformación (capacidad de línea) · INF-07 | E18: Entregas a Ondupack y Cierre · Joan Carles Girones (sin dedicación cargada: 0 h) | F18: Albert Fontanet Lopez | G18: Joan Carles Girones Campaña · Angélica Lemus Fernández (Ondupack) | H18: =MIN(IF(COUNTIFS('Interv. negocio y software'!$A$5:$A$36,$A18,'Interv. negocio y software'!$E$5:$E$36,$B18)>0,_xlfn.MINIFS('Interv. negocio y software'!$H$5:$H$36,'Interv. negocio y software'!$A$5:$A$36,$A18,'Interv. negocio y software'!$E$5:$E$36,$B18),2958465),IF(COUNTIFS('Interv. agentes'!$A$5:$A$18,$A18,'Interv. agentes'!$D$5:$D$18,$B18)>0,_xlfn.MINIFS('Interv. agentes'!$P$5:$P$18,'Interv. agentes'!$A$5:$A$18,$A18,'Interv. agentes'!$D$5:$D$18,$B18),2958465)) -> 46664 | I18: =MAX(_xlfn.MAXIFS('Interv. negocio y software'!$I$5:$I$36,'Interv. negocio y software'!$A$5:$A$36,$A18,'Interv. negocio y software'!$E$5:$E$36,$B18),_xlfn.MAXIFS('Interv. agentes'!$Q$5:$Q$18,'Interv. agentes'!$A$5:$A$18,$A18,'Interv. agentes'!$D$5:$D$18,$B18)) -> 47109 | J18: OTIF de clientes externos y de Ondupack, en SAP | K18: Despliegue P2R papeleras (MGT y PDA) 2027-28 | L18: Añadir «+ Horas de personas» en Entregas a Ondupack y Cierre (INT-06).
A19: Ondupack Almendralejo | B19: P2R-01 | C19: Gestión de la demanda | D19: Circulante · INF-01 | E19: — (ninguna intervención cambia cajas) | F19: Miguel Ángel Rosado Martínez | G19: Maria Teresa Espinosa Paredes · Tomás Buenavida Santiago | H19: =MIN(IF(COUNTIFS('Interv. negocio y software'!$A$5:$A$36,$A19,'Interv. negocio y software'!$E$5:$E$36,$B19)>0,_xlfn.MINIFS('Interv. negocio y software'!$H$5:$H$36,'Interv. negocio y software'!$A$5:$A$36,$A19,'Interv. negocio y software'!$E$5:$E$36,$B19),2958465),IF(COUNTIFS('Interv. agentes'!$A$5:$A$18,$A19,'Interv. agentes'!$D$5:$D$18,$B19)>0,_xlfn.MINIFS('Interv. agentes'!$P$5:$P$18,'Interv. agentes'!$A$5:$A$18,$A19,'Interv. agentes'!$D$5:$D$18,$B19),2958465)) -> 46539 | I19: =MAX(_xlfn.MAXIFS('Interv. negocio y software'!$I$5:$I$36,'Interv. negocio y software'!$A$5:$A$36,$A19,'Interv. negocio y software'!$E$5:$E$36,$B19),_xlfn.MAXIFS('Interv. agentes'!$Q$5:$Q$18,'Interv. agentes'!$A$5:$A$18,$A19,'Interv. agentes'!$D$5:$D$18,$B19)) -> 46752 | J19: % de la demanda repetitiva con previsión, en GIO | K19: Despliegue P2R Ondupack 2027
A20: Ondupack Almendralejo | B20: P2R-02 | C20: S&OP y plan de capacidad | D20: Transformación (capacidad de línea) · INF-06 | E20: Carga Capacidad · Miguel Ángel Rosado y Tomás Buenavida (sin dedicación cargada: 0 h) | F20: José María Baquero Jaen | G20: Miguel Ángel Rosado Martínez · Karim Karach Boujtat · Tomás Buenavida Santiago | H20: =MIN(IF(COUNTIFS('Interv. negocio y software'!$A$5:$A$36,$A20,'Interv. negocio y software'!$E$5:$E$36,$B20)>0,_xlfn.MINIFS('Interv. negocio y software'!$H$5:$H$36,'Interv. negocio y software'!$A$5:$A$36,$A20,'Interv. negocio y software'!$E$5:$E$36,$B20),2958465),IF(COUNTIFS('Interv. agentes'!$A$5:$A$18,$A20,'Interv. agentes'!$D$5:$D$18,$B20)>0,_xlfn.MINIFS('Interv. agentes'!$P$5:$P$18,'Interv. agentes'!$A$5:$A$18,$A20,'Interv. agentes'!$D$5:$D$18,$B20),2958465)) -> 46569 | I20: =MAX(_xlfn.MAXIFS('Interv. negocio y software'!$I$5:$I$36,'Interv. negocio y software'!$A$5:$A$36,$A20,'Interv. negocio y software'!$E$5:$E$36,$B20),_xlfn.MAXIFS('Interv. agentes'!$Q$5:$Q$18,'Interv. agentes'!$A$5:$A$18,$A20,'Interv. agentes'!$D$5:$D$18,$B20)) -> 47026 | J20: % de saturación de la 924 con la velocidad real, en GIO | K20: Despliegue P2R Ondupack 2027 | L20: Añadir «+ Horas de personas» en Carga Capacidad (INT-01), después de cargar la dedicación de la celda.
A21: Ondupack Almendralejo | B21: P2R-05 | C21: Planificación de materiales por excepción | D21: P&L · fuga · INF-02 Circulante · INF-03 | E21: Papel y Auxiliares · Miguel Ángel Rosado y Angélica Lemus (sin dedicación cargada: 0 h) | F21: Angélica Lemus Fernández | G21: Miguel Ángel Rosado Martínez · Tomás Buenavida Santiago | H21: =MIN(IF(COUNTIFS('Interv. negocio y software'!$A$5:$A$36,$A21,'Interv. negocio y software'!$E$5:$E$36,$B21)>0,_xlfn.MINIFS('Interv. negocio y software'!$H$5:$H$36,'Interv. negocio y software'!$A$5:$A$36,$A21,'Interv. negocio y software'!$E$5:$E$36,$B21),2958465),IF(COUNTIFS('Interv. agentes'!$A$5:$A$18,$A21,'Interv. agentes'!$D$5:$D$18,$B21)>0,_xlfn.MINIFS('Interv. agentes'!$P$5:$P$18,'Interv. agentes'!$A$5:$A$18,$A21,'Interv. agentes'!$D$5:$D$18,$B21),2958465)) -> 46631 | I21: =MAX(_xlfn.MAXIFS('Interv. negocio y software'!$I$5:$I$36,'Interv. negocio y software'!$A$5:$A$36,$A21,'Interv. negocio y software'!$E$5:$E$36,$B21),_xlfn.MAXIFS('Interv. agentes'!$Q$5:$Q$18,'Interv. agentes'!$A$5:$A$18,$A21,'Interv. agentes'!$D$5:$D$18,$B21)) -> 47026 | J21: Órdenes liberadas con material pendiente (GIO) y € de compras urgentes (SAP) | K21: Despliegue P2R Ondupack 2027 | L21: Anclar ACC-07 (agente) a Papel y Auxiliares y añadir «+ Horas de personas» en esa caja.
A22: Ondupack Almendralejo | B22: P2R-06 | C22: Programación estable y optimizada | D22: Transformación (capacidad de línea) · INF-04 Transformación (capacidad de línea) · INF-05 | E22: Converting · Miguel Ángel Rosado (sin dedicación cargada: 0 h) | F22: Miguel Ángel Rosado Martínez | G22: José María Baquero Jaen · Tomás Buenavida Santiago · Sistemas / IT (dar de alta en el censo) | H22: =MIN(IF(COUNTIFS('Interv. negocio y software'!$A$5:$A$36,$A22,'Interv. negocio y software'!$E$5:$E$36,$B22)>0,_xlfn.MINIFS('Interv. negocio y software'!$H$5:$H$36,'Interv. negocio y software'!$A$5:$A$36,$A22,'Interv. negocio y software'!$E$5:$E$36,$B22),2958465),IF(COUNTIFS('Interv. agentes'!$A$5:$A$18,$A22,'Interv. agentes'!$D$5:$D$18,$B22)>0,_xlfn.MINIFS('Interv. agentes'!$P$5:$P$18,'Interv. agentes'!$A$5:$A$18,$A22,'Interv. agentes'!$D$5:$D$18,$B22),2958465)) -> 46447 | I22: =MAX(_xlfn.MAXIFS('Interv. negocio y software'!$I$5:$I$36,'Interv. negocio y software'!$A$5:$A$36,$A22,'Interv. negocio y software'!$E$5:$E$36,$B22),_xlfn.MAXIFS('Interv. agentes'!$Q$5:$Q$18,'Interv. agentes'!$A$5:$A$18,$A22,'Interv. agentes'!$D$5:$D$18,$B22)) -> 47026 | J22: Horas de cambio en onduladora y converting, con los escenarios SMED de GIO | K22: Despliegue P2R Ondupack 2027 | L22: Añadir «+ Horas de personas» en Converting (INT-03).
A23: Ondupack Almendralejo | B23: P2R-08 | C23: Control del servicio y mejora continua | D23: Oportunidad (ingreso) · OPP-01 | E23: Seguimiento del Servicio · Miguel Ángel Rosado y Teresa Espinosa (sin dedicación cargada: 0 h) | F23: Maria Teresa Espinosa Paredes | G23: Miguel Ángel Rosado Martínez | H23: =MIN(IF(COUNTIFS('Interv. negocio y software'!$A$5:$A$36,$A23,'Interv. negocio y software'!$E$5:$E$36,$B23)>0,_xlfn.MINIFS('Interv. negocio y software'!$H$5:$H$36,'Interv. negocio y software'!$A$5:$A$36,$A23,'Interv. negocio y software'!$E$5:$E$36,$B23),2958465),IF(COUNTIFS('Interv. agentes'!$A$5:$A$18,$A23,'Interv. agentes'!$D$5:$D$18,$B23)>0,_xlfn.MINIFS('Interv. agentes'!$P$5:$P$18,'Interv. agentes'!$A$5:$A$18,$A23,'Interv. agentes'!$D$5:$D$18,$B23),2958465)) -> 46539 | I23: =MAX(_xlfn.MAXIFS('Interv. negocio y software'!$I$5:$I$36,'Interv. negocio y software'!$A$5:$A$36,$A23,'Interv. negocio y software'!$E$5:$E$36,$B23),_xlfn.MAXIFS('Interv. agentes'!$Q$5:$Q$18,'Interv. agentes'!$A$5:$A$18,$A23,'Interv. agentes'!$D$5:$D$18,$B23)) -> 47026 | J23: OTIF contra la fecha propuesta por el CTP, en GIO | K23: Despliegue P2R Ondupack 2027 | L23: Añadir «+ Horas de personas» en Seguimiento del Servicio (INT-02).

Sheet Interv. negocio y software
A1: Intervenciones de negocio y software · campos del formulario
A2: Cómo va: «pendiente» en todas. Responsable: «el owner» deja el campo vacío (lo lleva el owner de la palanca). La última columna propone marcar «Además cambia tareas del flujo» para que la intervención cuente en el to-be y en la capacidad.
A4: Empresa | B4: Código | C4: Nombre | D4: De qué es | E4: Palanca | F4: Qué hay que hacer | G4: Responsable | H4: Empieza | I4: Termina | J4: Marcar «cambia tareas del flujo» (caja › tarea → qué le pasa) | K4: Nota
A5: Ondupet | B5: ACC-01 | C5: Calendario de previsión con día de cierre | D5: negocio | E5: P2R-01 | F5: Fijar un día de cierre mensual de la previsión y congelar el mes en curso. Después del cierre, cualquier cambio necesita la aprobación de Planificación y queda registrado con su motivo. Publicar el calendario del año. | G5: el owner | H5: 46419 | I5: 46477 | K5: Ya rellenado en la aplicación: solo faltan fechas.
A6: Ondupet | B6: ACC-02 | C6: Registro diario de agotados | D6: negocio | E6: P2R-01 | F6: Definir qué es un agotado y qué es un pedido rechazado, y registrarlos cada día en el sistema con su motivo, para que el histórico de demanda deje de estar distorsionado. | G6: Victoriano Pérez Carrasco | H6: 46447 | I6: 46507
A7: Ondupet | B7: ACC-03 | C7: Cálculo de % de saturación | D7: software | E7: P2R-02 | F7: Al cerrar la previsión, el sistema calcula el % de saturación de cada línea de extrusión y termoformado (previsión × rutas × tiempos de ciclo frente al calendario) y marca las que pasan del umbral. | G7: Sistemas / IT (dar de alta en el censo) | H7: 46539 | I7: 46598 | J7: Plan Maestro › Plan de Fabricación → Decisión de turnos y balanceo de materiales → se simplifica | K7: Ya rellenado en la aplicación: solo faltan fechas.
A8: Ondupet | B8: ACC-04 | C8: Revisión mensual de la capacidad de la planta | D8: negocio | E8: P2R-02 | F8: Tras el cierre de la previsión, Planificación presenta la carga frente a la capacidad y la dirección de planta decide turnos y balanceo con umbrales de ocupación acordados. Es el S&OP de planta mientras llega el de grupo. | G8: el owner | H8: 46510 | I8: 46568
A9: Ondupet | B9: ACC-05 | C9: Cálculo automático de temporales | D9: software | E9: P2R-02 | F9: La reserva de ciclo por familia se calcula sola en cada cierre a partir de la previsión cerrada y los tiempos de ciclo. Planificación solo revisa los cambios en la reunión de consenso. | G9: Sistemas / IT (dar de alta en el censo) | H9: 46539 | I9: 46598 | J9: Plan Maestro › Temporales → Reserva de Ciclo Por Familia → la hace el sistema
A10: Ondupet | B10: ACC-06 | C10: Definir criterios ABC / estrategia | D10: negocio | E10: P2R-03 | F10: Definir ABC por valor, XYZ por variabilidad y la matriz que asigna a cada segmento MTS o MTO y su stock de seguridad. Comercial valida las estrategias. | G10: el owner | H10: 46447 | I10: 46477
A11: Ondupet | B11: ACC-07 | C11: Definir acciones para el stock sin rotación | D11: negocio | E11: P2R-03 | F11: Revisión mensual con Comercial del producto terminado sin movimiento: se decide venderlo, reprocesarlo o depreciarlo, y se imputa a quien lo originó cuando viene de un cambio de previsión fuera de plazo. | G11: Manuel Jesús Trinidad Montero | H11: 46478 | I11: 46538
A12: Ondupet | B12: ACC-08 | C12: Cálculo automático de días de stock | D12: software | E12: P2R-03 | F12: El sistema calcula la cobertura en días de stock de cada referencia y avisa de las que superan el objetivo de su segmento, para decidir a tiempo qué se deja de fabricar o se liquida. | G12: Sistemas / IT (dar de alta en el censo) | H12: 46631 | I12: 46721
A13: Ondupet | B13: ACC-09 | C13: Definir política de fecha confirmada | D13: negocio | E13: P2R-04 | F13: Cada pedido lleva fecha solicitada y fecha confirmada. Planificación confirma en un plazo fijo y, si sabe que no se llega, Comercial avisa al cliente con la nueva fecha; el aviso lo ejecuta O2C. | G13: el owner | H13: 46447 | I13: 46507
A14: Ondupet | B14: ACC-10 | C14: Análisis de atrasos de entregas | D14: negocio | E14: P2R-08 | F14: Cada atraso se clasifica con una lista cerrada de causas (previsión, capacidad, material, secuencia o cambio del cliente). Cada mes se revisan las principales con una acción y un responsable, y lo aprendido vuelve a la previsión o a los parámetros. | G14: el owner | H14: 46510 | I14: 46568
A15: Ondupet | B15: ACC-11 | C15: Informe automático de pedidos / cargas en riesgo | D15: software | E15: P2R-08 | F15: Informe automático diario de los pedidos y cargas en riesgo de llegar tarde: sustituye al reporte manual de cargas atrasadas y avisa a Comercial antes de que ocurra el atraso. | G15: Sistemas / IT (dar de alta en el censo) | H15: 46478 | I15: 46568 | J15: Seguimiento y control › Seguimiento Diario Cumplimiento Servicio → la hace el sistema
A16: MGT | B16: ACC-01 | C16: Previsión de papel de Ondupack | D16: negocio | E16: P2R-01 | F16: Acordar con Ondupack que, en cada ciclo, envíe la previsión de papel de los ciclos siguientes por calidad y ancho, además del pedido firme 10 días antes. Es la otra mitad de la intervención «Previsión de papel compartida con MGT/PDA» de Ondupack. | G16: Joan Carles Girones Campaña (con Angélica, Ondupack) | H16: 46664 | I16: 46738
A17: MGT | B17: ACC-02 | C17: Previsión de los clientes externos repetitivos | D17: negocio | E17: P2R-01 | F17: Identificar con Comercial los clientes externos con consumo repetitivo y acordar con ellos una previsión no vinculante por calidad y ancho, revisada en cada ciclo. | G17: el owner | H17: 46693 | I17: 46783
A18: MGT | B18: ACC-03 | C18: Política de llenado de capacidad | D18: negocio | E18: P2R-02 | F18: Decidir con Dirección qué se fabrica cuando sobra capacidad (referencias repetitivas con mínimo y máximo, sobre todo las de Ondupack) y cuándo compensa parar, comparando el coste de parada con el coste del stock. Sustituye a la regla de «3 turnos siempre». | G18: el owner | H18: 46664 | I18: 46738 | K18: Decisión con Dirección.
A19: MGT | B19: ACC-04 | C19: Revisión mensual de capacidad y ciclos | D19: negocio | E19: P2R-02 | F19: Reunión mensual de Joan Carles con Comercial (Albert) y Dirección: carga frente a capacidad de los próximos ciclos, duración de cada calidad y pedidos que no caben. | G19: el owner | H19: 46693 | I19: 46783
A20: MGT | B20: ACC-05 | C20: Pull system con Ondupack, con mínimo y máximo por referencia | D20: negocio | E20: P2R-03 | F20: Definir con Ondupack qué referencias se reponen por pull, con un mínimo y un máximo en MGT. Ondupack retira cada día de ese stock y MGT lo repone al combinar sus ciclos. | G20: el owner | H20: 46664 | I20: 46738 | K20: Se acuerda con Angélica (Ondupack).
A21: MGT | B21: ACC-06 | C21: MRP de materias primas en SAP | D21: software | E21: P2R-05 | F21: Pasar el MRP de materias primas del Excel a SAP, como ya se hace con los auxiliares, alimentado con el plan de ciclos y con lead time, lote mínimo y stock de seguridad completos. | G21: Sistemas / IT (dar de alta en el censo) | H21: 46722 | I21: 46843 | J21: MRP › MRP de materias primas en Excel → la hace el sistema
A22: MGT | B22: ACC-07 | C22: Algoritmo con lo ya fabricado y fecha límite de cartera | D22: software | E22: P2R-06 | F22: El algoritmo tiene en cuenta lo ya fabricado y el stock pull, y una fecha límite de cartera por ciclo. Su salida pasa a ser el estándar y la agrupación manual por calidad y ancho desaparece. | G22: Ramón (algoritmo, dar de alta en el censo) | H22: 46693 | I22: 46808 | J22: Programación › Agrupar por calidad y ancho → desaparece; Algoritmo de combinación por ciclos → se simplifica
A23: MGT | B23: ACC-11 | C23: Disponibilidad de material por orden | D23: software | E23: P2R-07 | F23: El sistema muestra en cada orden si el material está y cuándo llega, a partir del MRP y de los pedidos de compra. Sustituye la comprobación manual en varios sitios. | G23: Sistemas / IT (dar de alta en el censo) | H23: 46755 | I23: 46871 | J23: Liberación de la Orden › Comprobar a mano que hay material → la hace el sistema
A24: MGT | B24: ACC-08 | C24: Pilar de servicio semanal | D24: negocio | E24: P2R-08 | F24: Reunión semanal fija entre MGT, Ondupack y Comercial: servicio, pedidos pendientes, atrasos y sus causas, y restos de pedidos antiguos por cerrar. | G24: el owner | H24: 46664 | I24: 46721
A25: MGT | B25: ACC-09 | C25: KPI de servicio | D25: negocio | E25: P2R-08 | F25: Definir el OTIF contra fecha confirmada para clientes externos y para Ondupack, y publicarlo cada semana. | G25: el owner | H25: 46664 | I25: 46721
A26: MGT | B26: ACC-10 | C26: Visibilidad de stock y cargas para Ondupack | D26: software | E26: P2R-08 | F26: Ondupack ve en línea el stock de MGT y la producción prevista, y pide las cargas desde ahí, en lugar de los unos 16 correos diarios. La carga la sigue ejecutando T2D. | G26: Sistemas / IT (dar de alta en el censo) | H26: 46755 | I26: 46843 | J26: Entregas a Ondupack y Cierre › Enviar el stock a Ondupack cada día → desaparece
A27: Ondupack Almendralejo | B27: ACC-01 | C27: Integración de las referencias/clientes que vayan por previsión en GIO | D27: negocio | E27: P2R-01 | F27: Identificar con Comercial los clientes y referencias con consumo repetitivo, acordar con ellos una previsión no vinculante y cargarla en GIO para que la carga-capacidad y el CTP la tengan en cuenta. | G27: el owner | H27: 46539 | I27: 46752
A28: Ondupack Almendralejo | B28: ACC-02 | C28: Registro de la demanda perdida en GIO | D28: software | E28: P2R-01 | F28: Cuando el cliente no acepta la fecha que propone el CTP, reduce la cantidad o se rechaza un pedido por capacidad, GIO obliga a registrar el motivo. | G28: Sistemas / IT (dar de alta en el censo) | H28: 46539 | I28: 46630 | J28: Entrada de Pedidos y Fecha › nueva tarea «Registro de la demanda perdida» → la hace el sistema
A29: Ondupack Almendralejo | B29: ACC-03 | C29: Revisión mensual de capacidad y cuellos de botella | D29: negocio | E29: P2R-02 | F29: Reunión mensual Planificación–Producción–Comercial con la carga de los próximos 2–3 meses por máquina: decide turnos con los escenarios de 2 a 5, qué entra en la 924 y qué se desvía por ruta alternativa. | G29: el owner | H29: 46569 | I29: 46660
A30: Ondupack Almendralejo | B30: ACC-04 | C30: Necesidad de papel calculada desde el plan | D30: software | E30: P2R-05 | F30: Calcular cada día la necesidad neta de papel a partir de la cartera planificada, la previsión y la lista de materiales, en lugar del consumo pasado, y avisar de las faltas por orden y por fecha. | G30: Sistemas / IT (dar de alta en el censo) | H30: 46631 | I30: 46752 | J30: Papel y Auxiliares › Necesidad de papel por consumo pasado → la hace el sistema
A31: Ondupack Almendralejo | B31: ACC-05 | C31: Stock de papel fiable sin esperar al inventario mensual | D31: software | E31: P2R-05 | F31: Declarar el consumo real de papel por orden, que ya se puede trazar en GPO, en lugar de calcularlo por diferencia en el inventario mensual. El registro lo hace el proceso de inventario; aquí se usa. | G31: Sistemas / IT (dar de alta en el censo) | H31: 46631 | I31: 46721
A32: Ondupack Almendralejo | B32: ACC-06 | C32: Previsión de papel compartida con MGT/PDA/PAPRESA | D32: negocio | E32: P2R-05 | F32: En cada ciclo, Ondupack envía a MGT, PDA y Papresa la previsión de papel de los próximos ciclos por calidad y ancho, además del pedido firme 10 días antes. El pedido sigue yendo por P2P. | G32: el owner | H32: 46661 | I32: 46752
A33: Ondupack Almendralejo | B33: ACC-11 | C33: Algoritmo de combinación | D33: software | E33: P2R-06 | F33: Propone las combinaciones por canal minimizando trim y cambios, y agrupa las referencias que hoy se repiten en la misma semana. El planificador las revisa y aprueba. Ya está en el plan de sistemas. | G33: Sistemas / IT (dar de alta en el censo) | H33: 46447 | I33: 46660 | J33: Onduladora › Combinación y secuencia de onduladora → se simplifica; Cartera › Agrupar pedidos repetitivos → la hace el sistema | K33: Ya está en el plan de sistemas.
A34: Ondupack Almendralejo | B34: ACC-08 | C34: KPI oficial de servicio | D34: negocio | E34: P2R-08 | F34: Que Dirección y Comercial decidan el KPI oficial (recomendado: OTIF contra fecha confirmada por el CTP, pedido completo) y su objetivo, y publicarlo cada semana. | G34: el owner | H34: 46539 | I34: 46599 | K34: Lo decide Dirección con Comercial.
A35: Ondupack Almendralejo | B35: ACC-09 | C35: Reunión semanal con KPIs y causas | D35: negocio | E35: P2R-08 | F35: La reunión semanal de planificación Ondupack/Navalmoral incorpora el OTIF, la adherencia y las principales causas de atraso y de reprogramación, cada una con su acción y su responsable. | G35: Miguel Ángel Rosado Martínez | H35: 46600 | I35: 46660
A36: Ondupack Almendralejo | B36: ACC-10 | C36: Copiloto de estado de pedidos | D36: software | E36: P2R-08 | F36: Responde a Call center y a Comercial «¿cuándo sale el pedido X?» y «¿por qué va tarde?» con los datos de GIO, sin cambiar nada. | G36: Sistemas / IT (dar de alta en el censo) | H36: 46844 | I36: 46934 | J36: Seguimiento del Servicio › Seguimiento de fechas atrasadas → se simplifica

Sheet Interv. agentes
A1: Intervenciones de agentes · campos del formulario
A2: Qué le pasa a la caja: «reduce» (−30 % de dedicación por defecto; se ajusta en el lienzo). Confianza: EST. Responsable de la intervención: vacío, lo lleva el owner. Problema, cómo funciona hoy y resultado de INT-01 en Ondupet son los que ya escribiste.
A4: Empresa | B4: Código | C4: Nombre | D4: Palanca | E4: Caja | F4: Tareas del as-is y qué les pasa | G4: Problema | H4: Cómo funciona hoy | I4: Qué queremos cambiar (para el comité) | J4: Después: cómo se llama la tarea | K4: Tareas nuevas que añade (quién la hace) | L4: Cobertura objetivo % | M4: Excepción humana objetivo % | N4: Resultado esperado | O4: Criterio de éxito | P4: Desde | Q4: Hasta (go-live)
A5: Ondupet | B5: INT-01 | C5: Análisis de las desviaciones de la demanda | D5: P2R-01 | E5: Previsión y Precisión | F5: Comprobación de Accuracy Mes en Curso → la ejecuta un agente (toda la tarea) · ¿Buen % de Accuracy? → la ejecuta un agente · Corrección Previsiones Futuros Meses → la ejecuta un agente (solo una parte: propone, Comercial aprueba) | G5: Seguimiento manual de las posibles desviaciones de previsión del mes en curso; llegamos tarde a la corrección, así que se fabrica material por encima o por debajo de su necesidad y hay roturas. | H5: Seguimiento diario en GIO de lo expedido frente a la previsión del mes en curso. | I5: El agente compara cada día lo expedido con la previsión, detecta las familias que se desvían y propone la corrección de los meses siguientes con su causa; Planificación y Comercial la aprueban. | J5: Comprobación de Accuracy → «Desviaciones detectadas por el agente» · Corrección Previsiones Futuros Meses → «Aprobar la corrección propuesta» | K5: Revisar las familias que el agente marca como dudosas — persona (Planificación) | L5: 0.8 | M5: 0.2 | N5: Disminución del % de roturas y sobrestock que tenemos actualmente | O5: ≥ 80 % de las propuestas aceptadas sin rehacer y sesgo dentro del umbral 3 meses seguidos. | P5: 46692 | Q5: 46843
A6: Ondupet | B6: INT-02 | C6: Propuestas de balanceo | D6: P2R-02 | E6: Plan Maestro | F6: Plan de Fabricación → Decisión de turnos y balanceo de materiales → la ejecuta un agente (solo una parte: propone, Planificación decide) | G6: Los turnos y el balanceo entre extrusión y termoformado se deciden sin cruzar carga y capacidad: entran necesidades que no caben o quedan líneas ociosas. | H6: El planificador decide turnos y reparto de carga a mano, por experiencia, al preparar el plan de fabricación. | I6: Un agente propone cada mes el reparto de turnos y de carga por línea con su impacto en horas y €; Planificación lo aprueba en la revisión de capacidad. | J6: Decisión de turnos y balanceo → «Aprobar el plan de turnos propuesto» | K6: Revisar los escenarios que el agente marca como de riesgo — persona (Planificación) | L6: 0.7 | M6: 0.3 | N6: Cada mes hay un plan de capacidad propuesto con su coste, listo para decidir. | O6: ≥ 70 % de los planes aprobados sin rehacer; horas extra no planificadas a la baja 3 meses seguidos. | P6: 46692 | Q6: 46843
A7: Ondupet | B7: INT-03 | C7: Propuesta de fechas de entrega viables para los pedidos y notas de carga | D7: P2R-04 | E7: Plan Maestro | F7: Cartera Pedidos → la ejecuta un agente (solo una parte: propone fecha y notas de carga) | G7: Se mantiene la fecha del cliente aunque se sabe que no se llega, la cartera se revisa por separado en Comercial y en Planificación y las notas de carga se preparan a mano. | H7: Revisión diaria de la cartera en GIO por Comercial y por Planificación; las fechas no se cambian y las cargas se preparan a mano. | I7: Un agente propone para cada pedido una fecha viable con la capacidad y los temporales y prepara las notas de carga; Comercial confirma la fecha al cliente por O2C. | J7: Cartera Pedidos → «Revisar fechas y notas de carga propuestas» | K7: Confirmar la nueva fecha al cliente — persona (Comercial, por O2C) | L7: 0.85 | M7: 0.15 | N7: La fecha se propone con datos, no se teclea la que pide el cliente. | O7: ≥ 85 % de las fechas aceptadas sin cambios y OTIF a fecha confirmada en objetivo. | P7: 46692 | Q7: 46812
A8: Ondupet | B8: INT-04 | C8: Determinación de urgencias | D8: P2R-06 | E8: Programación | F8: ¿Cambios de última hora? → la ejecuta un agente (calcula el impacto) · Recuenciar urgencias y prioridades → la ejecuta un agente (solo una parte: propone la nueva secuencia) | G8: Las urgencias llegan por teléfono y se resecuencian a mano, sin zona congelada ni reglas; si no hay acuerdo, decide el director de planta. | H8: El planificador recibe la llamada, revisa a mano el programa en GIO y resecuencia. | I8: Un agente calcula el impacto de cada urgencia (pedidos que se retrasan y cambios extra), aplica las reglas de prioridad y propone la decisión; solo los conflictos llegan a dirección. | J8: ¿Cambios de última hora? → «Impacto de la urgencia calculado» · Recuenciar urgencias → «Aprobar la secuencia propuesta» | K8: Decidir los conflictos que el agente escala — persona (dirección de planta) | L8: 0.75 | M8: 0.25 | N8: Cada urgencia se decide con su impacto delante. | O8: 100 % de las urgencias con impacto calculado y −50 % de escalados. | P8: 46844 | Q8: 46934
A9: MGT | B9: INT-01 | C9: Agente de escenarios de ciclo | D9: P2R-02 | E9: Carga de Capacidad | F9: Carga a capacidad infinita · 3 turnos a velocidad máxima → la ejecuta un agente (solo una parte: propone el ciclo y su duración) | G9: Se carga a capacidad infinita, la máquina trabaja siempre a 3 turnos y la duración de cada calidad se ajusta sobre la marcha. | H9: Joan Carles fija a mano el ciclo de las 4 calidades y su duración con la cartera, y revisa con Comercial los pedidos que no caben. | I9: Un agente simula la duración y el orden de las calidades, las paradas y el stock, y propone el ciclo con su coste; Planificación decide. | J9: Carga a capacidad infinita → «Ciclo propuesto con su coste» | K9: Aprobar el ciclo — persona (Joan Carles con Comercial) | L9: 0.7 | M9: 0.3 | N9: Cada ciclo llega con un plan propuesto y valorado. | O9: ≥ 70 % de los planes aprobados sin rehacer. | P9: 46905 | Q9: 47109
A10: MGT | B10: INT-02 | C10: Agente de stock intercompany | D10: P2R-03 | E10: Plan Fabricación | F10: Nueva tarea «Revisión mensual del stock intercompany» → la ejecuta un agente | G10: Se acumula stock de Ondupack en MGT, sin límite ni revisión. | H10: Ondupack retira poco a poco lo fabricado y nadie revisa la cobertura de sus referencias en MGT. | I10: Un agente revisa cada mes la cobertura de las referencias de Ondupack en MGT, propone mínimos y máximos y avisa del stock sin salida. | J10: Revisión mensual del stock intercompany → la ejecuta el agente | K10: Aprobar mínimos y máximos — persona (Joan Carles con Angélica, Ondupack) | L10: 0.8 | M10: 0.2 | N10: El stock intercompany se ajusta antes de que envejezca. | O10: € de stock intercompany −20 % en 6 meses sin roturas en referencias pull. | P10: 46905 | Q10: 47109
A11: MGT | B11: INT-04 | C11: Copiloto de plazos para Comercial | D11: P2R-04 | E11: Demanda Externa | F11: Revisar capacidad para la fecha pedida → la ejecuta un agente (solo una parte: responde la consulta de plazo) | G11: No se propone fecha al entrar el pedido: Joan Carles revisa la capacidad a mano y además hace de atención al cliente. | H11: El cliente pide una fecha y Joan Carles comprueba a mano si hay capacidad y le responde. | I11: Comercial pregunta al copiloto cuándo sale la próxima tirada de una calidad y ancho y responde al cliente sin pasar por Planificación. | J11: Revisar capacidad para la fecha pedida → «Consulta de plazo resuelta por el copiloto» | K11: Atender las consultas que el copiloto no resuelve — persona (Joan Carles) | L11: 0.8 | M11: 0.2 | N11: Comercial resuelve sola las consultas de plazo. | O11: −60 % de consultas de plazo a Planificación. | P11: 46905 | Q11: 47025
A12: MGT | B12: INT-03 | C12: Agente de compras de materiales | D12: P2R-05 | E12: MRP | F12: MRP de materias primas en Excel → la ejecuta un agente (solo una parte: revisa los mensajes del MRP) · Solicitud de compra y pedido → la ejecuta un agente (solo una parte: prepara la solped) | G12: El MRP de materias primas vive en un Excel, el de auxiliares se descuadra y las solicitudes de compra se preparan a mano. | H12: Marta Boyo calcula las materias primas en Excel con la planificación de Joan Carles; Joan Carles lanza el MRP de auxiliares en SAP y crea las solped y los pedidos. | I12: Un agente revisa cada día los mensajes del MRP, propone las solicitudes de compra y avisa de los consumos que se separan del plan; Marta Boyo y Joan Carles aprueban. | J12: MRP de materias primas en Excel → «Mensajes del MRP revisados por el agente» · Solicitud de compra y pedido → «Aprobar la solped propuesta» | K12: Revisar los consumos fuera de plan que marca el agente — persona (Marta Boyo) | L12: 0.8 | M12: 0.2 | N12: Las solicitudes de compra salen preparadas y solo se revisan las excepciones. | O12: ≥ 80 % de las solicitudes propuestas aceptadas sin cambios. | P12: 46905 | Q12: 47109
A13: MGT | B13: INT-05 | C13: Agente de urgencias | D13: P2R-06 | E13: Programación | F13: Encajar la urgencia a mano → la ejecuta un agente (solo una parte: propone si cabe y qué mueve) | G13: Las urgencias, también las de Ondupack fuera de plazo, se encajan a mano, sin alertas ni reglas. | H13: Joan Carles revisa a mano si la urgencia cabe en lo planificado y, si hay varias comprometidas, lo negocia con Comercial. | I13: Un agente comprueba si la urgencia cabe en el ciclo y qué pedidos y combinaciones afecta, y propone la decisión según las reglas. | J13: Encajar la urgencia a mano → «Aprobar la propuesta del agente» | K13: Decidir con Comercial los conflictos que el agente escala — persona (Joan Carles) | L13: 0.75 | M13: 0.25 | N13: Cada urgencia se decide con su impacto delante. | O13: 100 % de las urgencias con impacto calculado. | P13: 46905 | Q13: 47109
A14: MGT | B14: INT-06 | C14: Agente de coordinación de cargas con Ondupack | D14: P2R-08 | E14: Entregas a Ondupack y Cierre | F14: Enviar el stock a Ondupack cada día → la ejecuta un agente (toda la tarea) · Ondupack decide qué se carga al día siguiente → la ejecuta un agente (solo una parte: propone la carga) | G14: La coordinación diaria de entregas con Ondupack lleva unos 16 correos al día. | H14: Cada día Joan Carles envía el stock a Ondupack por correo y Ondupack contesta qué cargar al día siguiente. | I14: Un agente lee las peticiones de Ondupack, comprueba stock y plan y propone la carga del día dentro del mínimo y máximo; Joan Carles aprueba. | J14: Enviar el stock a Ondupack cada día → desaparece · Ondupack decide qué se carga → «Aprobar la carga propuesta» | K14: Resolver las peticiones de Ondupack que no encajan en el mínimo y máximo — persona (Joan Carles) | L14: 0.8 | M14: 0.2 | N14: La coordinación diaria con Ondupack sale preparada y solo se revisan las excepciones. | O14: ≥ 80 % de las cargas propuestas aceptadas sin cambios. | P14: 46905 | Q14: 47109
A15: Ondupack Almendralejo | B15: INT-01 | C15: Agente de escenarios de capacidad | D15: P2R-02 | E15: Carga Capacidad | F15: Carga frente a capacidad con escenarios de 2 a 5 turnos → la ejecuta un agente (prepara los escenarios) · Replanificar ruta, fecha o turnos → la ejecuta un agente (solo una parte: propone, Planificación decide) | G15: La 924 no alcanza los metros planificados y la sobresaturación se ve tarde, por las fechas o porque se llena el almacén intermedio. | H15: Planificación compara a mano escenarios de 2 a 5 turnos en la carga-capacidad de GIO y replanifica ruta, fecha o turnos cuando hay saturación. | I15: Un agente simula turnos, rutas alternativas para descargar la 924 y agrupaciones, y propone el plan con su impacto; Planificación decide. | J15: Replanificar ruta, fecha o turnos → «Aprobar el plan de capacidad propuesto» | K15: Revisar los escenarios de riesgo de la 924 — persona (Planificación con Producción) | L15: 0.7 | M15: 0.3 | N15: Cada saturación llega con un plan propuesto y valorado. | O15: ≥ 70 % de los planes aprobados sin rehacer. | P15: 46844 | Q15: 47026
A16: Ondupack Almendralejo | B16: ACC-07 | C16: Faltas de materia prima | D16: P2R-05 | E16: Papel y Auxiliares | F16: Necesidad de papel por consumo pasado → la ejecuta un agente (solo una parte: revisa las faltas por orden y propone la acción) | G16: La falta de materia prima es el primer problema de la planta: las faltas se ven tarde y se resuelven a mano entre Planificación y Compras. | H16: El papel se pide por consumo pasado y GIO solo ve su stock; las faltas aparecen al liberar y se autorizan a mano con Compras. | I16: Un agente revisa cada día las faltas por orden y propone la acción (adelantar el pedido a MGT, un sustituto aprobado o mover la orden); Planificación y Compras deciden. | J16: Necesidad de papel → «Faltas por orden con acción propuesta» | K16: Aprobar la acción ante cada falta — persona (Planificación y Compras) | L16: 0.8 | M16: 0.2 | N16: Cada falta llega a Planificación con la solución propuesta. | O16: ≥ 80 % de las propuestas aceptadas y −30 % de horas de máquina paradas por falta de materia prima. | P16: 46844 | Q16: 47026
... A18: Ondupack Almendralejo | B18: INT-02 | C18: Agente de causa raíz | D18: P2R-08 | E18: Seguimiento del Servicio | F18: Seguimiento de fechas atrasadas → la ejecuta un agente (solo una parte: clasifica la causa y propone la acción) | G18: Los atrasos y las reprogramaciones no tienen causa registrada, así que se repiten. | H18: Las fechas atrasadas se ven en rojo en GIO y se revisan en la reunión semanal, sin clasificar la causa. | I18: Un agente clasifica cada atraso por causa (velocidad, OEE, falta de papel, cambio del cliente o saturación) y propone la acción y el ajuste de parámetros; Planificación aprueba. | J18: Seguimiento de fechas atrasadas → «Atrasos con causa y acción propuesta» | K18: Aprobar la acción y el ajuste de parámetros — persona (Planificación) | L18: 0.75 | M18: 0.25 | N18: Cada atraso deja una corrección propuesta y las causas dejan de repetirse. | O18: ≥ 90 % de los atrasos con causa y causas repetidas −30 % en 6 meses. | P18: 46844 | Q18: 47026
