Workbook

Sheet Portada
B2: Modelo de planificación corporativo · CL Grupo Industrial
B3: Corporativo define procesos, roles, personas, políticas y KPIs; cada planta ejecuta.
B5: Origen de los datos | C5: Datos del equipo · export de la herramienta · 2026-10-08 · incluye: Análisis E2E de Ondupet, Necesidades de Ondupet y plan de acción 2027-2028
B6: Generado | C6: 08/10/2026
B7: Dónde se edita | C7: En la herramienta Modelo_Planificacion_CL.html; este Excel es una foto para revisar y compartir.
B9: Contenido
B10: Procesos | C10: Catálogo de procesos y actividades de planificación | D10: =COUNTA(Procesos!B:B)-1 -> 44 | E10: actividades
B11: Flujos | C11: Flujos de proceso as-is y to-be por empresa: pasos, responsables y conexiones | D11: =COUNT(Flujos!D:D) -> 103 | E11: cajas
B12: Notas | C12: Notas por empresa y actividad: situación actual, quién, problemas y propuesta | D12: =COUNTA(Notas!E:E)-1-COUNTIF(Notas!E:E,"Sin revisar") -> 22 | E12: actividades revisadas
B13: Madurez | C13: Situación por empresa y proceso
B14: RACI | C14: Matriz RACI por rol, con revisión automática de cada fila | D14: =COUNTIF(RACI!S:S,"OK") -> 44 | E14: filas correctas
B15: RACI as-is | C15: Cómo se hace hoy en cada empresa y diferencias con el estándar | D15: =COUNTA('RACI as-is'!C:C)-1 -> 14 | E15: filas
B16: Roles | C16: Fichas de rol: misión, responsabilidades, qué decide y KPIs | D16: =COUNTA(Roles!A:A)-1 -> 15 | E16: roles
B17: Asignación | C17: Titular y suplente de cada rol en cada empresa | D17: =COUNTA(Asignación!C:C)-1 -> 21 | E17: roles con titular
B18: Organigramas | C18: Organigramas as-is y to-be de cada empresa: puesto, persona y dependencias | D18: =COUNTA(Organigramas!D:D)-1 -> 60 | E18: puestos
B19: Empresas | C19: Perímetro: empresas y plantas | D19: =COUNTA(Empresas!A:A)-1 -> 7 | E19: empresas
B20: Políticas | C20: Políticas de planificación: estándar corporativo y parámetros por planta | D20: =COUNTA(Políticas!A:A)-1 -> 10 | E20: políticas
B21: KPIs | C21: Cuadro de mando común | D21: =COUNTA(KPIs!A:A)-1 -> 12 | E21: KPIs
B22: Reuniones | C22: Cadencia de planificación del grupo | D22: =COUNTA(Reuniones!A:A)-1 -> 0 | E22: reuniones
B23: Decisiones | C23: Decisiones que hay que cerrar con dirección | D23: =COUNTIF(Decisiones!F:F,"Abierta") -> 0 | E23: abiertas
B24: Plan | C24: Plan de acción: acciones por fase, empresa, responsable y fechas | D24: =COUNTA(Plan!B:B)-1 -> 46 | E24: acciones
B25: Gantt | C25: Cronograma mensual del plan de acción (se calcula desde la hoja Plan) | D25: =COUNTIF(Plan!G:G,"Hito") -> 10 | E25: hitos
B27: Leyenda RACI
B28: A | C28: Decide y responde del resultado (una sola por actividad)
B29: R | C29: Lo ejecuta
B30: A/R | C30: Decide y además lo ejecuta
B31: C | C31: Se le consulta antes
B32: I | C32: Se le informa después

Sheet Notas
A1: Empresa | B1: Proceso | C1: ID | D1: Actividad | E1: Situación | F1: Quién lo hace hoy | G1: Herramienta | H1: Frecuencia real | I1: Horas/semana | J1: Cómo se hace hoy | K1: Problemas | L1: Propuesta | M1: Prioridad | N1: Notas | O1: Origen
A2: Corporativo · Planificación | B2: Gobierno y S&OP | C2: G.1 | D2: Modelo de procesos y manual de planificación | E2: Sin revisar | O2: Catálogo
A3: Corporativo · Planificación | B3: Gobierno y S&OP | C3: G.2 | D3: Políticas de planificación | E3: Sin revisar | O3: Catálogo
A4: Corporativo · Planificación | B4: Gobierno y S&OP | C4: G.3 | D4: S&OP mensual del grupo | E4: Sin revisar | O4: Catálogo
A5: Corporativo · Planificación | B5: Gobierno y S&OP | C5: G.4 | D5: Objetivos y revisión de KPIs | E5: Sin revisar | O5: Catálogo
A6: Corporativo · Planificación | B6: Gobierno y S&OP | C6: G.5 | D6: Roles, personas, suplencias y formación | E6: Sin revisar | O6: Catálogo
A7: Corporativo · Planificación | B7: Gobierno y S&OP | C7: G.6 | D7: Gestión de cambios y prioridad de desarrollos | E7: Sin revisar | O7: Catálogo
A8: Corporativo · Planificación | B8: Dato maestro | C8: 1.1 | D8: Datos de planificación del material | E8: Sin revisar | O8: Catálogo
A9: Corporativo · Planificación | B9: Dato maestro | C9: 1.2 | D9: Segmentación ABC/XYZ y estrategia MTS/MTO | E9: Sin revisar | O9: Catálogo
A10: Corporativo · Planificación | B10: Dato maestro | C10: 1.3 | D10: Velocidades, tiempos de cambio y rutas | E10: Sin revisar | O10: Catálogo
A11: Corporativo · Planificación | B11: Dato maestro | C11: 1.4 | D11: Calendario de turnos, días y paradas | E11: Sin revisar | O11: Catálogo
A12: Corporativo · Planificación | B12: Dato maestro | C12: 1.5 | D12: Auditoría de calidad del dato | E12: Sin revisar | O12: Catálogo
A13: Corporativo · Planificación | B13: Demanda | C13: 2.1 | D13: Previsión de demanda | E13: Sin revisar | O13: Catálogo
... A51: Ondupet | B51: Gobierno y S&OP | C51: G.6 | D51: Gestión de cambios y prioridad de desarrollos | E51: Sin revisar | O51: Catálogo
A52: Ondupet | B52: Dato maestro | C52: 1.1 | D52: Datos de planificación del material | E52: Estándar propio | F52: Monica Gordillo | G52: GIO | H52: Bajo demanda (alta de material nuevo) | J52: Monica Gordillo crea los materiales: como es de Comercial, es quien antes se entera de que hace falta uno. Consulta con Calidad las características técnicas, pero no pregunta a Planificación qué estrategia debe llevar. | K52: Planificación no participa en el alta: el material llega sin estrategia (MTS/MTO, ABC) ni ruta revisada. Duda abierta: ¿se consulta a Producción y Mantenimiento la ruta por defecto? | L52: Alta con plantilla única: Comercial lo solicita, Calidad fija las características y Dato maestro asigna estrategia y ruta consultando a Planificación y Producción. Antes de crear, se comprueba que no haya duplicados. | M52: Media | O52: Catálogo
A53: Ondupet | B53: Dato maestro | C53: 1.2 | D53: Segmentación ABC/XYZ y estrategia MTS/MTO | E53: No se hace | F53: Nadie | G53: GIO | H53: Nunca | I53: 0 | J53: NO SE HACE | K53: Falta de coordinación y seguimiento entre planificación y comercial | L53: Cada tres meses debe haber revisión por parte de comercial y planificación para revisar estrategias de productos ya creados y de nueva creación | M53: Alta | N53: Tienen transacción preparada para calculo automático de ABC y estrategias | O53: Catálogo
A54: Ondupet | B54: Dato maestro | C54: 1.3 | D54: Velocidades, tiempos de cambio y rutas | E54: Estándar propio | G54: GIO | H54: Solo al dar de alta; las rutas no se revisan | J54: Las velocidades y los tiempos de cambio dependen del molde, que es un dato fijo del dato maestro. Por eso necesitan mucho menos mantenimiento que en otras plantas. | K54: Las rutas no se actualizan con la carga de capacidad del mes, así que la carga entre máquinas no se equilibra. | L54: Cada mes, Programación revisa las rutas por defecto con la carga del mes, consultando a Producción. Velocidades y tiempos de cambio se revisan solo si cambia el molde o hay desviaciones frente a lo real. | M54: Media | O54: Catálogo
A55: Ondupet | B55: Dato maestro | C55: 1.4 | D55: Calendario de turnos, días y paradas | E55: Sin revisar | O55: Catálogo
A56: Ondupet | B56: Dato maestro | C56: 1.5 | D56: Auditoría de calidad del dato | E56: No se hace | F56: Nadie (correcciones puntuales de Monica Gordillo y su equipo) | G56: GIO · campo «material reemplazante» | H56: Nunca; solo correcciones puntuales | J56: No hay auditoría ni estándar para detectar duplicados, porque no está claro qué características definen un material. Cuando Monica o alguien de su equipo encuentra uno, lo corrige con el campo «material reemplazante», que une el duplicado con el material definitivo sin perder el histórico de ventas ni de producción. | K56: Los duplicados se encuentran por casualidad: no hay análisis del dato maestro ni un criterio de qué define un material. | L56: Definir qué características identifican un material y hacer una auditoría mensual (duplicados, datos incompletos e incoherencias) con su KPI. Se sigue usando «material reemplazante» para unir materiales sin perder histórico. | M56: Media | O56: Catálogo
A57: Ondupet | B57: Demanda | C57: 2.1 | D57: Previsión de demanda | E57: Estándar propio | F57: Manuel Jesus Trinidad | H57: Mensual, sin día de cierre | J57: Cada mes, Manuel Jesus Trinidad carga la previsión de cada material: como mínimo, el mes en curso y los tres siguientes. | K57: No hay día límite para cerrar la previsión. La del mes en curso se cambia sin consultar a Planificación, incluso cuando el material ya está fabricado (no debería estar permitido). | L57: Calendario mensual con día límite de cierre: Planificación propone la previsión estadística y Comercial la ajusta. Después del cierre, el mes en curso queda congelado y cualquier cambio necesita la aprobación de Planificación. | M57: Alta | O57: Catálogo
A58: Ondupet | B58: Demanda | C58: 2.2 | D58: Consenso de la previsión con Comercial | E58: No se hace | F58: Nadie | H58: Nunca | J58: No hay un estándar para que Planificación y Comercial se pongan de acuerdo en qué se va a fabricar. Planificación fabrica lo que diga la previsión (descontando stock, órdenes lanzadas…) y con ella genera los temporales. | K58: No hay plan de demanda acordado: si la previsión es mala, lo son también lo fabricado y los plazos que se dan. | L58: Reunión mensual de consenso (Comercial, Planificación y S&OP) tras cerrar la previsión, que incluya la revisión de temporales (2.5). Si no hay acuerdo, decide S&OP. | M58: Alta | O58: Catálogo
A59: Ondupet | B59: Demanda | C59: 2.3 | D59: Demanda perdida (agotados) | E59: Informal | F59: Monica Gordillo y su equipo | H59: Irregular | J59: Se va de un extremo a otro: épocas con muchos agotados registrados y 2-3 meses sin registrar ninguno, aunque haya roturas. | K59: No está claro qué es un agotado, así que el dato no sirve para corregir la previsión. | L59: Definir qué es un agotado (pedido no servido o rechazado por falta de stock o de plazo), registrarlo a diario con un motivo codificado y revisarlo en el ciclo mensual de previsión. | M59: Media | O59: Catálogo
A60: Ondupet | B60: Demanda | C60: 2.4 | D60: Precisión y sesgo de la previsión | E60: Informal | F60: Manuel Jesus Trinidad y Victoriano Perez | H60: Reunión mensual | J60: Hay una reunión mensual de accuracy entre Manuel Jesus Trinidad y Victoriano Perez, pero Comercial no se implica y Planificación no la impulsa. | K60: Se ven desviaciones enormes en algunos materiales y no se hace nada. | L60: KPI mensual de precisión y sesgo por familia y material. Los diez peores se ven en la reunión de consenso y cada desviación tiene responsable y acción, que se revisa al mes siguiente. | M60: Media | O60: Catálogo
A61: Ondupet | B61: Demanda | C61: 2.5 | D61: Revisión de temporales | E61: Informal | F61: Victoriano Perez | H61: Mensual, sin revisión conjunta | J61: Planificación genera los temporales (previsiones de fabricación) a partir de la previsión de Comercial. Sirven para reservar tiempo de cada familia en el ciclo y poder dar plazos en la consulta de plazos. | K61: No se revisan con Comercial ni con un criterio común: si la previsión no es buena, los plazos que se dan tampoco. | L61: Revisión mensual de los temporales con la previsión ya consensuada, dentro de la reunión de consenso (2.2). | M61: Alta | N61: Del análisis E2E: falta decidir si es un apartado propio o forma parte de 2.2 (consenso de la previsión). | O61: Propio de la planta
A62: Ondupet | B62: Cartera | C62: 3.1 | D62: Revisión diaria de la cartera | E62: Estándar propio | F62: Monica Gordillo (Comercial) y Victoriano Perez (Planificación), por separado | H62: Diaria | J62: Cada día, Comercial y Planificación revisan por separado la cartera de pedidos, el stock disponible y las cargas, y lo ponen en común en la reunión de producción. | K62: No hay acuerdo sobre las fechas de entrega de cargas y pedidos: aunque Planificación avise de que no llega a la fecha del cliente, no se cambia. Y eso que el pedido tiene dos fechas: la que pidió el cliente y otra para medir retrasos. | L62: Una sola revisión con una sola fuente de datos. Planificación confirma una fecha viable y Comercial la negocia con el cliente. Se usan las dos fechas del pedido: la solicitada para medir el servicio y la confirmada para planificar. | M62: Alta | O62: Catálogo
A63: Ondupet | B63: Cartera | C63: 3.2 | D63: Cargas vinculadas a pedidos | E63: Estándar propio | F63: Monica Gordillo y su equipo (Victoriano Perez envía el reporte de atrasos) | H63: Diaria | J63: Cada día, Monica y su equipo vinculan todas las cargas a sus pedidos. Planificación envía un reporte diario de cargas atrasadas. | K63: A veces se crean cargas por mucha más cantidad que la del pedido y con fechas de entrega imposibles de cumplir. | L63: Al crear la carga, validar que la cantidad no supere lo pendiente del pedido y que la fecha sea la confirmada. El reporte de atrasos pasa a ser un KPI diario con su causa. | M63: Media | O63: Catálogo
A64: Ondupet | B64: Cartera | C64: 3.3 | D64: Cierre (saldado) de pedidos | E64: Informal | F64: Monica Gordillo y su equipo | H64: Sin pauta | J64: Comercial salda los pedidos. Da la sensación de que algunos, ya planificados, se saldan sin avisar a Planificación. | K64: Planificación puede seguir fabricando o reservando capacidad para pedidos que ya están cerrados. | L64: Saldado semanal con una regla común: Planificación propone qué pedidos saldar (completos o con un resto mínimo) y Comercial lo valida. Si se salda un pedido planificado, Planificación se entera en el momento. | M64: Media | O64: Catálogo
A65: Ondupet | B65: Cartera | C65: 3.4 | D65: Prioridad de pedidos en conflicto | E65: Informal | F65: Comercial (Monica Gordillo, Manuel Jesus Trinidad) y Victoriano Perez; decide Manuel Castro si no hay acuerdo | H65: Bajo demanda (por teléfono) | J65: Cuando hay varios pedidos comprometidos, Comercial (Monica y su equipo, o incluso Manuel Jesus) llama a Planificación para buscar soluciones. Si no se ponen de acuerdo, llaman a Manuel Castro (director de planta) para que decida. | K65: No hay reglas de prioridad: se resuelve caso a caso por teléfono y acaba en el director de planta. | L65: Reglas de prioridad acordadas (tipo de cliente, fecha comprometida, margen y stock de seguridad) que aplica Planificación consultando a Comercial y Programación. Si afecta a otras plantas, decide S&OP. Al director de planta solo se le informa. | M65: Media | O65: Catálogo
A66: Ondupet | B66: Necesidades | C66: 4.1 | D66: Ejecución y revisión del MRP | E66: Estándar propio | F66: Victoriano Perez (Planificación) y Barbara Ayuste (Compras) | G66: SAP · MRP y transacción de faltas de materia prima y auxiliares | H66: Semanal | J66: Cada semana, Planificación y Compras analizan juntos el MRP. Tienen preparada en SAP una transacción que muestra las faltas de materias primas y auxiliares. | K66: No se han detectado problemas. Falta confirmar cómo se tratan las excepciones del MRP y quién lanza los pedidos de las faltas. | L66: Tomarlo como base del estándar del grupo: revisión semanal Planificación–Compras con la transacción de faltas, incluyendo materias primas y auxiliares (4.4) en la misma revisión. | M66: Baja | O66: Catálogo
A67: Ondupet | B67: Necesidades | C67: 4.2 | D67: Propuesta de fabricación de producto terminado | E67: Estándar propio | F67: Victoriano Perez | G67: GIO · pantalla de propuesta de fabricación (por material y pedido) | H67: Diaria | J67: En GIO hay una pantalla que da, por material (y por pedido en los MTO), una propuesta de fabricación. Victoriano la consulta cada día y la corrige si ve desviaciones del accuracy o si Comercial le llama. | K67: Las correcciones son manuales y dependen de la persona; los cambios de Comercial llegan por teléfono y no queda registro del motivo. Los errores de la previsión (2.4) acaban corrigiéndose aquí. | L67: Corregir la propuesta solo con un motivo registrado y con reglas comunes. Los cambios de Comercial entran por la previsión o la cartera, no por llamada, y el KPI de accuracy indica dónde mirar. | M67: Media | O67: Catálogo
A68: Ondupet | B68: Necesidades | C68: 4.3 | D68: Necesidades de semielaborado | E68: Estándar propio | F68: Victoriano Perez | G68: GIO · pantalla de necesidades de semielaborado | H68: Diaria | J68: Una pantalla de GIO propone automáticamente las necesidades de semielaborado. Victoriano la revisa cada día con la misma lógica que el producto terminado. | K68: Igual que en 4.2: correcciones manuales sin registro que dependen de una sola persona. | L68: Mismas reglas de corrección que en 4.2. A medio plazo, que la revise el planificador de materiales para repartir la carga de Victoriano. | M68: Media | O68: Catálogo
A69: Ondupet | B69: Necesidades | C69: 4.4 | D69: Necesidades de materias primas y auxiliares | E69: Estándar propio | F69: Victoriano Perez y Barbara Ayuste (dentro de 4.1) | G69: SAP · transacción de faltas | H69: Semanal | J69: Se hace dentro de la revisión semanal del MRP (4.1). | L69: Fusionar 4.4 con 4.1 en el catálogo corporativo (lo propone el equipo en el E2E). | M69: Baja | N69: Del E2E: está duplicado, debería ir incluido en 4.1. | O69: Catálogo
A70: Ondupet | B70: Capacidad | C70: 5.1 | D70: Carga de capacidad y saturación por línea | E70: Sin revisar | O70: Catálogo
A71: Ondupet | B71: Capacidad | C71: 5.2 | D71: Balanceo entre líneas y plantas | E71: Sin revisar | O71: Catálogo
A72: Ondupet | B72: Capacidad | C72: 5.3 | D72: Saturación de almacenes | E72: Sin revisar | O72: Catálogo
A73: Ondupet | B73: Programación | C73: 6.1 | D73: Plan de producción semanal | E73: Sin revisar | O73: Catálogo
A74: Ondupet | B74: Programación | C74: 6.2 | D74: Secuenciación, ciclos y combinación | E74: Sin revisar | O74: Catálogo
A75: Ondupet | B75: Programación | C75: 6.3 | D75: Lanzamiento de órdenes a máquina | E75: Sin revisar | O75: Catálogo
A76: Ondupet | B76: Programación | C76: 6.4 | D76: Replanificación ante incidencias | E76: Sin revisar | O76: Catálogo
A77: Ondupet | B77: Programación | C77: 6.5 | D77: Cronograma de cambios | E77: Sin revisar | O77: Catálogo
A78: Ondupet | B78: Entrega | C78: 7.1 | D78: Compromiso de fecha al cliente | E78: Sin revisar | O78: Catálogo
A79: Ondupet | B79: Entrega | C79: 7.2 | D79: Reserva de stock a pedidos | E79: Sin revisar | O79: Catálogo
A80: Ondupet | B80: Entrega | C80: 7.3 | D80: Retrasos y aviso al cliente | E80: Sin revisar | O80: Catálogo
A81: Ondupet | B81: Entrega | C81: 7.4 | D81: Coordinación con expediciones | E81: Sin revisar | O81: Catálogo
... A310: Papresa | B310: Intercompany | C310: I.5 | D310: Control y cierre de pedidos intercompany | E310: Sin revisar | O310: Catálogo

Sheet Madurez
A1: Actividades alineadas con el estándar / actividades aplicables
A2: Se calcula desde la hoja Notas.
A4: Empresa | B4: Gobierno y S&OP | C4: Dato maestro | D4: Demanda | E4: Cartera | F4: Necesidades | G4: Capacidad | H4: Programación | I4: Entrega | J4: Control | K4: Intercompany | L4: Total
A5: Corporativo · Planificación | B5: =IFERROR(COUNTIFS(Notas!$A:$A,$A5,Notas!$B:$B,"Gobierno y S&OP",Notas!$E:$E,"Alineado con el estándar")/(COUNTIFS(Notas!$A:$A,$A5,Notas!$B:$B,"Gobierno y S&OP")-COUNTIFS(Notas!$A:$A,$A5,Notas!$B:$B,"Gobierno y S&OP",Notas!$E:$E,"No aplica")),0) -> 0 | C5: =IFERROR(COUNTIFS(Notas!$A:$A,$A5,Notas!$B:$B,"Dato maestro",Notas!$E:$E,"Alineado con el estándar")/(COUNTIFS(Notas!$A:$A,$A5,Notas!$B:$B,"Dato maestro")-COUNTIFS(Notas!$A:$A,$A5,Notas!$B:$B,"Dato maestro",Notas!$E:$E,"No aplica")),0) -> 0 | D5: =IFERROR(COUNTIFS(Notas!$A:$A,$A5,Notas!$B:$B,"Demanda",Notas!$E:$E,"Alineado con el estándar")/(COUNTIFS(Notas!$A:$A,$A5,Notas!$B:$B,"Demanda")-COUNTIFS(Notas!$A:$A,$A5,Notas!$B:$B,"Demanda",Notas!$E:$E,"No aplica")),0) -> 0 | E5: =IFERROR(COUNTIFS(Notas!$A:$A,$A5,Notas!$B:$B,"Cartera",Notas!$E:$E,"Alineado con el estándar")/(COUNTIFS(Notas!$A:$A,$A5,Notas!$B:$B,"Cartera")-COUNTIFS(Notas!$A:$A,$A5,Notas!$B:$B,"Cartera",Notas!$E:$E,"No aplica")),0) -> 0 | F5: =IFERROR(COUNTIFS(Notas!$A:$A,$A5,Notas!$B:$B,"Necesidades",Notas!$E:$E,"Alineado con el estándar")/(COUNTIFS(Notas!$A:$A,$A5,Notas!$B:$B,"Necesidades")-COUNTIFS(Notas!$A:$A,$A5,Notas!$B:$B,"Necesidades",Notas!$E:$E,"No aplica")),0) -> 0 | G5: =IFERROR(COUNTIFS(Notas!$A:$A,$A5,Notas!$B:$B,"Capacidad",Notas!$E:$E,"Alineado con el estándar")/(COUNTIFS(Notas!$A:$A,$A5,Notas!$B:$B,"Capacidad")-COUNTIFS(Notas!$A:$A,$A5,Notas!$B:$B,"Capacidad",Notas!$E:$E,"No aplica")),0) -> 0 | H5: =IFERROR(COUNTIFS(Notas!$A:$A,$A5,Notas!$B:$B,"Programación",Notas!$E:$E,"Alineado con el estándar")/(COUNTIFS(Notas!$A:$A,$A5,Notas!$B:$B,"Programación")-COUNTIFS(Notas!$A:$A,$A5,Notas!$B:$B,"Programación",Notas!$E:$E,"No aplica")),0) -> 0 | I5: =IFERROR(COUNTIFS(Notas!$A:$A,$A5,Notas!$B:$B,"Entrega",Notas!$E:$E,"Alineado con el estándar")/(COUNTIFS(Notas!$A:$A,$A5,Notas!$B:$B,"Entrega")-COUNTIFS(Notas!$A:$A,$A5,Notas!$B:$B,"Entrega",Notas!$E:$E,"No aplica")),0) -> 0 | J5: =IFERROR(COUNTIFS(Notas!$A:$A,$A5,Notas!$B:$B,"Control",Notas!$E:$E,"Alineado con el estándar")/(COUNTIFS(Notas!$A:$A,$A5,Notas!$B:$B,"Control")-COUNTIFS(Notas!$A:$A,$A5,Notas!$B:$B,"Control",Notas!$E:$E,"No aplica")),0) -> 0 | K5: =IFERROR(COUNTIFS(Notas!$A:$A,$A5,Notas!$B:$B,"Intercompany",Notas!$E:$E,"Alineado con el estándar")/(COUNTIFS(Notas!$A:$A,$A5,Notas!$B:$B,"Intercompany")-COUNTIFS(Notas!$A:$A,$A5,Notas!$B:$B,"Intercompany",Notas!$E:$E,"No aplica")),0) -> 0 | L5: =IFERROR(COUNTIFS(Notas!$A:$A,$A5,Notas!$E:$E,"Alineado con el estándar")/(COUNTIFS(Notas!$A:$A,$A5)-COUNTIFS(Notas!$A:$A,$A5,Notas!$E:$E,"No aplica")),0) -> 0
A6: Ondupet | B6: =IFERROR(COUNTIFS(Notas!$A:$A,$A6,Notas!$B:$B,"Gobierno y S&OP",Notas!$E:$E,"Alineado con el estándar")/(COUNTIFS(Notas!$A:$A,$A6,Notas!$B:$B,"Gobierno y S&OP")-COUNTIFS(Notas!$A:$A,$A6,Notas!$B:$B,"Gobierno y S&OP",Notas!$E:$E,"No aplica")),0) -> 0 | C6: =IFERROR(COUNTIFS(Notas!$A:$A,$A6,Notas!$B:$B,"Dato maestro",Notas!$E:$E,"Alineado con el estándar")/(COUNTIFS(Notas!$A:$A,$A6,Notas!$B:$B,"Dato maestro")-COUNTIFS(Notas!$A:$A,$A6,Notas!$B:$B,"Dato maestro",Notas!$E:$E,"No aplica")),0) -> 0 | D6: =IFERROR(COUNTIFS(Notas!$A:$A,$A6,Notas!$B:$B,"Demanda",Notas!$E:$E,"Alineado con el estándar")/(COUNTIFS(Notas!$A:$A,$A6,Notas!$B:$B,"Demanda")-COUNTIFS(Notas!$A:$A,$A6,Notas!$B:$B,"Demanda",Notas!$E:$E,"No aplica")),0) -> 0 | E6: =IFERROR(COUNTIFS(Notas!$A:$A,$A6,Notas!$B:$B,"Cartera",Notas!$E:$E,"Alineado con el estándar")/(COUNTIFS(Notas!$A:$A,$A6,Notas!$B:$B,"Cartera")-COUNTIFS(Notas!$A:$A,$A6,Notas!$B:$B,"Cartera",Notas!$E:$E,"No aplica")),0) -> 0 | F6: =IFERROR(COUNTIFS(Notas!$A:$A,$A6,Notas!$B:$B,"Necesidades",Notas!$E:$E,"Alineado con el estándar")/(COUNTIFS(Notas!$A:$A,$A6,Notas!$B:$B,"Necesidades")-COUNTIFS(Notas!$A:$A,$A6,Notas!$B:$B,"Necesidades",Notas!$E:$E,"No aplica")),0) -> 0 | G6: =IFERROR(COUNTIFS(Notas!$A:$A,$A6,Notas!$B:$B,"Capacidad",Notas!$E:$E,"Alineado con el estándar")/(COUNTIFS(Notas!$A:$A,$A6,Notas!$B:$B,"Capacidad")-COUNTIFS(Notas!$A:$A,$A6,Notas!$B:$B,"Capacidad",Notas!$E:$E,"No aplica")),0) -> 0 | H6: =IFERROR(COUNTIFS(Notas!$A:$A,$A6,Notas!$B:$B,"Programación",Notas!$E:$E,"Alineado con el estándar")/(COUNTIFS(Notas!$A:$A,$A6,Notas!$B:$B,"Programación")-COUNTIFS(Notas!$A:$A,$A6,Notas!$B:$B,"Programación",Notas!$E:$E,"No aplica")),0) -> 0 | I6: =IFERROR(COUNTIFS(Notas!$A:$A,$A6,Notas!$B:$B,"Entrega",Notas!$E:$E,"Alineado con el estándar")/(COUNTIFS(Notas!$A:$A,$A6,Notas!$B:$B,"Entrega")-COUNTIFS(Notas!$A:$A,$A6,Notas!$B:$B,"Entrega",Notas!$E:$E,"No aplica")),0) -> 0 | J6: =IFERROR(COUNTIFS(Notas!$A:$A,$A6,Notas!$B:$B,"Control",Notas!$E:$E,"Alineado con el estándar")/(COUNTIFS(Notas!$A:$A,$A6,Notas!$B:$B,"Control")-COUNTIFS(Notas!$A:$A,$A6,Notas!$B:$B,"Control",Notas!$E:$E,"No aplica")),0) -> 0 | K6: =IFERROR(COUNTIFS(Notas!$A:$A,$A6,Notas!$B:$B,"Intercompany",Notas!$E:$E,"Alineado con el estándar")/(COUNTIFS(Notas!$A:$A,$A6,Notas!$B:$B,"Intercompany")-COUNTIFS(Notas!$A:$A,$A6,Notas!$B:$B,"Intercompany",Notas!$E:$E,"No aplica")),0) -> 0 | L6: =IFERROR(COUNTIFS(Notas!$A:$A,$A6,Notas!$E:$E,"Alineado con el estándar")/(COUNTIFS(Notas!$A:$A,$A6)-COUNTIFS(Notas!$A:$A,$A6,Notas!$E:$E,"No aplica")),0) -> 0
A7: Ondupack Almendralejo | B7: =IFERROR(COUNTIFS(Notas!$A:$A,$A7,Notas!$B:$B,"Gobierno y S&OP",Notas!$E:$E,"Alineado con el estándar")/(COUNTIFS(Notas!$A:$A,$A7,Notas!$B:$B,"Gobierno y S&OP")-COUNTIFS(Notas!$A:$A,$A7,Notas!$B:$B,"Gobierno y S&OP",Notas!$E:$E,"No aplica")),0) -> 0 | C7: =IFERROR(COUNTIFS(Notas!$A:$A,$A7,Notas!$B:$B,"Dato maestro",Notas!$E:$E,"Alineado con el estándar")/(COUNTIFS(Notas!$A:$A,$A7,Notas!$B:$B,"Dato maestro")-COUNTIFS(Notas!$A:$A,$A7,Notas!$B:$B,"Dato maestro",Notas!$E:$E,"No aplica")),0) -> 0 | D7: =IFERROR(COUNTIFS(Notas!$A:$A,$A7,Notas!$B:$B,"Demanda",Notas!$E:$E,"Alineado con el estándar")/(COUNTIFS(Notas!$A:$A,$A7,Notas!$B:$B,"Demanda")-COUNTIFS(Notas!$A:$A,$A7,Notas!$B:$B,"Demanda",Notas!$E:$E,"No aplica")),0) -> 0 | E7: =IFERROR(COUNTIFS(Notas!$A:$A,$A7,Notas!$B:$B,"Cartera",Notas!$E:$E,"Alineado con el estándar")/(COUNTIFS(Notas!$A:$A,$A7,Notas!$B:$B,"Cartera")-COUNTIFS(Notas!$A:$A,$A7,Notas!$B:$B,"Cartera",Notas!$E:$E,"No aplica")),0) -> 0 | F7: =IFERROR(COUNTIFS(Notas!$A:$A,$A7,Notas!$B:$B,"Necesidades",Notas!$E:$E,"Alineado con el estándar")/(COUNTIFS(Notas!$A:$A,$A7,Notas!$B:$B,"Necesidades")-COUNTIFS(Notas!$A:$A,$A7,Notas!$B:$B,"Necesidades",Notas!$E:$E,"No aplica")),0) -> 0 | G7: =IFERROR(COUNTIFS(Notas!$A:$A,$A7,Notas!$B:$B,"Capacidad",Notas!$E:$E,"Alineado con el estándar")/(COUNTIFS(Notas!$A:$A,$A7,Notas!$B:$B,"Capacidad")-COUNTIFS(Notas!$A:$A,$A7,Notas!$B:$B,"Capacidad",Notas!$E:$E,"No aplica")),0) -> 0 | H7: =IFERROR(COUNTIFS(Notas!$A:$A,$A7,Notas!$B:$B,"Programación",Notas!$E:$E,"Alineado con el estándar")/(COUNTIFS(Notas!$A:$A,$A7,Notas!$B:$B,"Programación")-COUNTIFS(Notas!$A:$A,$A7,Notas!$B:$B,"Programación",Notas!$E:$E,"No aplica")),0) -> 0 | I7: =IFERROR(COUNTIFS(Notas!$A:$A,$A7,Notas!$B:$B,"Entrega",Notas!$E:$E,"Alineado con el estándar")/(COUNTIFS(Notas!$A:$A,$A7,Notas!$B:$B,"Entrega")-COUNTIFS(Notas!$A:$A,$A7,Notas!$B:$B,"Entrega",Notas!$E:$E,"No aplica")),0) -> 0 | J7: =IFERROR(COUNTIFS(Notas!$A:$A,$A7,Notas!$B:$B,"Control",Notas!$E:$E,"Alineado con el estándar")/(COUNTIFS(Notas!$A:$A,$A7,Notas!$B:$B,"Control")-COUNTIFS(Notas!$A:$A,$A7,Notas!$B:$B,"Control",Notas!$E:$E,"No aplica")),0) -> 0 | K7: =IFERROR(COUNTIFS(Notas!$A:$A,$A7,Notas!$B:$B,"Intercompany",Notas!$E:$E,"Alineado con el estándar")/(COUNTIFS(Notas!$A:$A,$A7,Notas!$B:$B,"Intercompany")-COUNTIFS(Notas!$A:$A,$A7,Notas!$B:$B,"Intercompany",Notas!$E:$E,"No aplica")),0) -> 0 | L7: =IFERROR(COUNTIFS(Notas!$A:$A,$A7,Notas!$E:$E,"Alineado con el estándar")/(COUNTIFS(Notas!$A:$A,$A7)-COUNTIFS(Notas!$A:$A,$A7,Notas!$E:$E,"No aplica")),0) -> 0
A8: Ondupack Navalmoral | B8: =IFERROR(COUNTIFS(Notas!$A:$A,$A8,Notas!$B:$B,"Gobierno y S&OP",Notas!$E:$E,"Alineado con el estándar")/(COUNTIFS(Notas!$A:$A,$A8,Notas!$B:$B,"Gobierno y S&OP")-COUNTIFS(Notas!$A:$A,$A8,Notas!$B:$B,"Gobierno y S&OP",Notas!$E:$E,"No aplica")),0) -> 0 | C8: =IFERROR(COUNTIFS(Notas!$A:$A,$A8,Notas!$B:$B,"Dato maestro",Notas!$E:$E,"Alineado con el estándar")/(COUNTIFS(Notas!$A:$A,$A8,Notas!$B:$B,"Dato maestro")-COUNTIFS(Notas!$A:$A,$A8,Notas!$B:$B,"Dato maestro",Notas!$E:$E,"No aplica")),0) -> 0 | D8: =IFERROR(COUNTIFS(Notas!$A:$A,$A8,Notas!$B:$B,"Demanda",Notas!$E:$E,"Alineado con el estándar")/(COUNTIFS(Notas!$A:$A,$A8,Notas!$B:$B,"Demanda")-COUNTIFS(Notas!$A:$A,$A8,Notas!$B:$B,"Demanda",Notas!$E:$E,"No aplica")),0) -> 0 | E8: =IFERROR(COUNTIFS(Notas!$A:$A,$A8,Notas!$B:$B,"Cartera",Notas!$E:$E,"Alineado con el estándar")/(COUNTIFS(Notas!$A:$A,$A8,Notas!$B:$B,"Cartera")-COUNTIFS(Notas!$A:$A,$A8,Notas!$B:$B,"Cartera",Notas!$E:$E,"No aplica")),0) -> 0 | F8: =IFERROR(COUNTIFS(Notas!$A:$A,$A8,Notas!$B:$B,"Necesidades",Notas!$E:$E,"Alineado con el estándar")/(COUNTIFS(Notas!$A:$A,$A8,Notas!$B:$B,"Necesidades")-COUNTIFS(Notas!$A:$A,$A8,Notas!$B:$B,"Necesidades",Notas!$E:$E,"No aplica")),0) -> 0 | G8: =IFERROR(COUNTIFS(Notas!$A:$A,$A8,Notas!$B:$B,"Capacidad",Notas!$E:$E,"Alineado con el estándar")/(COUNTIFS(Notas!$A:$A,$A8,Notas!$B:$B,"Capacidad")-COUNTIFS(Notas!$A:$A,$A8,Notas!$B:$B,"Capacidad",Notas!$E:$E,"No aplica")),0) -> 0 | H8: =IFERROR(COUNTIFS(Notas!$A:$A,$A8,Notas!$B:$B,"Programación",Notas!$E:$E,"Alineado con el estándar")/(COUNTIFS(Notas!$A:$A,$A8,Notas!$B:$B,"Programación")-COUNTIFS(Notas!$A:$A,$A8,Notas!$B:$B,"Programación",Notas!$E:$E,"No aplica")),0) -> 0 | I8: =IFERROR(COUNTIFS(Notas!$A:$A,$A8,Notas!$B:$B,"Entrega",Notas!$E:$E,"Alineado con el estándar")/(COUNTIFS(Notas!$A:$A,$A8,Notas!$B:$B,"Entrega")-COUNTIFS(Notas!$A:$A,$A8,Notas!$B:$B,"Entrega",Notas!$E:$E,"No aplica")),0) -> 0 | J8: =IFERROR(COUNTIFS(Notas!$A:$A,$A8,Notas!$B:$B,"Control",Notas!$E:$E,"Alineado con el estándar")/(COUNTIFS(Notas!$A:$A,$A8,Notas!$B:$B,"Control")-COUNTIFS(Notas!$A:$A,$A8,Notas!$B:$B,"Control",Notas!$E:$E,"No aplica")),0) -> 0 | K8: =IFERROR(COUNTIFS(Notas!$A:$A,$A8,Notas!$B:$B,"Intercompany",Notas!$E:$E,"Alineado con el estándar")/(COUNTIFS(Notas!$A:$A,$A8,Notas!$B:$B,"Intercompany")-COUNTIFS(Notas!$A:$A,$A8,Notas!$B:$B,"Intercompany",Notas!$E:$E,"No aplica")),0) -> 0 | L8: =IFERROR(COUNTIFS(Notas!$A:$A,$A8,Notas!$E:$E,"Alineado con el estándar")/(COUNTIFS(Notas!$A:$A,$A8)-COUNTIFS(Notas!$A:$A,$A8,Notas!$E:$E,"No aplica")),0) -> 0
A9: MGT | B9: =IFERROR(COUNTIFS(Notas!$A:$A,$A9,Notas!$B:$B,"Gobierno y S&OP",Notas!$E:$E,"Alineado con el estándar")/(COUNTIFS(Notas!$A:$A,$A9,Notas!$B:$B,"Gobierno y S&OP")-COUNTIFS(Notas!$A:$A,$A9,Notas!$B:$B,"Gobierno y S&OP",Notas!$E:$E,"No aplica")),0) -> 0 | C9: =IFERROR(COUNTIFS(Notas!$A:$A,$A9,Notas!$B:$B,"Dato maestro",Notas!$E:$E,"Alineado con el estándar")/(COUNTIFS(Notas!$A:$A,$A9,Notas!$B:$B,"Dato maestro")-COUNTIFS(Notas!$A:$A,$A9,Notas!$B:$B,"Dato maestro",Notas!$E:$E,"No aplica")),0) -> 0 | D9: =IFERROR(COUNTIFS(Notas!$A:$A,$A9,Notas!$B:$B,"Demanda",Notas!$E:$E,"Alineado con el estándar")/(COUNTIFS(Notas!$A:$A,$A9,Notas!$B:$B,"Demanda")-COUNTIFS(Notas!$A:$A,$A9,Notas!$B:$B,"Demanda",Notas!$E:$E,"No aplica")),0) -> 0 | E9: =IFERROR(COUNTIFS(Notas!$A:$A,$A9,Notas!$B:$B,"Cartera",Notas!$E:$E,"Alineado con el estándar")/(COUNTIFS(Notas!$A:$A,$A9,Notas!$B:$B,"Cartera")-COUNTIFS(Notas!$A:$A,$A9,Notas!$B:$B,"Cartera",Notas!$E:$E,"No aplica")),0) -> 0 | F9: =IFERROR(COUNTIFS(Notas!$A:$A,$A9,Notas!$B:$B,"Necesidades",Notas!$E:$E,"Alineado con el estándar")/(COUNTIFS(Notas!$A:$A,$A9,Notas!$B:$B,"Necesidades")-COUNTIFS(Notas!$A:$A,$A9,Notas!$B:$B,"Necesidades",Notas!$E:$E,"No aplica")),0) -> 0 | G9: =IFERROR(COUNTIFS(Notas!$A:$A,$A9,Notas!$B:$B,"Capacidad",Notas!$E:$E,"Alineado con el estándar")/(COUNTIFS(Notas!$A:$A,$A9,Notas!$B:$B,"Capacidad")-COUNTIFS(Notas!$A:$A,$A9,Notas!$B:$B,"Capacidad",Notas!$E:$E,"No aplica")),0) -> 0 | H9: =IFERROR(COUNTIFS(Notas!$A:$A,$A9,Notas!$B:$B,"Programación",Notas!$E:$E,"Alineado con el estándar")/(COUNTIFS(Notas!$A:$A,$A9,Notas!$B:$B,"Programación")-COUNTIFS(Notas!$A:$A,$A9,Notas!$B:$B,"Programación",Notas!$E:$E,"No aplica")),0) -> 0 | I9: =IFERROR(COUNTIFS(Notas!$A:$A,$A9,Notas!$B:$B,"Entrega",Notas!$E:$E,"Alineado con el estándar")/(COUNTIFS(Notas!$A:$A,$A9,Notas!$B:$B,"Entrega")-COUNTIFS(Notas!$A:$A,$A9,Notas!$B:$B,"Entrega",Notas!$E:$E,"No aplica")),0) -> 0 | J9: =IFERROR(COUNTIFS(Notas!$A:$A,$A9,Notas!$B:$B,"Control",Notas!$E:$E,"Alineado con el estándar")/(COUNTIFS(Notas!$A:$A,$A9,Notas!$B:$B,"Control")-COUNTIFS(Notas!$A:$A,$A9,Notas!$B:$B,"Control",Notas!$E:$E,"No aplica")),0) -> 0 | K9: =IFERROR(COUNTIFS(Notas!$A:$A,$A9,Notas!$B:$B,"Intercompany",Notas!$E:$E,"Alineado con el estándar")/(COUNTIFS(Notas!$A:$A,$A9,Notas!$B:$B,"Intercompany")-COUNTIFS(Notas!$A:$A,$A9,Notas!$B:$B,"Intercompany",Notas!$E:$E,"No aplica")),0) -> 0 | L9: =IFERROR(COUNTIFS(Notas!$A:$A,$A9,Notas!$E:$E,"Alineado con el estándar")/(COUNTIFS(Notas!$A:$A,$A9)-COUNTIFS(Notas!$A:$A,$A9,Notas!$E:$E,"No aplica")),0) -> 0
A10: PDA | B10: =IFERROR(COUNTIFS(Notas!$A:$A,$A10,Notas!$B:$B,"Gobierno y S&OP",Notas!$E:$E,"Alineado con el estándar")/(COUNTIFS(Notas!$A:$A,$A10,Notas!$B:$B,"Gobierno y S&OP")-COUNTIFS(Notas!$A:$A,$A10,Notas!$B:$B,"Gobierno y S&OP",Notas!$E:$E,"No aplica")),0) -> 0 | C10: =IFERROR(COUNTIFS(Notas!$A:$A,$A10,Notas!$B:$B,"Dato maestro",Notas!$E:$E,"Alineado con el estándar")/(COUNTIFS(Notas!$A:$A,$A10,Notas!$B:$B,"Dato maestro")-COUNTIFS(Notas!$A:$A,$A10,Notas!$B:$B,"Dato maestro",Notas!$E:$E,"No aplica")),0) -> 0 | D10: =IFERROR(COUNTIFS(Notas!$A:$A,$A10,Notas!$B:$B,"Demanda",Notas!$E:$E,"Alineado con el estándar")/(COUNTIFS(Notas!$A:$A,$A10,Notas!$B:$B,"Demanda")-COUNTIFS(Notas!$A:$A,$A10,Notas!$B:$B,"Demanda",Notas!$E:$E,"No aplica")),0) -> 0 | E10: =IFERROR(COUNTIFS(Notas!$A:$A,$A10,Notas!$B:$B,"Cartera",Notas!$E:$E,"Alineado con el estándar")/(COUNTIFS(Notas!$A:$A,$A10,Notas!$B:$B,"Cartera")-COUNTIFS(Notas!$A:$A,$A10,Notas!$B:$B,"Cartera",Notas!$E:$E,"No aplica")),0) -> 0 | F10: =IFERROR(COUNTIFS(Notas!$A:$A,$A10,Notas!$B:$B,"Necesidades",Notas!$E:$E,"Alineado con el estándar")/(COUNTIFS(Notas!$A:$A,$A10,Notas!$B:$B,"Necesidades")-COUNTIFS(Notas!$A:$A,$A10,Notas!$B:$B,"Necesidades",Notas!$E:$E,"No aplica")),0) -> 0 | G10: =IFERROR(COUNTIFS(Notas!$A:$A,$A10,Notas!$B:$B,"Capacidad",Notas!$E:$E,"Alineado con el estándar")/(COUNTIFS(Notas!$A:$A,$A10,Notas!$B:$B,"Capacidad")-COUNTIFS(Notas!$A:$A,$A10,Notas!$B:$B,"Capacidad",Notas!$E:$E,"No aplica")),0) -> 0 | H10: =IFERROR(COUNTIFS(Notas!$A:$A,$A10,Notas!$B:$B,"Programación",Notas!$E:$E,"Alineado con el estándar")/(COUNTIFS(Notas!$A:$A,$A10,Notas!$B:$B,"Programación")-COUNTIFS(Notas!$A:$A,$A10,Notas!$B:$B,"Programación",Notas!$E:$E,"No aplica")),0) -> 0 | I10: =IFERROR(COUNTIFS(Notas!$A:$A,$A10,Notas!$B:$B,"Entrega",Notas!$E:$E,"Alineado con el estándar")/(COUNTIFS(Notas!$A:$A,$A10,Notas!$B:$B,"Entrega")-COUNTIFS(Notas!$A:$A,$A10,Notas!$B:$B,"Entrega",Notas!$E:$E,"No aplica")),0) -> 0 | J10: =IFERROR(COUNTIFS(Notas!$A:$A,$A10,Notas!$B:$B,"Control",Notas!$E:$E,"Alineado con el estándar")/(COUNTIFS(Notas!$A:$A,$A10,Notas!$B:$B,"Control")-COUNTIFS(Notas!$A:$A,$A10,Notas!$B:$B,"Control",Notas!$E:$E,"No aplica")),0) -> 0 | K10: =IFERROR(COUNTIFS(Notas!$A:$A,$A10,Notas!$B:$B,"Intercompany",Notas!$E:$E,"Alineado con el estándar")/(COUNTIFS(Notas!$A:$A,$A10,Notas!$B:$B,"Intercompany")-COUNTIFS(Notas!$A:$A,$A10,Notas!$B:$B,"Intercompany",Notas!$E:$E,"No aplica")),0) -> 0 | L10: =IFERROR(COUNTIFS(Notas!$A:$A,$A10,Notas!$E:$E,"Alineado con el estándar")/(COUNTIFS(Notas!$A:$A,$A10)-COUNTIFS(Notas!$A:$A,$A10,Notas!$E:$E,"No aplica")),0) -> 0
A11: Papresa | B11: =IFERROR(COUNTIFS(Notas!$A:$A,$A11,Notas!$B:$B,"Gobierno y S&OP",Notas!$E:$E,"Alineado con el estándar")/(COUNTIFS(Notas!$A:$A,$A11,Notas!$B:$B,"Gobierno y S&OP")-COUNTIFS(Notas!$A:$A,$A11,Notas!$B:$B,"Gobierno y S&OP",Notas!$E:$E,"No aplica")),0) -> 0 | C11: =IFERROR(COUNTIFS(Notas!$A:$A,$A11,Notas!$B:$B,"Dato maestro",Notas!$E:$E,"Alineado con el estándar")/(COUNTIFS(Notas!$A:$A,$A11,Notas!$B:$B,"Dato maestro")-COUNTIFS(Notas!$A:$A,$A11,Notas!$B:$B,"Dato maestro",Notas!$E:$E,"No aplica")),0) -> 0 | D11: =IFERROR(COUNTIFS(Notas!$A:$A,$A11,Notas!$B:$B,"Demanda",Notas!$E:$E,"Alineado con el estándar")/(COUNTIFS(Notas!$A:$A,$A11,Notas!$B:$B,"Demanda")-COUNTIFS(Notas!$A:$A,$A11,Notas!$B:$B,"Demanda",Notas!$E:$E,"No aplica")),0) -> 0 | E11: =IFERROR(COUNTIFS(Notas!$A:$A,$A11,Notas!$B:$B,"Cartera",Notas!$E:$E,"Alineado con el estándar")/(COUNTIFS(Notas!$A:$A,$A11,Notas!$B:$B,"Cartera")-COUNTIFS(Notas!$A:$A,$A11,Notas!$B:$B,"Cartera",Notas!$E:$E,"No aplica")),0) -> 0 | F11: =IFERROR(COUNTIFS(Notas!$A:$A,$A11,Notas!$B:$B,"Necesidades",Notas!$E:$E,"Alineado con el estándar")/(COUNTIFS(Notas!$A:$A,$A11,Notas!$B:$B,"Necesidades")-COUNTIFS(Notas!$A:$A,$A11,Notas!$B:$B,"Necesidades",Notas!$E:$E,"No aplica")),0) -> 0 | G11: =IFERROR(COUNTIFS(Notas!$A:$A,$A11,Notas!$B:$B,"Capacidad",Notas!$E:$E,"Alineado con el estándar")/(COUNTIFS(Notas!$A:$A,$A11,Notas!$B:$B,"Capacidad")-COUNTIFS(Notas!$A:$A,$A11,Notas!$B:$B,"Capacidad",Notas!$E:$E,"No aplica")),0) -> 0 | H11: =IFERROR(COUNTIFS(Notas!$A:$A,$A11,Notas!$B:$B,"Programación",Notas!$E:$E,"Alineado con el estándar")/(COUNTIFS(Notas!$A:$A,$A11,Notas!$B:$B,"Programación")-COUNTIFS(Notas!$A:$A,$A11,Notas!$B:$B,"Programación",Notas!$E:$E,"No aplica")),0) -> 0 | I11: =IFERROR(COUNTIFS(Notas!$A:$A,$A11,Notas!$B:$B,"Entrega",Notas!$E:$E,"Alineado con el estándar")/(COUNTIFS(Notas!$A:$A,$A11,Notas!$B:$B,"Entrega")-COUNTIFS(Notas!$A:$A,$A11,Notas!$B:$B,"Entrega",Notas!$E:$E,"No aplica")),0) -> 0 | J11: =IFERROR(COUNTIFS(Notas!$A:$A,$A11,Notas!$B:$B,"Control",Notas!$E:$E,"Alineado con el estándar")/(COUNTIFS(Notas!$A:$A,$A11,Notas!$B:$B,"Control")-COUNTIFS(Notas!$A:$A,$A11,Notas!$B:$B,"Control",Notas!$E:$E,"No aplica")),0) -> 0 | K11: =IFERROR(COUNTIFS(Notas!$A:$A,$A11,Notas!$B:$B,"Intercompany",Notas!$E:$E,"Alineado con el estándar")/(COUNTIFS(Notas!$A:$A,$A11,Notas!$B:$B,"Intercompany")-COUNTIFS(Notas!$A:$A,$A11,Notas!$B:$B,"Intercompany",Notas!$E:$E,"No aplica")),0) -> 0 | L11: =IFERROR(COUNTIFS(Notas!$A:$A,$A11,Notas!$E:$E,"Alineado con el estándar")/(COUNTIFS(Notas!$A:$A,$A11)-COUNTIFS(Notas!$A:$A,$A11,Notas!$E:$E,"No aplica")),0) -> 0

Sheet Procesos
A1: Proceso | B1: ID | C1: Actividad | D1: Descripción | E1: Frecuencia estándar | F1: Decide (A) | G1: Ejecuta (R)
A2: Gobierno y S&OP | B2: G.1 | C2: Modelo de procesos y manual de planificación | D2: Definir, documentar y mantener cómo se ejecuta cada actividad en todas las plantas. | E2: Continua | F2: Director/a de Planificación | G2: Responsable de procesos (Functional Lead)
A3: Gobierno y S&OP | B3: G.2 | C3: Políticas de planificación | D3: MTS/MTO, stock de seguridad, horizonte congelado, prioridades, lotes, mínimos y máximos. | E3: Trimestral | F3: Director/a de Planificación | G3: Responsable de procesos (Functional Lead)
A4: Gobierno y S&OP | B4: G.3 | C4: S&OP mensual del grupo | D4: Revisión de demanda, de suministro y reunión ejecutiva para decidir capacidad y prioridades. | E4: Mensual | F4: Director/a de Planificación | G4: Coordinador/a de S&OP e intercompany
A5: Gobierno y S&OP | B5: G.4 | C5: Objetivos y revisión de KPIs | D5: Fijar objetivos por planta y revisar el cuadro de mando común. | E5: Mensual | F5: Director/a de Planificación | G5: Responsable de procesos (Functional Lead)
A6: Gobierno y S&OP | B6: G.5 | C6: Roles, personas, suplencias y formación | D6: Asignar cada rol con nombre y apellidos, con titular y suplente, y su plan de formación. | E6: Trimestral | F6: Director/a de Planificación | G6: Responsable de procesos (Functional Lead)
A7: Gobierno y S&OP | B7: G.6 | C7: Gestión de cambios y prioridad de desarrollos | D7: Canal único de peticiones, priorización y paso a producción de mejoras. | E7: Semanal | F7: Director/a de Planificación | G7: Responsable de procesos (Functional Lead), Sistemas de planificación (Technical Lead y desarrollo)
A8: Dato maestro | B8: 1.1 | C8: Datos de planificación del material | D8: Altas y mantenimiento de los datos que usa la planificación (unidades, rutas, máquinas por defecto). | E8: Diaria | F8: Responsable de dato maestro | G8: Responsable de dato maestro
A9: Dato maestro | B9: 1.2 | C9: Segmentación ABC/XYZ y estrategia MTS/MTO | D9: Clasificar materiales y asignar su estrategia de planificación con criterio común. | E9: Trimestral | F9: Responsable de procesos (Functional Lead) | G9: Responsable de dato maestro
A10: Dato maestro | B10: 1.3 | C10: Velocidades, tiempos de cambio y rutas | D10: Mantener los estándares de máquina a partir de los datos reales registrados. | E10: Mensual | F10: Responsable de dato maestro | G10: Responsable de dato maestro, Programador/a de producción
A11: Dato maestro | B11: 1.4 | C11: Calendario de turnos, días y paradas | D11: Turnos activos, días festivos y paradas de mantenimiento por máquina. | E11: Semanal | F11: Responsable de planificación de planta | G11: Programador/a de producción
A12: Dato maestro | B12: 1.5 | C12: Auditoría de calidad del dato | D12: Detectar duplicados, datos incompletos e incoherencias y corregirlos. | E12: Mensual | F12: Responsable de procesos (Functional Lead) | G12: Responsable de dato maestro
... A45: Intercompany | B45: I.5 | C45: Control y cierre de pedidos intercompany | D45: Apertura y cierre controlado de pedidos entre plantas. | E45: Semanal | F45: Coordinador/a de S&OP e intercompany | G45: Planificador/a de materiales

Sheet Flujos
A1: Empresa | B1: Vista | C1: Proceso | D1: Nº | E1: Tipo | F1: Paso | G1: Responsable | H1: Sistema / herramienta | I1: Actividad | J1: Punto de dolor | K1: Siguiente | L1: Notas
A2: Ondupet | B2: As-is | C2: Dato maestro | D2: 1 | E2: Inicio / fin | F2: Material nuevo | K2: → 2
A3: Ondupet | B3: As-is | C3: Dato maestro | D3: 2 | E3: Tarea | F3: Comercial detecta que hace falta un material nuevo | G3: Monica Gordillo | I3: 1.1 | K3: → 3
A4: Ondupet | B4: As-is | C4: Dato maestro | D4: 3 | E4: Tarea | F4: Consulta a Calidad las características técnicas | G4: Monica Gordillo · Calidad | K4: → 4
A5: Ondupet | B5: As-is | C5: Dato maestro | D5: 4 | E5: Tarea | F5: Alta del material: molde, velocidad, tiempos de cambio y ruta por defecto | G5: Monica Gordillo | H5: GIO | I5: 1.1 | J5: Sí | K5: → 5 | L5: No se consulta a Planificación la estrategia (MTS/MTO, ABC) ni la ruta.
A6: Ondupet | B6: As-is | C6: Dato maestro | D6: 5 | E6: Tarea | F6: Planificación planifica con el dato tal cual llega | G6: Victoriano Perez | H6: GIO | K6: → 6
A7: Ondupet | B7: As-is | C7: Dato maestro | D7: 6 | E7: Decisión | F7: ¿Aparece un duplicado? | K7: → 8 (Sí); → 7 (No)
A8: Ondupet | B8: As-is | C8: Dato maestro | D8: 7 | E8: Inicio / fin | F8: Material en uso
A9: Ondupet | B9: As-is | C9: Dato maestro | D9: 8 | E9: Tarea | F9: Corrección puntual con el campo «material reemplazante» | G9: Monica Gordillo y equipo | H9: GIO | I9: 1.5 | J9: Sí | K9: → 7 | L9: No hay auditoría ni criterio de qué define un material: los duplicados aparecen por casualidad.
A10: Ondupet | B10: As-is | C10: Dato maestro | D10: 9 | E10: Nota | F10: ¿Se consulta a Producción y Mantenimiento la ruta por defecto? Duda abierta. | K10: → 4
A11: Ondupet | B11: As-is | C11: Dato maestro | D11: 10 | E11: Nota | F11: Nadie revisa ABC ni estrategias (1.2) ni reequilibra las rutas con la carga del mes (1.3). | K11: → 5
A12: Ondupet | B12: As-is | C12: Demanda | D12: 1 | E12: Inicio / fin | F12: Inicio de mes | K12: → 2
A13: Ondupet | B13: As-is | C13: Demanda | D13: 2 | E13: Tarea | F13: Comercial carga la previsión de cada material: mes en curso + 3 | G13: Manuel Jesus Trinidad | I13: 2.1 | J13: Sí | K13: → 3 | L13: No hay día límite para cerrar la previsión.
A14: Ondupet | B14: As-is | C14: Demanda | D14: 3 | E14: Tarea | F14: Planificación calcula qué fabricar con la previsión, el stock y las órdenes lanzadas | G14: Victoriano Perez | K14: → 4
A15: Ondupet | B15: As-is | C15: Demanda | D15: 4 | E15: Tarea | F15: Genera los temporales para reservar tiempo de cada familia en el ciclo | G15: Victoriano Perez | I15: 2.5 | J15: Sí | K15: → 5 | L15: No se revisan con Comercial.
A16: Ondupet | B16: As-is | C16: Demanda | D16: 5 | E16: Tarea | F16: Comercial cambia la previsión del mes en curso sin consultar a Planificación | G16: Manuel Jesus Trinidad | I16: 2.1 | J16: Sí | K16: → 6 | L16: A veces con el material ya fabricado.
A17: Ondupet | B17: As-is | C17: Demanda | D17: 6 | E17: Tarea | F17: Registro de agotados irregular: épocas con muchos y meses sin ninguno | G17: Monica Gordillo y equipo | I17: 2.3 | J17: Sí | K17: → 7
A18: Ondupet | B18: As-is | C18: Demanda | D18: 7 | E18: Tarea | F18: Reunión mensual de accuracy | G18: Manuel Jesus Trinidad · Victoriano Perez | I18: 2.4 | J18: Sí | K18: → 8 | L18: Comercial no se implica y Planificación no la impulsa.
A19: Ondupet | B19: As-is | C19: Demanda | D19: 8 | E19: Inicio / fin | F19: Fin de mes sin acciones | J19: Sí
A20: Ondupet | B20: As-is | C20: Demanda | D20: 9 | E20: Nota | F20: No hay consenso con Comercial (2.2): Planificación fabrica lo que diga la previsión. | K20: → 3
A21: Ondupet | B21: As-is | C21: Cartera | D21: 1 | E21: Inicio / fin | F21: Inicio del día | K21: → 2; → 3
A22: Ondupet | B22: As-is | C22: Cartera | D22: 2 | E22: Tarea | F22: Comercial revisa cartera, stock y cargas | G22: Monica Gordillo | H22: SAP | I22: 3.1 | K22: → 4
A23: Ondupet | B23: As-is | C23: Cartera | D23: 3 | E23: Tarea | F23: Planificación revisa por su cuenta cartera, stock y cargas | G23: Victoriano Perez | H23: GIO | I23: 3.1 | K23: → 4
A24: Ondupet | B24: As-is | C24: Cartera | D24: 4 | E24: Tarea | F24: Puesta en común en la reunión de producción | G24: Comercial · Planificación · Producción | I24: 3.1 | K24: → 5
A25: Ondupet | B25: As-is | C25: Cartera | D25: 5 | E25: Tarea | F25: Fechas sin consenso: se mantiene la del cliente aunque no se llegue | G25: Comercial | I25: 3.1 | J25: Sí | K25: → 6 | L25: El pedido tiene dos fechas (la del cliente y otra para medir retrasos), pero no se usan.
A26: Ondupet | B26: As-is | C26: Cartera | D26: 6 | E26: Tarea | F26: Comercial vincula a diario las cargas a los pedidos | G26: Monica Gordillo y equipo | H26: SAP | I26: 3.2 | J26: Sí | K26: → 7 | L26: A veces se crean cargas por mucha más cantidad que el pedido y con fechas imposibles.
A27: Ondupet | B27: As-is | C27: Cartera | D27: 7 | E27: Tarea | F27: Planificación envía el reporte diario de cargas atrasadas | G27: Victoriano Perez | I27: 3.2 | K27: → 8
A28: Ondupet | B28: As-is | C28: Cartera | D28: 8 | E28: Decisión | F28: ¿Pedidos en conflicto? | K28: → 9 (No); → 10 (Sí)
A29: Ondupet | B29: As-is | C29: Cartera | D29: 9 | E29: Inicio / fin | F29: Fin del día
A30: Ondupet | B30: As-is | C30: Cartera | D30: 10 | E30: Tarea | F30: Comercial llama a Planificación para buscar una solución | G30: Monica Gordillo · Manuel Jesus Trinidad | I30: 3.4 | K30: → 11
A31: Ondupet | B31: As-is | C31: Cartera | D31: 11 | E31: Decisión | F31: ¿Hay acuerdo? | K31: → 12 (Sí); → 13 (No)
A32: Ondupet | B32: As-is | C32: Cartera | D32: 12 | E32: Inicio / fin | F32: Prioridad resuelta
A33: Ondupet | B33: As-is | C33: Cartera | D33: 13 | E33: Tarea | F33: Decide el director de planta | G33: Manuel Castro | I33: 3.4 | J33: Sí | K33: → 12 | L33: No hay reglas de prioridad.
A34: Ondupet | B34: As-is | C34: Cartera | D34: 14 | E34: Tarea | F34: Comercial salda pedidos, algunos ya planificados, sin avisar a Planificación | G34: Monica Gordillo y equipo | H34: SAP | I34: 3.3 | J34: Sí
A35: Ondupet | B35: As-is | C35: Necesidades | D35: 1 | E35: Inicio / fin | F35: Inicio de semana | K35: → 2
A36: Ondupet | B36: As-is | C36: Necesidades | D36: 2 | E36: Tarea | F36: Ejecución del MRP | H36: SAP | I36: 4.1 | K36: → 3
A37: Ondupet | B37: As-is | C37: Necesidades | D37: 3 | E37: Tarea | F37: Planificación y Compras revisan el MRP y las faltas de MP y auxiliares | G37: Victoriano Perez · Barbara Ayuste | H37: SAP | I37: 4.1 | K37: → 4
A38: Ondupet | B38: As-is | C38: Necesidades | D38: 4 | E38: Tarea | F38: Compras gestiona las necesidades de materias primas y auxiliares | G38: Barbara Ayuste | H38: SAP | I38: 4.4
A39: Ondupet | B39: As-is | C39: Necesidades | D39: 5 | E39: Inicio / fin | F39: Cada día | K39: → 6
A40: Ondupet | B40: As-is | C40: Necesidades | D40: 6 | E40: Tarea | F40: GIO propone la fabricación de producto terminado (por material y pedido en MTO) | H40: GIO | I40: 4.2 | K40: → 7
A41: Ondupet | B41: As-is | C41: Necesidades | D41: 7 | E41: Tarea | F41: Planificación revisa y corrige la propuesta | G41: Victoriano Perez | H41: GIO | I41: 4.2 | J41: Sí | K41: → 8 | L41: Corrige por desviaciones del accuracy que detecta él o por llamadas de Comercial; no queda registro del motivo.
A42: Ondupet | B42: As-is | C42: Necesidades | D42: 8 | E42: Tarea | F42: GIO propone las necesidades de semielaborado | H42: GIO | I42: 4.3 | K42: → 9
A43: Ondupet | B43: As-is | C43: Necesidades | D43: 9 | E43: Tarea | F43: Planificación las revisa con la misma lógica | G43: Victoriano Perez | H43: GIO | I43: 4.3 | J43: Sí | K43: → 10 | L43: Depende de una sola persona.
A44: Ondupet | B44: As-is | C44: Necesidades | D44: 10 | E44: Inicio / fin | F44: Propuesta revisada
A45: Ondupet | B45: As-is | C45: Necesidades | D45: 11 | E45: Nota | F45: 4.4 duplica a 4.1: se propone fusionarlas. | K45: → 4
A46: Ondupet | B46: As-is | C46: Necesidades | D46: 12 | E46: Nota | F46: Comercial llama para pedir cambios en la propuesta. | K46: → 7 (llamadas)
A47: Ondupet | B47: To-be | C47: Dato maestro | D47: 1 | E47: Inicio / fin | F47: Solicitud de material | K47: → 2
A48: Ondupet | B48: To-be | C48: Dato maestro | D48: 2 | E48: Tarea | F48: Comercial solicita el alta con los datos del cliente | G48: Comercial | I48: 1.1 | K48: → 3
A49: Ondupet | B49: To-be | C49: Dato maestro | D49: 3 | E49: Tarea | F49: Calidad fija las características técnicas | G49: Calidad | K49: → 4
A50: Ondupet | B50: To-be | C50: Dato maestro | D50: 4 | E50: Tarea | F50: Dato maestro asigna estrategia MTS/MTO y ABC/XYZ con el criterio común | G50: Dato maestro · consulta a Resp. planif. planta | I50: 1.2 | K50: → 5
A51: Ondupet | B51: To-be | C51: Dato maestro | D51: 5 | E51: Tarea | F51: Programación y Producción validan ruta, velocidad y tiempos de cambio | G51: Programación · Producción | I51: 1.3 | K51: → 6
A52: Ondupet | B52: To-be | C52: Dato maestro | D52: 6 | E52: Decisión | F52: ¿Ficha completa y sin duplicados? | K52: → 7 (Sí); → 8 (No)
A53: Ondupet | B53: To-be | C53: Dato maestro | D53: 7 | E53: Tarea | F53: Alta en GIO con la plantilla única | G53: Dato maestro | H53: GIO | I53: 1.1 | K53: → 9
A54: Ondupet | B54: To-be | C54: Dato maestro | D54: 8 | E54: Tarea | F54: Completar la ficha o reutilizar el material existente («material reemplazante») | G54: Dato maestro | H54: GIO | I54: 1.5 | K54: → 7
A55: Ondupet | B55: To-be | C55: Dato maestro | D55: 9 | E55: Inicio / fin | F55: Listo para planificar
A56: Ondupet | B56: To-be | C56: Dato maestro | D56: 10 | E56: Inicio / fin | F56: Cierre de mes | K56: → 11
A57: Ondupet | B57: To-be | C57: Dato maestro | D57: 11 | E57: Tarea | F57: Reequilibrar las rutas por defecto con la carga del mes | G57: Programación | H57: GIO | I57: 1.3 | K57: → 12
A58: Ondupet | B58: To-be | C58: Dato maestro | D58: 12 | E58: Tarea | F58: Auditoría del dato: duplicados, incompletos e incoherencias | G58: Dato maestro | H58: GIO | I58: 1.5 | K58: → 13
A59: Ondupet | B59: To-be | C59: Dato maestro | D59: 13 | E59: Decisión | F59: ¿Cierre de trimestre? | K59: → 15 (Sí); → 14 (No)
A60: Ondupet | B60: To-be | C60: Dato maestro | D60: 14 | E60: Inicio / fin | F60: Datos al día
A61: Ondupet | B61: To-be | C61: Dato maestro | D61: 15 | E61: Tarea | F61: Revisión de ABC/XYZ y estrategias con la transacción automática | G61: Dato maestro · Resp. planif. planta · Comercial | H61: GIO | I61: 1.2 | K61: → 14
A62: Ondupet | B62: To-be | C62: Demanda | D62: 1 | E62: Inicio / fin | F62: Inicio del ciclo mensual | K62: → 2
A63: Ondupet | B63: To-be | C63: Demanda | D63: 2 | E63: Tarea | F63: Planificación propone la previsión estadística | G63: Demanda y cartera | H63: SAP | I63: 2.1 | K63: → 3
A64: Ondupet | B64: To-be | C64: Demanda | D64: 3 | E64: Tarea | F64: Comercial ajusta la previsión antes del día de cierre | G64: Comercial | H64: SAP | I64: 2.1 | K64: → 4
A65: Ondupet | B65: To-be | C65: Demanda | D65: 4 | E65: Tarea | F65: Reunión de consenso: previsión, temporales y desviaciones | G65: Demanda y cartera · Comercial · S&OP | I65: 2.2 | K65: → 5
A66: Ondupet | B66: To-be | C66: Demanda | D66: 5 | E66: Decisión | F66: ¿Hay acuerdo? | K66: → 6 (Sí); → 7 (No)
A67: Ondupet | B67: To-be | C67: Demanda | D67: 6 | E67: Tarea | F67: Cierre de la previsión: el mes en curso queda congelado | G67: Resp. planif. planta | H67: SAP | I67: 2.1 | K67: → 8
A68: Ondupet | B68: To-be | C68: Demanda | D68: 7 | E68: Tarea | F68: S&OP resuelve la discrepancia | G68: S&OP | I68: 2.2 | K68: → 6
A69: Ondupet | B69: To-be | C69: Demanda | D69: 8 | E69: Tarea | F69: Revisión de temporales por familia con la previsión cerrada | G69: Demanda y cartera | I69: 2.5 | K69: → 9
A70: Ondupet | B70: To-be | C70: Demanda | D70: 9 | E70: Inicio / fin | F70: Demanda cerrada
A71: Ondupet | B71: To-be | C71: Demanda | D71: 10 | E71: Tarea | F71: Registro diario de agotados con motivo codificado | G71: Demanda y cartera · Comercial | I71: 2.3 | K71: → 2 (alimenta)
A72: Ondupet | B72: To-be | C72: Demanda | D72: 11 | E72: Tarea | F72: KPI de precisión y sesgo con acción para cada desviación | G72: Demanda y cartera | I72: 2.4 | K72: → 4 (se revisa aquí)
A73: Ondupet | B73: To-be | C73: Demanda | D73: 12 | E73: Nota | F73: Cambios en el mes congelado: solo con la aprobación de Planificación. | K73: → 6
A74: Ondupet | B74: To-be | C74: Cartera | D74: 1 | E74: Inicio / fin | F74: Inicio del día | K74: → 2
A75: Ondupet | B75: To-be | C75: Cartera | D75: 2 | E75: Tarea | F75: Revisión única de cartera, stock y cargas con una sola fuente | G75: Demanda y cartera | H75: SAP / GIO | I75: 3.1 | K75: → 3
A76: Ondupet | B76: To-be | C76: Cartera | D76: 3 | E76: Tarea | F76: Planificación propone una fecha viable según capacidad y stock | G76: Demanda y cartera | H76: GIO | I76: 3.1 | K76: → 4
A77: Ondupet | B77: To-be | C77: Cartera | D77: 4 | E77: Decisión | F77: ¿Llega a la fecha del cliente? | K77: → 5 (Sí); → 6 (No)
A78: Ondupet | B78: To-be | C78: Cartera | D78: 5 | E78: Tarea | F78: Se registran las dos fechas: solicitada (servicio) y confirmada (plan) | G78: Comercial | H78: SAP | I78: 3.1 | K78: → 7
A79: Ondupet | B79: To-be | C79: Cartera | D79: 6 | E79: Tarea | F79: Comercial negocia una nueva fecha con el cliente | G79: Comercial | I79: 3.1 | K79: → 5
A80: Ondupet | B80: To-be | C80: Cartera | D80: 7 | E80: Tarea | F80: Logística vincula las cargas: cantidad ≤ pendiente y fecha confirmada | G80: Logística | H80: SAP | I80: 3.2 | K80: → 8
A81: Ondupet | B81: To-be | C81: Cartera | D81: 8 | E81: Decisión | F81: ¿Pedidos en conflicto? | K81: → 9 (Sí); → 10 (No)
A82: Ondupet | B82: To-be | C82: Cartera | D82: 9 | E82: Tarea | F82: Planificación aplica las reglas de prioridad acordadas | G82: Resp. planif. planta · consulta a Comercial y Programación | I82: 3.4 | K82: → 11
A83: Ondupet | B83: To-be | C83: Cartera | D83: 10 | E83: Inicio / fin | F83: Fin del día
A84: Ondupet | B84: To-be | C84: Cartera | D84: 11 | E84: Decisión | F84: ¿Afecta a otras plantas? | K84: → 12 (No); → 13 (Sí)
A85: Ondupet | B85: To-be | C85: Cartera | D85: 12 | E85: Tarea | F85: Se informa a Comercial, Programación y Dirección de planta | G85: Resp. planif. planta | I85: 3.4 | K85: → 14
A86: Ondupet | B86: To-be | C86: Cartera | D86: 13 | E86: Tarea | F86: Decide S&OP | G86: S&OP | I86: 3.4 | K86: → 12
A87: Ondupet | B87: To-be | C87: Cartera | D87: 14 | E87: Inicio / fin | F87: Prioridad resuelta
A88: Ondupet | B88: To-be | C88: Cartera | D88: 15 | E88: Inicio / fin | F88: Cierre semanal | K88: → 16
A89: Ondupet | B89: To-be | C89: Cartera | D89: 16 | E89: Tarea | F89: Planificación propone los pedidos a saldar con la regla común | G89: Demanda y cartera | H89: SAP | I89: 3.3 | K89: → 17
A90: Ondupet | B90: To-be | C90: Cartera | D90: 17 | E90: Tarea | F90: Comercial valida y se saldan; Planificación queda avisada | G90: Comercial | H90: SAP | I90: 3.3 | K90: → 18
A91: Ondupet | B91: To-be | C91: Cartera | D91: 18 | E91: Inicio / fin | F91: Cartera limpia
A92: Ondupet | B92: To-be | C92: Necesidades | D92: 1 | E92: Inicio / fin | F92: Inicio de semana | K92: → 2
A93: Ondupet | B93: To-be | C93: Necesidades | D93: 2 | E93: Tarea | F93: MRP con la previsión consensuada y el mes congelado | G93: Materiales | H93: SAP | I93: 4.1 | K93: → 3
A94: Ondupet | B94: To-be | C94: Necesidades | D94: 3 | E94: Tarea | F94: Revisión semanal de excepciones y faltas de materias primas y auxiliares | G94: Materiales · Compras | H94: SAP | I94: 4.1 | K94: → 4
A95: Ondupet | B95: To-be | C95: Necesidades | D95: 4 | E95: Decisión | F95: ¿Faltas sin cubrir? | K95: → 5 (No); → 6 (Sí)
A96: Ondupet | B96: To-be | C96: Necesidades | D96: 5 | E96: Inicio / fin | F96: Materiales cubiertos
A97: Ondupet | B97: To-be | C97: Necesidades | D97: 6 | E97: Tarea | F97: Compras acelera o busca alternativa e informa a Programación | G97: Compras | H97: SAP | I97: 4.1 | K97: → 5
A98: Ondupet | B98: To-be | C98: Necesidades | D98: 7 | E98: Inicio / fin | F98: Cada día | K98: → 8
A99: Ondupet | B99: To-be | C99: Necesidades | D99: 8 | E99: Tarea | F99: GIO propone la fabricación de producto terminado (MTO y MTS) | G99: Demanda y cartera | H99: GIO | I99: 4.2 | K99: → 9
A100: Ondupet | B100: To-be | C100: Necesidades | D100: 9 | E100: Tarea | F100: Revisión con reglas comunes: solo se corrige con un motivo registrado | G100: Demanda y cartera | H100: GIO | I100: 4.2 | K100: → 10
...

Sheet RACI
A1: Matriz RACI
D2: CORPORATIVO | H2: PLANTA
A3: Proceso | B3: ID | C3: Actividad | D3: Dir. Planificación | E3: Resp. procesos | F3: S&OP / Intercompany | G3: Sistemas | H3: Dir. planta | I3: Dato maestro | J3: Resp. planif. planta | K3: Demanda y cartera | L3: Programación | M3: Producción | N3: Producción | O3: Compras | P3: Materiales | Q3: Comercial | R3: Logística | S3: Revisión
A4: Gobierno y S&OP | B4: G.1 | C4: Modelo de procesos y manual de planificación | D4: A | E4: R | G4: C | H4: I | J4: C | S4: =IF(COUNTIF(D4:R4,"A")+COUNTIF(D4:R4,"A/R")<>1,"Revisar A",IF(COUNTIF(D4:R4,"R")+COUNTIF(D4:R4,"A/R")=0,"Falta R","OK")) -> OK
A5: Gobierno y S&OP | B5: G.2 | C5: Políticas de planificación | D5: A | E5: R | F5: C | H5: C | J5: C | K5: I | L5: I | P5: I | Q5: C | S5: =IF(COUNTIF(D5:R5,"A")+COUNTIF(D5:R5,"A/R")<>1,"Revisar A",IF(COUNTIF(D5:R5,"R")+COUNTIF(D5:R5,"A/R")=0,"Falta R","OK")) -> OK
A6: Gobierno y S&OP | B6: G.3 | C6: S&OP mensual del grupo | D6: A | E6: I | F6: R | H6: C | J6: C | O6: C | Q6: C | S6: =IF(COUNTIF(D6:R6,"A")+COUNTIF(D6:R6,"A/R")<>1,"Revisar A",IF(COUNTIF(D6:R6,"R")+COUNTIF(D6:R6,"A/R")=0,"Falta R","OK")) -> OK
A7: Gobierno y S&OP | B7: G.4 | C7: Objetivos y revisión de KPIs | D7: A | E7: R | H7: C | J7: C | K7: I | L7: I | P7: I | S7: =IF(COUNTIF(D7:R7,"A")+COUNTIF(D7:R7,"A/R")<>1,"Revisar A",IF(COUNTIF(D7:R7,"R")+COUNTIF(D7:R7,"A/R")=0,"Falta R","OK")) -> OK
A8: Gobierno y S&OP | B8: G.5 | C8: Roles, personas, suplencias y formación | D8: A | E8: R | H8: C | J8: C | K8: I | L8: I | P8: I | S8: =IF(COUNTIF(D8:R8,"A")+COUNTIF(D8:R8,"A/R")<>1,"Revisar A",IF(COUNTIF(D8:R8,"R")+COUNTIF(D8:R8,"A/R")=0,"Falta R","OK")) -> OK
A9: Gobierno y S&OP | B9: G.6 | C9: Gestión de cambios y prioridad de desarrollos | D9: A | E9: R | G9: R | H9: I | J9: C | S9: =IF(COUNTIF(D9:R9,"A")+COUNTIF(D9:R9,"A/R")<>1,"Revisar A",IF(COUNTIF(D9:R9,"R")+COUNTIF(D9:R9,"A/R")=0,"Falta R","OK")) -> OK
A10: Dato maestro | B10: 1.1 | C10: Datos de planificación del material | G10: I | I10: A/R | J10: I | L10: C | P10: C | S10: =IF(COUNTIF(D10:R10,"A")+COUNTIF(D10:R10,"A/R")<>1,"Revisar A",IF(COUNTIF(D10:R10,"R")+COUNTIF(D10:R10,"A/R")=0,"Falta R","OK")) -> OK
A11: Dato maestro | B11: 1.2 | C11: Segmentación ABC/XYZ y estrategia MTS/MTO | E11: A | F11: C | I11: R | J11: C | K11: I | P11: I | Q11: C | S11: =IF(COUNTIF(D11:R11,"A")+COUNTIF(D11:R11,"A/R")<>1,"Revisar A",IF(COUNTIF(D11:R11,"R")+COUNTIF(D11:R11,"A/R")=0,"Falta R","OK")) -> OK
A12: Dato maestro | B12: 1.3 | C12: Velocidades, tiempos de cambio y rutas | I12: A/R | J12: I | L12: R | N12: C | S12: =IF(COUNTIF(D12:R12,"A")+COUNTIF(D12:R12,"A/R")<>1,"Revisar A",IF(COUNTIF(D12:R12,"R")+COUNTIF(D12:R12,"A/R")=0,"Falta R","OK")) -> OK
A13: Dato maestro | B13: 1.4 | C13: Calendario de turnos, días y paradas | I13: I | J13: A | K13: I | L13: R | N13: C | S13: =IF(COUNTIF(D13:R13,"A")+COUNTIF(D13:R13,"A/R")<>1,"Revisar A",IF(COUNTIF(D13:R13,"R")+COUNTIF(D13:R13,"A/R")=0,"Falta R","OK")) -> OK
A14: Dato maestro | B14: 1.5 | C14: Auditoría de calidad del dato | D14: I | E14: A | I14: R | J14: C | S14: =IF(COUNTIF(D14:R14,"A")+COUNTIF(D14:R14,"A/R")<>1,"Revisar A",IF(COUNTIF(D14:R14,"R")+COUNTIF(D14:R14,"A/R")=0,"Falta R","OK")) -> OK
A15: Demanda | B15: 2.1 | C15: Previsión de demanda | F15: C | J15: A | K15: R | L15: I | P15: I | Q15: C | S15: =IF(COUNTIF(D15:R15,"A")+COUNTIF(D15:R15,"A/R")<>1,"Revisar A",IF(COUNTIF(D15:R15,"R")+COUNTIF(D15:R15,"A/R")=0,"Falta R","OK")) -> OK
A16: Demanda | B16: 2.2 | C16: Consenso de la previsión con Comercial | D16: I | F16: A | J16: C | K16: R | Q16: C | S16: =IF(COUNTIF(D16:R16,"A")+COUNTIF(D16:R16,"A/R")<>1,"Revisar A",IF(COUNTIF(D16:R16,"R")+COUNTIF(D16:R16,"A/R")=0,"Falta R","OK")) -> OK
A17: Demanda | B17: 2.3 | C17: Demanda perdida (agotados) | F17: I | J17: A | K17: R | Q17: C | S17: =IF(COUNTIF(D17:R17,"A")+COUNTIF(D17:R17,"A/R")<>1,"Revisar A",IF(COUNTIF(D17:R17,"R")+COUNTIF(D17:R17,"A/R")=0,"Falta R","OK")) -> OK
A18: Demanda | B18: 2.4 | C18: Precisión y sesgo de la previsión | D18: I | F18: A | J18: C | K18: R | Q18: C | S18: =IF(COUNTIF(D18:R18,"A")+COUNTIF(D18:R18,"A/R")<>1,"Revisar A",IF(COUNTIF(D18:R18,"R")+COUNTIF(D18:R18,"A/R")=0,"Falta R","OK")) -> OK
A19: Cartera | B19: 3.1 | C19: Revisión diaria de la cartera | J19: A | K19: R | L19: I | Q19: C | S19: =IF(COUNTIF(D19:R19,"A")+COUNTIF(D19:R19,"A/R")<>1,"Revisar A",IF(COUNTIF(D19:R19,"R")+COUNTIF(D19:R19,"A/R")=0,"Falta R","OK")) -> OK
A20: Cartera | B20: 3.2 | C20: Cargas vinculadas a pedidos | J20: A | K20: C | Q20: I | R20: R | S20: =IF(COUNTIF(D20:R20,"A")+COUNTIF(D20:R20,"A/R")<>1,"Revisar A",IF(COUNTIF(D20:R20,"R")+COUNTIF(D20:R20,"A/R")=0,"Falta R","OK")) -> OK
A21: Cartera | B21: 3.3 | C21: Cierre (saldado) de pedidos | J21: A | K21: R | Q21: C | R21: I | S21: =IF(COUNTIF(D21:R21,"A")+COUNTIF(D21:R21,"A/R")<>1,"Revisar A",IF(COUNTIF(D21:R21,"R")+COUNTIF(D21:R21,"A/R")=0,"Falta R","OK")) -> OK
A22: Cartera | B22: 3.4 | C22: Prioridad de pedidos en conflicto | F22: C | H22: I | J22: A | K22: R | L22: C | Q22: C | S22: =IF(COUNTIF(D22:R22,"A")+COUNTIF(D22:R22,"A/R")<>1,"Revisar A",IF(COUNTIF(D22:R22,"R")+COUNTIF(D22:R22,"A/R")=0,"Falta R","OK")) -> OK
A23: Necesidades | B23: 4.1 | C23: Ejecución y revisión del MRP | I23: C | J23: A | L23: I | O23: I | P23: R | S23: =IF(COUNTIF(D23:R23,"A")+COUNTIF(D23:R23,"A/R")<>1,"Revisar A",IF(COUNTIF(D23:R23,"R")+COUNTIF(D23:R23,"A/R")=0,"Falta R","OK")) -> OK
A24: Necesidades | B24: 4.2 | C24: Propuesta de fabricación de producto terminado | J24: A | K24: R | L24: C | P24: C | Q24: I | S24: =IF(COUNTIF(D24:R24,"A")+COUNTIF(D24:R24,"A/R")<>1,"Revisar A",IF(COUNTIF(D24:R24,"R")+COUNTIF(D24:R24,"A/R")=0,"Falta R","OK")) -> OK
A25: Necesidades | B25: 4.3 | C25: Necesidades de semielaborado | J25: A | L25: C | N25: I | P25: R | S25: =IF(COUNTIF(D25:R25,"A")+COUNTIF(D25:R25,"A/R")<>1,"Revisar A",IF(COUNTIF(D25:R25,"R")+COUNTIF(D25:R25,"A/R")=0,"Falta R","OK")) -> OK
A26: Necesidades | B26: 4.4 | C26: Necesidades de materias primas y auxiliares | F26: I | J26: A | O26: C | P26: R | S26: =IF(COUNTIF(D26:R26,"A")+COUNTIF(D26:R26,"A/R")<>1,"Revisar A",IF(COUNTIF(D26:R26,"R")+COUNTIF(D26:R26,"A/R")=0,"Falta R","OK")) -> OK
A27: Capacidad | B27: 5.1 | C27: Carga de capacidad y saturación por línea | F27: I | H27: I | J27: A | L27: R | N27: C | S27: =IF(COUNTIF(D27:R27,"A")+COUNTIF(D27:R27,"A/R")<>1,"Revisar A",IF(COUNTIF(D27:R27,"R")+COUNTIF(D27:R27,"A/R")=0,"Falta R","OK")) -> OK
A28: Capacidad | B28: 5.2 | C28: Balanceo entre líneas y plantas | D28: I | F28: A | H28: C | J28: R | L28: C | Q28: I | S28: =IF(COUNTIF(D28:R28,"A")+COUNTIF(D28:R28,"A/R")<>1,"Revisar A",IF(COUNTIF(D28:R28,"R")+COUNTIF(D28:R28,"A/R")=0,"Falta R","OK")) -> OK
A29: Capacidad | B29: 5.3 | C29: Saturación de almacenes | J29: A | L29: R | N29: I | R29: C | S29: =IF(COUNTIF(D29:R29,"A")+COUNTIF(D29:R29,"A/R")<>1,"Revisar A",IF(COUNTIF(D29:R29,"R")+COUNTIF(D29:R29,"A/R")=0,"Falta R","OK")) -> OK
A30: Programación | B30: 6.1 | C30: Plan de producción semanal | H30: I | J30: A | K30: C | L30: R | N30: C | P30: C | Q30: I | S30: =IF(COUNTIF(D30:R30,"A")+COUNTIF(D30:R30,"A/R")<>1,"Revisar A",IF(COUNTIF(D30:R30,"R")+COUNTIF(D30:R30,"A/R")=0,"Falta R","OK")) -> OK
A31: Programación | B31: 6.2 | C31: Secuenciación, ciclos y combinación | J31: A | K31: I | L31: R | N31: C | S31: =IF(COUNTIF(D31:R31,"A")+COUNTIF(D31:R31,"A/R")<>1,"Revisar A",IF(COUNTIF(D31:R31,"R")+COUNTIF(D31:R31,"A/R")=0,"Falta R","OK")) -> OK
A32: Programación | B32: 6.3 | C32: Lanzamiento de órdenes a máquina | J32: A | K32: C | L32: R | N32: I | S32: =IF(COUNTIF(D32:R32,"A")+COUNTIF(D32:R32,"A/R")<>1,"Revisar A",IF(COUNTIF(D32:R32,"R")+COUNTIF(D32:R32,"A/R")=0,"Falta R","OK")) -> OK
A33: Programación | B33: 6.4 | C33: Replanificación ante incidencias | J33: A | K33: C | L33: R | N33: C | Q33: I | S33: =IF(COUNTIF(D33:R33,"A")+COUNTIF(D33:R33,"A/R")<>1,"Revisar A",IF(COUNTIF(D33:R33,"R")+COUNTIF(D33:R33,"A/R")=0,"Falta R","OK")) -> OK
A34: Programación | B34: 6.5 | C34: Cronograma de cambios | J34: A | L34: R | N34: C | S34: =IF(COUNTIF(D34:R34,"A")+COUNTIF(D34:R34,"A/R")<>1,"Revisar A",IF(COUNTIF(D34:R34,"R")+COUNTIF(D34:R34,"A/R")=0,"Falta R","OK")) -> OK
A35: Entrega | B35: 7.1 | C35: Compromiso de fecha al cliente | J35: A | K35: R | L35: C | Q35: I | S35: =IF(COUNTIF(D35:R35,"A")+COUNTIF(D35:R35,"A/R")<>1,"Revisar A",IF(COUNTIF(D35:R35,"R")+COUNTIF(D35:R35,"A/R")=0,"Falta R","OK")) -> OK
A36: Entrega | B36: 7.2 | C36: Reserva de stock a pedidos | J36: A | K36: R | Q36: I | R36: C | S36: =IF(COUNTIF(D36:R36,"A")+COUNTIF(D36:R36,"A/R")<>1,"Revisar A",IF(COUNTIF(D36:R36,"R")+COUNTIF(D36:R36,"A/R")=0,"Falta R","OK")) -> OK
A37: Entrega | B37: 7.3 | C37: Retrasos y aviso al cliente | H37: I | J37: A | K37: R | L37: C | Q37: R | S37: =IF(COUNTIF(D37:R37,"A")+COUNTIF(D37:R37,"A/R")<>1,"Revisar A",IF(COUNTIF(D37:R37,"R")+COUNTIF(D37:R37,"A/R")=0,"Falta R","OK")) -> OK
A38: Entrega | B38: 7.4 | C38: Coordinación con expediciones | J38: A | K38: R | Q38: I | R38: R | S38: =IF(COUNTIF(D38:R38,"A")+COUNTIF(D38:R38,"A/R")<>1,"Revisar A",IF(COUNTIF(D38:R38,"R")+COUNTIF(D38:R38,"A/R")=0,"Falta R","OK")) -> OK
A39: Control | B39: 8.1 | C39: Plan frente a real (adherencia) | E39: I | H39: I | J39: A | L39: R | N39: C | S39: =IF(COUNTIF(D39:R39,"A")+COUNTIF(D39:R39,"A/R")<>1,"Revisar A",IF(COUNTIF(D39:R39,"R")+COUNTIF(D39:R39,"A/R")=0,"Falta R","OK")) -> OK
A40: Control | B40: 8.2 | C40: OEE y rendimiento por máquina | E40: I | H40: A | J40: I | L40: C | N40: R | S40: =IF(COUNTIF(D40:R40,"A")+COUNTIF(D40:R40,"A/R")<>1,"Revisar A",IF(COUNTIF(D40:R40,"R")+COUNTIF(D40:R40,"A/R")=0,"Falta R","OK")) -> OK
A41: Control | B41: 8.3 | C41: Balance de masas | E41: I | I41: C | J41: A | N41: C | P41: R | S41: =IF(COUNTIF(D41:R41,"A")+COUNTIF(D41:R41,"A/R")<>1,"Revisar A",IF(COUNTIF(D41:R41,"R")+COUNTIF(D41:R41,"A/R")=0,"Falta R","OK")) -> OK
A42: Control | B42: 8.4 | C42: Causa raíz de desviaciones | E42: I | J42: A | K42: C | L42: R | N42: C | P42: C | S42: =IF(COUNTIF(D42:R42,"A")+COUNTIF(D42:R42,"A/R")<>1,"Revisar A",IF(COUNTIF(D42:R42,"R")+COUNTIF(D42:R42,"A/R")=0,"Falta R","OK")) -> OK
A43: Intercompany | B43: I.1 | C43: Mapeo de materiales y mínimos/máximos | F43: A | I43: R | J43: C | O43: I | P43: R | S43: =IF(COUNTIF(D43:R43,"A")+COUNTIF(D43:R43,"A/R")<>1,"Revisar A",IF(COUNTIF(D43:R43,"R")+COUNTIF(D43:R43,"A/R")=0,"Falta R","OK")) -> OK
A44: Intercompany | B44: I.2 | C44: Necesidad y pedidos de compra/venta | F44: A | J44: I | O44: C | P44: R | Q44: C | S44: =IF(COUNTIF(D44:R44,"A")+COUNTIF(D44:R44,"A/R")<>1,"Revisar A",IF(COUNTIF(D44:R44,"R")+COUNTIF(D44:R44,"A/R")=0,"Falta R","OK")) -> OK
A45: Intercompany | B45: I.3 | C45: Planificación en papelera contra pedidos de stock | F45: C | J45: A | L45: R | P45: I | S45: =IF(COUNTIF(D45:R45,"A")+COUNTIF(D45:R45,"A/R")<>1,"Revisar A",IF(COUNTIF(D45:R45,"R")+COUNTIF(D45:R45,"A/R")=0,"Falta R","OK")) -> OK
A46: Intercompany | B46: I.4 | C46: Recepciones y % de integración | D46: I | F46: A | O46: C | P46: R | R46: C | S46: =IF(COUNTIF(D46:R46,"A")+COUNTIF(D46:R46,"A/R")<>1,"Revisar A",IF(COUNTIF(D46:R46,"R")+COUNTIF(D46:R46,"A/R")=0,"Falta R","OK")) -> OK
A47: Intercompany | B47: I.5 | C47: Control y cierre de pedidos intercompany | F47: A | J47: I | O47: C | P47: R | Q47: C | S47: =IF(COUNTIF(D47:R47,"A")+COUNTIF(D47:R47,"A/R")<>1,"Revisar A",IF(COUNTIF(D47:R47,"R")+COUNTIF(D47:R47,"A/R")=0,"Falta R","OK")) -> OK
A49: A = decide y responde (una por fila) · R = ejecuta · A/R = decide y ejecuta · C = se le consulta · I = se le informa. La columna «Revisión» se recalcula sola.

Sheet RACI as-is
A1: RACI as-is · cómo se hace hoy en cada empresa
A3: Empresa | B3: Proceso | C3: ID | D3: Actividad | E3: Dir. Planificación | F3: Resp. procesos | G3: S&OP / Intercompany | H3: Sistemas | I3: Dir. planta | J3: Dato maestro | K3: Resp. planif. planta | L3: Demanda y cartera | M3: Programación | N3: Producción | O3: Producción | P3: Compras | Q3: Materiales | R3: Comercial | S3: Logística | T3: Revisión | U3: Dif. con to-be
A4: Ondupet | B4: Dato maestro | C4: 1.1 | D4: Datos de planificación del material | J4: A/R | K4: C | R4: C | T4: =IF(COUNTIF(E4:S4,"A")+COUNTIF(E4:S4,"A/R")<>1,"Revisar A",IF(COUNTIF(E4:S4,"R")+COUNTIF(E4:S4,"A/R")=0,"Falta R","OK")) -> OK | U4: =SUMPRODUCT(--(E4:S4<>RACI!D10:R10)) -> 5
A5: Ondupet | B5: Dato maestro | C5: 1.3 | D5: Velocidades, tiempos de cambio y rutas | J5: A/R | T5: =IF(COUNTIF(E5:S5,"A")+COUNTIF(E5:S5,"A/R")<>1,"Revisar A",IF(COUNTIF(E5:S5,"R")+COUNTIF(E5:S5,"A/R")=0,"Falta R","OK")) -> OK | U5: =SUMPRODUCT(--(E5:S5<>RACI!D12:R12)) -> 3
A6: Ondupet | B6: Dato maestro | C6: 1.5 | D6: Auditoría de calidad del dato | J6: R | T6: =IF(COUNTIF(E6:S6,"A")+COUNTIF(E6:S6,"A/R")<>1,"Revisar A",IF(COUNTIF(E6:S6,"R")+COUNTIF(E6:S6,"A/R")=0,"Falta R","OK")) -> Revisar A | U6: =SUMPRODUCT(--(E6:S6<>RACI!D14:R14)) -> 3
A7: Ondupet | B7: Demanda | C7: 2.1 | D7: Previsión de demanda | L7: I | R7: A/R | T7: =IF(COUNTIF(E7:S7,"A")+COUNTIF(E7:S7,"A/R")<>1,"Revisar A",IF(COUNTIF(E7:S7,"R")+COUNTIF(E7:S7,"A/R")=0,"Falta R","OK")) -> OK | U7: =SUMPRODUCT(--(E7:S7<>RACI!D15:R15)) -> 6
A8: Ondupet | B8: Demanda | C8: 2.3 | D8: Demanda perdida (agotados) | R8: R | T8: =IF(COUNTIF(E8:S8,"A")+COUNTIF(E8:S8,"A/R")<>1,"Revisar A",IF(COUNTIF(E8:S8,"R")+COUNTIF(E8:S8,"A/R")=0,"Falta R","OK")) -> Revisar A | U8: =SUMPRODUCT(--(E8:S8<>RACI!D17:R17)) -> 4
A9: Ondupet | B9: Demanda | C9: 2.4 | D9: Precisión y sesgo de la previsión | L9: R | R9: R | T9: =IF(COUNTIF(E9:S9,"A")+COUNTIF(E9:S9,"A/R")<>1,"Revisar A",IF(COUNTIF(E9:S9,"R")+COUNTIF(E9:S9,"A/R")=0,"Falta R","OK")) -> Revisar A | U9: =SUMPRODUCT(--(E9:S9<>RACI!D18:R18)) -> 4
A10: Ondupet | B10: Cartera | C10: 3.1 | D10: Revisión diaria de la cartera | L10: R | N10: I | R10: A/R | T10: =IF(COUNTIF(E10:S10,"A")+COUNTIF(E10:S10,"A/R")<>1,"Revisar A",IF(COUNTIF(E10:S10,"R")+COUNTIF(E10:S10,"A/R")=0,"Falta R","OK")) -> OK | U10: =SUMPRODUCT(--(E10:S10<>RACI!D19:R19)) -> 4
A11: Ondupet | B11: Cartera | C11: 3.2 | D11: Cargas vinculadas a pedidos | L11: C | S11: A/R | T11: =IF(COUNTIF(E11:S11,"A")+COUNTIF(E11:S11,"A/R")<>1,"Revisar A",IF(COUNTIF(E11:S11,"R")+COUNTIF(E11:S11,"A/R")=0,"Falta R","OK")) -> OK | U11: =SUMPRODUCT(--(E11:S11<>RACI!D20:R20)) -> 3
A12: Ondupet | B12: Cartera | C12: 3.3 | D12: Cierre (saldado) de pedidos | R12: A/R | T12: =IF(COUNTIF(E12:S12,"A")+COUNTIF(E12:S12,"A/R")<>1,"Revisar A",IF(COUNTIF(E12:S12,"R")+COUNTIF(E12:S12,"A/R")=0,"Falta R","OK")) -> OK | U12: =SUMPRODUCT(--(E12:S12<>RACI!D21:R21)) -> 4
A13: Ondupet | B13: Cartera | C13: 3.4 | D13: Prioridad de pedidos en conflicto | I13: A | L13: R | R13: C | T13: =IF(COUNTIF(E13:S13,"A")+COUNTIF(E13:S13,"A/R")<>1,"Revisar A",IF(COUNTIF(E13:S13,"R")+COUNTIF(E13:S13,"A/R")=0,"Falta R","OK")) -> OK | U13: =SUMPRODUCT(--(E13:S13<>RACI!D22:R22)) -> 4
A14: Ondupet | B14: Necesidades | C14: 4.1 | D14: Ejecución y revisión del MRP | K14: A/R | P14: R | T14: =IF(COUNTIF(E14:S14,"A")+COUNTIF(E14:S14,"A/R")<>1,"Revisar A",IF(COUNTIF(E14:S14,"R")+COUNTIF(E14:S14,"A/R")=0,"Falta R","OK")) -> OK | U14: =SUMPRODUCT(--(E14:S14<>RACI!D23:R23)) -> 5
A15: Ondupet | B15: Necesidades | C15: 4.2 | D15: Propuesta de fabricación de producto terminado | K15: A | L15: R | R15: C | T15: =IF(COUNTIF(E15:S15,"A")+COUNTIF(E15:S15,"A/R")<>1,"Revisar A",IF(COUNTIF(E15:S15,"R")+COUNTIF(E15:S15,"A/R")=0,"Falta R","OK")) -> OK | U15: =SUMPRODUCT(--(E15:S15<>RACI!D24:R24)) -> 3
A16: Ondupet | B16: Necesidades | C16: 4.3 | D16: Necesidades de semielaborado | K16: A/R | T16: =IF(COUNTIF(E16:S16,"A")+COUNTIF(E16:S16,"A/R")<>1,"Revisar A",IF(COUNTIF(E16:S16,"R")+COUNTIF(E16:S16,"A/R")=0,"Falta R","OK")) -> OK | U16: =SUMPRODUCT(--(E16:S16<>RACI!D25:R25)) -> 4
A17: Ondupet | B17: Necesidades | C17: 4.4 | D17: Necesidades de materias primas y auxiliares | K17: A/R | P17: R | T17: =IF(COUNTIF(E17:S17,"A")+COUNTIF(E17:S17,"A/R")<>1,"Revisar A",IF(COUNTIF(E17:S17,"R")+COUNTIF(E17:S17,"A/R")=0,"Falta R","OK")) -> OK | U17: =SUMPRODUCT(--(E17:S17<>RACI!D26:R26)) -> 4
A19: «Dif. con to-be» cuenta las celdas de la fila que no coinciden con la hoja RACI (estándar corporativo).

Sheet Roles
A1: Rol | B1: Nombre corto | C1: Ámbito | D1: Misión | E1: Responsabilidades | F1: Qué decide | G1: KPIs
A2: Director/a de Planificación | B2: Dir. Planificación | C2: Corporativo | D2: Dueño del modelo de planificación del grupo: define cómo se planifica, quién lo hace y con qué objetivos. | E2: Aprobar procesos, políticas y roles · Fijar objetivos y KPIs por planta · Presidir el S&OP del grupo · Asignar personas y suplencias · Priorizar mejoras y desarrollos. | F2: Políticas, estructura de roles, asignación de personas, objetivos y prioridades de desarrollo. | G2: OTIF del grupo · Madurez de procesos · % integración intercompany.
A3: Responsable de procesos (Functional Lead) | B3: Resp. procesos | C3: Corporativo | D3: Diseña, documenta y mantiene los procedimientos estándar y vela por que cada planta los cumpla. | E3: Manual de planificación · Auditorías de madurez · Formación y certificación de planificadores · Interlocución con las plantas. | F3: Cómo se ejecuta cada actividad; aprueba las excepciones locales al estándar. | G3: Madurez de procesos · Adherencia al plan.
A4: Coordinador/a de S&OP e intercompany | B4: S&OP / Intercompany | C4: Corporativo | D4: Integra demanda y suministro del grupo y coordina los flujos de papel hacia las cartoneras. | E4: Preparar y conducir el S&OP mensual · Balanceo de carga entre plantas · Mínimos y máximos intercompany · Seguimiento del % de integración. | F4: Reparto de capacidad entre plantas dentro de las políticas; escalados intercompany. | G4: Precisión de la previsión · % integración intercompany · OTIF del grupo.
A5: Sistemas de planificación (Technical Lead y desarrollo) | B5: Sistemas | C5: Corporativo | D5: Construye y mantiene las herramientas de planificación comunes a todas las plantas (SAP, GIO, SIGPA). | E5: Desarrollos y mejoras · Despliegues controlados · Soporte de segundo nivel · Documentación técnica. | F5: Arquitectura técnica y pasos a producción. | G5: Plazo de entrega de mejoras · Incidencias resueltas en plazo.
A6: Dirección de planta | B6: Dir. planta | C6: Planta | D6: Dirige la operación de la planta y apoya la ejecución del plan. | E6: Recursos de producción · Conflictos operativos · OEE. | F6: Recursos operativos de la planta. | G6: OEE · Coste de producción.
A7: Responsable de dato maestro | B7: Dato maestro | C7: Planta | D7: Garantiza que el dato de planificación es único, completo y fiable en todas las plantas. | E7: Altas y cambios de datos de planificación · Velocidades, tiempos de cambio y estrategias · Auditoría de calidad del dato · Mapeo de materiales intercompany. | F7: Aprobación de cualquier cambio en el dato maestro de planificación. | G7: Calidad del dato maestro.
A8: Responsable de planificación de planta | B8: Resp. planif. planta | C8: Planta | D8: Responde del plan de la planta y de que se ejecute según el estándar corporativo. | E8: Aprobar el plan semanal · Resolver conflictos de prioridad · Representar a la planta en el S&OP · Coordinar al equipo de planificación de la planta. | F8: Plan semanal y prioridades dentro de las políticas; escala lo que las supera. | G8: OTIF · Adherencia y estabilidad del plan.
A9: Planificador/a de demanda y cartera | B9: Demanda y cartera | C9: Planta | D9: Convierte previsión y pedidos en necesidades de fabricación y compromete fechas fiables. | E9: Previsión y demanda perdida · Cartera diaria y cierre de pedidos · Propuesta de fabricación · Fechas al cliente y reservas de stock. | F9: Fecha comprometida dentro del plan y propuesta de fabricación. | G9: Precisión de la previsión · Salud de la cartera · OTIF.
A10: Programador/a de producción | B10: Programación | C10: Planta | D10: Secuencia la producción para cumplir el plan con el menor coste de cambios. | E10: Plan semanal y secuencia (ciclos, combinación) · Lanzamiento de órdenes · Replanificación ante incidencias · Carga de capacidad. | F10: Secuencia y lanzamiento dentro del horizonte congelado. | G10: Adherencia al plan · Horas de cambio · Saturación por línea.
A11: Responsable Producción | B11: Producción | C11: Planta | D11: Ejecuta el plan en máquina e informa de lo real. | E11: Cumplir la secuencia · Registrar producción, paradas y consumos · Avisar de incidencias. | F11: Ajustes operativos dentro del turno | G11: OEE · Adherencia al plan.
A12: Producción (jefes de turno) | B12: Producción | C12: Planta | D12: Ejecuta el plan en máquina e informa de lo real. | E12: Cumplir la secuencia · Registrar producción, paradas y consumos · Avisar de incidencias. | F12: Ajustes operativos dentro del turno.
A13: Compras | B13: Compras | C13: Planta | D13: Gestiona proveedores externos y el aprovisionamiento intercompany. | E13: Pedidos de compra · Seguimiento de proveedores. | F13: Proveedor y condiciones. | G13: Plazo y fiabilidad de suministro.
A14: Planificador/a de materiales | B14: Materiales | C14: Planta | D14: Asegura que papel y materias primas llegan a tiempo y en la cantidad necesaria. | E14: MRP · Necesidades de semielaborado y materias primas · Flujo intercompany y recepciones · Balance de masas. | F14: Propuestas de aprovisionamiento dentro de las políticas. | G14: Cobertura de stock · Roturas · % integración intercompany.
A15: Comercial / Atención al cliente | B15: Comercial | C15: Planta | D15: Aporta la visión de mercado y es la voz del cliente. | E15: Información de demanda · Comunicación de fechas y retrasos al cliente. | F15: Prioridad comercial dentro de las reglas acordadas. | G15: Servicio al cliente.
A16: Logística / Expediciones | B16: Logística | C16: Planta | D16: Expide los pedidos y gestiona los almacenes. | E16: Cargas vinculadas a pedido · Saturación de almacén. | F16: Organización de cargas. | G16: Expediciones en fecha.

Sheet Asignación
A1: Empresa | B1: Rol | C1: Titular | D1: Suplente | E1: Puesto actual | F1: % dedicación | G1: Email | H1: Notas
A2: Corporativo · Planificación | B2: Director/a de Planificación | C2: Enrique Tejada | F2: 100 %
A3: Corporativo · Planificación | B3: Responsable de procesos (Functional Lead) | C3: Manuel Rodriguez | F3: 100 %
A4: Corporativo · Planificación | B4: Sistemas de planificación (Technical Lead y desarrollo) | C4: Daniel Leal | F4: 100 %
A5: Corporativo · Planificación | B5: Sistemas de planificación (Technical Lead y desarrollo) | C5: Jesus Amigo | F5: 100 %
A6: Ondupet | B6: Coordinador/a de S&OP e intercompany | C6: Fernando Tolosa | F6: 100 %
A7: Ondupet | B7: Dirección de planta | C7: Manuel Castro | F7: 100 %
A8: Ondupet | B8: Responsable de planificación de planta | C8: Victoriano Perez | F8: 30 %
A9: Ondupet | B9: Planificador/a de demanda y cartera | C9: Victoriano Perez | F9: 30 %
A10: Ondupet | B10: Programador/a de producción | C10: Victoriano Perez | F10: 30 %
A11: Ondupet | B11: Compras | C11: Victoriano Perez | F11: 10 %
A12: Ondupack Almendralejo | B12: Responsable de planificación de planta
A13: Ondupack Almendralejo | B13: Planificador/a de demanda y cartera
A14: Ondupack Almendralejo | B14: Programador/a de producción
A15: Ondupack Almendralejo | B15: Planificador/a de materiales
A16: Ondupack Navalmoral | B16: Responsable de planificación de planta
A17: Ondupack Navalmoral | B17: Planificador/a de demanda y cartera
A18: Ondupack Navalmoral | B18: Programador/a de producción
A19: Ondupack Navalmoral | B19: Planificador/a de materiales
A20: MGT | B20: Responsable de planificación de planta
A21: MGT | B21: Planificador/a de demanda y cartera
A22: MGT | B22: Programador/a de producción
A23: MGT | B23: Planificador/a de materiales
... A31: Papresa | B31: Planificador/a de materiales
A32: Ondupet | B32: Compras | C32: Antonio Nogales | F32: 100 %
A33: Ondupet | B33: Compras | C33: Barbara Ayuste | F33: 50 %
A34: Ondupet | B34: Planificador/a de materiales | C34: Barbara Ayuste | F34: 50 %
A35: Ondupet | B35: Comercial / Atención al cliente | C35: Manuel Jesus Trinidad | F35: 100 %
A36: Corporativo · Planificación | B36: Sistemas de planificación (Technical Lead y desarrollo) | C36: Vicente Hernandez | F36: 100 %
A37: Corporativo · Planificación | B37: Sistemas de planificación (Technical Lead y desarrollo) | C37: Juan Trigo | F37: 100 %
A38: Ondupet | B38: Comercial / Atención al cliente | C38: Monica Gordillo | F38: 50 %
A39: Ondupet | B39: Responsable de dato maestro | C39: Monica Gordillo | F39: 20 %
A40: Ondupet | B40: Logística / Expediciones | C40: Monica Gordillo | F40: 30 %
A41: Ondupet | B41: Responsable Producción | C41: Juan Manuel Barroso | F41: 100 %
A42: Ondupet | B42: Producción (jefes de turno) | C42: Jefes Turno | F42: 100 %
A44: En amarillo, los huecos por asignar (titular o suplente).

Sheet Organigramas
A1: Empresa | B1: Vista | C1: Nivel | D1: Puesto | E1: Persona | F1: Área | G1: Rol del modelo | H1: De otra empresa | I1: Depende de | J1: Dependencia funcional de | K1: % planificación | L1: Notas
A2: Corporativo · Planificación | B2: As-is | C2: 1 | D2: Responsable Planificacion | E2: Enrique Tejada | F2: Planificación | G2: Director/a de Planificación
A3: Corporativo · Planificación | B3: As-is | C3: 2 | D3: Responsable Técnico | E3: Daniel Leal | F3: Planificación | I3: Responsable Planificacion · Enrique Tejada
A4: Corporativo · Planificación | B4: As-is | C4: 2 | D4: Responsable Procesos | E4: Manuel Rodríguez | F4: Planificación | G4: Responsable de procesos (Functional Lead) | I4: Responsable Planificacion · Enrique Tejada
A5: Corporativo · Planificación | B5: As-is | C5: 3 | D5: Programador .NET | E5: Jesus Amigo | F5: Planificación | G5: Sistemas de planificación (Technical Lead y desarrollo) | I5: Responsable Procesos · Manuel Rodríguez
A6: Corporativo · Planificación | B6: As-is | C6: 3 | D6: Programador .NET | E6: Vicente Hernández | F6: Planificación | G6: Sistemas de planificación (Technical Lead y desarrollo) | I6: Responsable Procesos · Manuel Rodríguez
A7: Corporativo · Planificación | B7: As-is | C7: 3 | D7: Nuevo puesto | E7: Vacante | I7: Responsable Procesos · Manuel Rodríguez
A8: Corporativo · Planificación | B8: As-is | C8: 3 | D8: Nuevo puesto | E8: Vacante | I8: Responsable Procesos · Manuel Rodríguez
A9: Corporativo · Planificación | B9: To-be | C9: 1 | D9: Dirección General | E9: Vacante | F9: Dirección
A10: Corporativo · Planificación | B10: To-be | C10: 2 | D10: Director/a de Planificación | E10: Vacante | F10: Planificación | G10: Director/a de Planificación | I10: Dirección General
A11: Corporativo · Planificación | B11: To-be | C11: 3 | D11: Responsable de procesos (Functional Lead) | E11: Vacante | F11: Planificación | G11: Responsable de procesos (Functional Lead) | I11: Director/a de Planificación
A12: Corporativo · Planificación | B12: To-be | C12: 3 | D12: Responsable de dato maestro | E12: Vacante | F12: Planificación | G12: Responsable de dato maestro | I12: Director/a de Planificación
A13: Corporativo · Planificación | B13: To-be | C13: 3 | D13: Coordinador/a de S&OP e intercompany | E13: Vacante | F13: Planificación | G13: Coordinador/a de S&OP e intercompany | I13: Director/a de Planificación
A14: Corporativo · Planificación | B14: To-be | C14: 3 | D14: Technical Lead | E14: Vacante | F14: Planificación | G14: Sistemas de planificación (Technical Lead y desarrollo) | I14: Director/a de Planificación
A15: Corporativo · Planificación | B15: To-be | C15: 4 | D15: Solution Developer | E15: Vacante | F15: Planificación | G15: Sistemas de planificación (Technical Lead y desarrollo) | I15: Technical Lead
A16: Corporativo · Planificación | B16: To-be | C16: 3 | D16: Responsables de planificación de planta | E16: Vacante | F16: Planificación | G16: Responsable de planificación de planta | I16: Director/a de Planificación | L16: Uno por planta; ver el organigrama de cada empresa.
A17: Ondupet | B17: As-is | C17: 1 | D17: Responsable Division | E17: Fernando Tolosa | F17: Dirección | G17: Coordinador/a de S&OP e intercompany | H17: Ondupack Almendralejo
A18: Ondupet | B18: As-is | C18: 2 | D18: Director Planta | E18: Manuel Castro | F18: Dirección | G18: Dirección de planta | I18: Responsable Division · Fernando Tolosa
A19: Ondupet | B19: As-is | C19: 3 | D19: Responsable Planificación | E19: Victoriano Perez | F19: Planificación | G19: Responsable de planificación de planta | I19: Director Planta · Manuel Castro
A20: Ondupet | B20: As-is | C20: 3 | D20: Responsable Comercial | E20: Manuel Jesus Trinidad | F20: Comercial | G20: Comercial / Atención al cliente | I20: Director Planta · Manuel Castro
A21: Ondupet | B21: As-is | C21: 4 | D21: Comercial / Logística Externa | E21: Monica Gordillo | F21: Comercial | G21: Comercial / Atención al cliente | I21: Responsable Comercial · Manuel Jesus Trinidad
A22: Ondupet | B22: As-is | C22: 3 | D22: Responsable Compras | E22: Antonio Nogales | F22: Compras | G22: Compras | I22: Director Planta · Manuel Castro
A23: Ondupet | B23: As-is | C23: 4 | D23: Gestor Compras | E23: Barbara Ayuste | F23: Compras | G23: Compras | I23: Responsable Compras · Antonio Nogales
A24: Ondupet | B24: As-is | C24: 3 | D24: Responsable Produccion | E24: Juan Manuel Barroso | F24: Producción | G24: Producción (jefes de turno) | I24: Director Planta · Manuel Castro
A25: Ondupet | B25: As-is | C25: 4 | D25: Jefes Turno | E25: Jefes Turno | F25: Producción | G25: Producción (jefes de turno) | I25: Responsable Produccion · Juan Manuel Barroso
A26: Ondupet | B26: To-be | C26: 1 | D26: Director/a de Planificación | E26: Vacante | F26: Dirección | G26: Director/a de Planificación | H26: Corporativo · Planificación | L26: Corporativo.
A27: Ondupet | B27: To-be | C27: 2 | D27: Responsable de planificación de planta | E27: Vacante | F27: Planificación | G27: Responsable de planificación de planta | I27: Director/a de Planificación | J27: Dirección de planta | L27: Dependencia jerárquica de corporativo y funcional de la dirección de planta (opción A, pendiente de decisión).
A28: Ondupet | B28: To-be | C28: 3 | D28: Planificador/a de demanda y cartera | E28: Vacante | F28: Planificación | G28: Planificador/a de demanda y cartera | I28: Responsable de planificación de planta
A29: Ondupet | B29: To-be | C29: 3 | D29: Programador/a de producción | E29: Vacante | F29: Planificación | G29: Programador/a de producción | I29: Responsable de planificación de planta
A30: Ondupet | B30: To-be | C30: 3 | D30: Planificador/a de materiales | E30: Vacante | F30: Planificación | G30: Planificador/a de materiales | I30: Responsable de planificación de planta
A31: Ondupet | B31: To-be | C31: 1 | D31: Dirección de planta | E31: Vacante | F31: Dirección | G31: Dirección de planta
A32: Ondupack Almendralejo | B32: To-be | C32: 1 | D32: Director/a de Planificación | E32: Vacante | F32: Dirección | G32: Director/a de Planificación | H32: Corporativo · Planificación | L32: Corporativo.
A33: Ondupack Almendralejo | B33: To-be | C33: 2 | D33: Responsable de planificación de planta | E33: Vacante | F33: Planificación | G33: Responsable de planificación de planta | I33: Director/a de Planificación | J33: Dirección de planta | L33: Dependencia jerárquica de corporativo y funcional de la dirección de planta (opción A, pendiente de decisión).
A34: Ondupack Almendralejo | B34: To-be | C34: 3 | D34: Planificador/a de demanda y cartera | E34: Vacante | F34: Planificación | G34: Planificador/a de demanda y cartera | I34: Responsable de planificación de planta
A35: Ondupack Almendralejo | B35: To-be | C35: 3 | D35: Programador/a de producción | E35: Vacante | F35: Planificación | G35: Programador/a de producción | I35: Responsable de planificación de planta
A36: Ondupack Almendralejo | B36: To-be | C36: 3 | D36: Planificador/a de materiales | E36: Vacante | F36: Planificación | G36: Planificador/a de materiales | I36: Responsable de planificación de planta
A37: Ondupack Almendralejo | B37: To-be | C37: 1 | D37: Dirección de planta | E37: Vacante | F37: Dirección | G37: Dirección de planta
A38: Ondupack Navalmoral | B38: To-be | C38: 1 | D38: Director/a de Planificación | E38: Vacante | F38: Dirección | G38: Director/a de Planificación | H38: Corporativo · Planificación | L38: Corporativo.
A39: Ondupack Navalmoral | B39: To-be | C39: 2 | D39: Responsable de planificación de planta | E39: Vacante | F39: Planificación | G39: Responsable de planificación de planta | I39: Director/a de Planificación | J39: Dirección de planta | L39: Dependencia jerárquica de corporativo y funcional de la dirección de planta (opción A, pendiente de decisión).
A40: Ondupack Navalmoral | B40: To-be | C40: 3 | D40: Planificador/a de demanda y cartera | E40: Vacante | F40: Planificación | G40: Planificador/a de demanda y cartera | I40: Responsable de planificación de planta
A41: Ondupack Navalmoral | B41: To-be | C41: 3 | D41: Programador/a de producción | E41: Vacante | F41: Planificación | G41: Programador/a de producción | I41: Responsable de planificación de planta
A42: Ondupack Navalmoral | B42: To-be | C42: 3 | D42: Planificador/a de materiales | E42: Vacante | F42: Planificación | G42: Planificador/a de materiales | I42: Responsable de planificación de planta
A43: Ondupack Navalmoral | B43: To-be | C43: 1 | D43: Dirección de planta | E43: Vacante | F43: Dirección | G43: Dirección de planta
A44: MGT | B44: To-be | C44: 1 | D44: Director/a de Planificación | E44: Vacante | F44: Dirección | G44: Director/a de Planificación | H44: Corporativo · Planificación | L44: Corporativo.
A45: MGT | B45: To-be | C45: 2 | D45: Responsable de planificación de planta | E45: Vacante | F45: Planificación | G45: Responsable de planificación de planta | I45: Director/a de Planificación | J45: Dirección de planta | L45: Dependencia jerárquica de corporativo y funcional de la dirección de planta (opción A, pendiente de decisión).
A46: MGT | B46: To-be | C46: 3 | D46: Planificador/a de demanda y cartera | E46: Vacante | F46: Planificación | G46: Planificador/a de demanda y cartera | I46: Responsable de planificación de planta
A47: MGT | B47: To-be | C47: 3 | D47: Programador/a de producción | E47: Vacante | F47: Planificación | G47: Programador/a de producción | I47: Responsable de planificación de planta
A48: MGT | B48: To-be | C48: 3 | D48: Planificador/a de materiales | E48: Vacante | F48: Planificación | G48: Planificador/a de materiales | I48: Responsable de planificación de planta
A49: MGT | B49: To-be | C49: 1 | D49: Dirección de planta | E49: Vacante | F49: Dirección | G49: Dirección de planta
A50: PDA | B50: To-be | C50: 1 | D50: Director/a de Planificación | E50: Vacante | F50: Dirección | G50: Director/a de Planificación | H50: Corporativo · Planificación | L50: Corporativo.
A51: PDA | B51: To-be | C51: 2 | D51: Responsable de planificación de planta | E51: Vacante | F51: Planificación | G51: Responsable de planificación de planta | I51: Director/a de Planificación | J51: Dirección de planta | L51: Dependencia jerárquica de corporativo y funcional de la dirección de planta (opción A, pendiente de decisión).
A52: PDA | B52: To-be | C52: 3 | D52: Planificador/a de demanda y cartera | E52: Vacante | F52: Planificación | G52: Planificador/a de demanda y cartera | I52: Responsable de planificación de planta
A53: PDA | B53: To-be | C53: 3 | D53: Programador/a de producción | E53: Vacante | F53: Planificación | G53: Programador/a de producción | I53: Responsable de planificación de planta
A54: PDA | B54: To-be | C54: 3 | D54: Planificador/a de materiales | E54: Vacante | F54: Planificación | G54: Planificador/a de materiales | I54: Responsable de planificación de planta
A55: PDA | B55: To-be | C55: 1 | D55: Dirección de planta | E55: Vacante | F55: Dirección | G55: Dirección de planta
A56: Papresa | B56: To-be | C56: 1 | D56: Director/a de Planificación | E56: Vacante | F56: Dirección | G56: Director/a de Planificación | H56: Corporativo · Planificación | L56: Corporativo.
A57: Papresa | B57: To-be | C57: 2 | D57: Responsable de planificación de planta | E57: Vacante | F57: Planificación | G57: Responsable de planificación de planta | I57: Director/a de Planificación | J57: Dirección de planta | L57: Dependencia jerárquica de corporativo y funcional de la dirección de planta (opción A, pendiente de decisión).
A58: Papresa | B58: To-be | C58: 3 | D58: Planificador/a de demanda y cartera | E58: Vacante | F58: Planificación | G58: Planificador/a de demanda y cartera | I58: Responsable de planificación de planta
A59: Papresa | B59: To-be | C59: 3 | D59: Programador/a de producción | E59: Vacante | F59: Planificación | G59: Programador/a de producción | I59: Responsable de planificación de planta
A60: Papresa | B60: To-be | C60: 3 | D60: Planificador/a de materiales | E60: Vacante | F60: Planificación | G60: Planificador/a de materiales | I60: Responsable de planificación de planta
A61: Papresa | B61: To-be | C61: 1 | D61: Dirección de planta | E61: Vacante | F61: Dirección | G61: Dirección de planta

Sheet Empresas
A1: Empresa / planta | B1: Tipo | C1: ERP | D1: Herramienta de planificación | E1: Director/a de planta | F1: Responsable de planificación hoy | G1: Nº personas planificando | H1: Particularidades | I1: Notas
A2: Corporativo · Planificación | B2: Corporativo | C2: SAP | D2: SAP · GIO · SIGPA | H2: Define el modelo y gobierna la planificación de todas las plantas.
A3: Ondupet | B3: PET · extrusión y termoformado | C3: SAP | D3: GIO (escritorio; migración a web propuesta para 2027) | H3: Ciclos por molde (termoformado) y por calidad (extrusión); MRP en SAP integrado con GIO.
A4: Ondupack Almendralejo | B4: Cartón ondulado · onduladora y converting | C4: SAP | D4: GIO Aplicación de escritorio (migración a web propuesta para 2027) | H4: Combiplan para combinar pedidos; consume papel intercompany.
A5: Ondupack Navalmoral | B5: Cartón ondulado · onduladora y converting | C5: SAP | D5: GIO Aplicación de escritorio (migración a web propuesta para 2027) | H5: Consume papel intercompany.
A6: MGT | B6: Papelera | C6: SAP | D6: SIGPA (web) | H6: Algoritmo de combinación en SIGPA en pruebas; suministra papel a Ondupack.
A7: PDA | B7: Papelera | C7: SAP | D7: SIGPA (web) | H7: Suministra papel a Ondupack.
A8: Papresa | B8: Papelera · nueva incorporación | C8: ERP propio · SAP previsto 01/01/2027 | D8: Por confirmar | H8: Trazabilidad compra-venta en un HTML conectado a los distintos ERP hasta su paso a SAP.

Sheet Políticas
A1: Política | B1: Estándar corporativo | C1: Parámetros por planta | D1: Responsable | E1: Estado | F1: Notas
A2: Segmentación ABC/XYZ | B2: Volumen (ABC) y variabilidad (XYZ) con el mismo criterio en todas las plantas; recálculo trimestral. | C2: Umbrales de cada planta | D2: Responsable de dato maestro | E2: Propuesta
A3: Estrategia MTS/MTO | B3: Regla común por segmento para decidir qué se fabrica contra stock y qué contra pedido; las excepciones las aprueba corporativo. | C3: Excepciones por planta | D3: Responsable de procesos (Functional Lead) | E3: Propuesta
A4: Stock de seguridad y cobertura | B4: Cobertura objetivo en días por segmento, revisada en el S&OP. | C4: Días de cobertura por segmento | D4: Coordinador/a de S&OP e intercompany | E4: Propuesta
A5: Horizonte congelado | B5: Ventana en la que el plan no se cambia sin aprobación del responsable de planta. | C5: Días por tipo de planta | D5: Director/a de Planificación | E5: Propuesta
A6: Prioridad de pedidos | B6: Orden común: fecha comprometida, cliente estratégico, antigüedad. Los conflictos entre plantas se deciden en el S&OP. | D6: Director/a de Planificación | E6: Propuesta
A7: Mínimos y máximos intercompany | B7: Los propone la cartonera, los valida S&OP y se revisan cada mes. | C7: Por referencia | D7: Coordinador/a de S&OP e intercompany | E7: Propuesta
A8: Lote mínimo de fabricación | B8: Lote mínimo por familia según el coste del cambio. | C8: Por familia y máquina | D8: Responsable de procesos (Functional Lead) | E8: Propuesta
A9: Nivel de servicio objetivo | B9: OTIF objetivo por segmento de cliente o material. | C9: Objetivo por planta | D9: Director/a de Planificación | E9: Propuesta
A10: Reglas de secuenciación | B10: Ciclos por molde o calidad y combinación de pedidos según el estándar de cada tipo de planta. | C10: Familias y ciclos de cada planta | D10: Responsable de procesos (Functional Lead) | E10: Propuesta
A11: Cambios en el dato maestro | B11: Todo cambio se solicita al responsable de dato maestro, que lo aprueba y deja trazado. | D11: Responsable de dato maestro | E11: Propuesta

Sheet KPIs
A1: KPI | B1: Definición | C1: Fórmula | D1: Frecuencia | E1: Responsable | F1: Objetivo | G1: Notas
A2: OTIF | B2: Pedidos entregados en la fecha y cantidad comprometidas. | C2: Pedidos en fecha y completos / pedidos entregados | D2: Mensual | E2: Responsable de planificación de planta
A3: Adherencia al plan | B3: Lo producido según el plan semanal. | C3: Órdenes fabricadas en su semana y cantidad / órdenes planificadas | D3: Semanal | E3: Programador/a de producción
A4: Estabilidad del plan | B4: Cambios dentro del horizonte congelado. | C4: Órdenes modificadas en horizonte congelado / órdenes del plan | D4: Semanal | E4: Responsable de planificación de planta
A5: Precisión de la previsión | B5: Error y sesgo de la previsión. | C5: 1 − MAPE; sesgo = Σ(previsión − real) / Σ real | D5: Mensual | E5: Coordinador/a de S&OP e intercompany
A6: Cobertura de stock | B6: Días de consumo que cubre el stock. | C6: Stock / consumo medio diario | D6: Semanal | E6: Planificador/a de materiales
A7: Horas de cambio | B7: Tiempo de máquina dedicado a cambios. | C7: Σ horas de cambio por línea | D7: Semanal | E7: Programador/a de producción
A8: OEE | B8: Eficiencia global de los equipos. | C8: Disponibilidad × rendimiento × calidad | D8: Semanal | E8: Producción (jefes de turno)
A9: Saturación por línea | B9: Ocupación prevista de cada máquina. | C9: Horas cargadas / horas disponibles | D9: Semanal | E9: Programador/a de producción
A10: % integración intercompany | B10: Recepciones de SQ y DU servidas por MGT, PDA o Papresa. | C10: Recepciones intercompany / recepciones totales | D10: Mensual | E10: Coordinador/a de S&OP e intercompany
A11: Salud de la cartera | B11: Pedidos vencidos o sin cerrar. | C11: Pedidos vencidos o abiertos indebidamente / cartera | D11: Semanal | E11: Planificador/a de demanda y cartera
A12: Calidad del dato maestro | B12: Materiales con datos completos y sin duplicados. | C12: Materiales correctos / materiales activos | D12: Mensual | E12: Responsable de dato maestro
A13: Madurez del proceso | B13: Procesos alineados con el estándar corporativo. | C13: Actividades alineadas / actividades aplicables | D13: Trimestral | E13: Responsable de procesos (Functional Lead)

Sheet Reuniones
A1: Reunión | B1: Frecuencia | C1: Duración | D1: Participantes | E1: Entradas | F1: Salidas / decisiones | G1: Notas

Sheet Decisiones
A1: Decisión | B1: Opciones | C1: Recomendación | D1: Quién decide | E1: Fecha límite | F1: Estado | G1: Resolución

Sheet Plan
A1: Fase | B1: Acción | C1: Empresa | D1: Proceso | E1: Actividades | F1: Responsable | G1: Tipo | H1: Inicio | I1: Fin | J1: Días | K1: Estado | L1: % avance | M1: Entregables | N1: Notas
A2: 1 · Gobierno y estándares | B2: Arranque y aprobación del modelo: roles, RACI to-be y calendario | C2: Grupo (todas) | D2: Gobierno y S&OP | E2: G.1 | F2: Director/a de Planificación | G2: Tarea | H2: 46398 | I2: 46416 | J2: =IF(AND(H2<>"",I2<>""),I2-H2+1,"") -> 19 | K2: Pendiente | M2: Modelo aprobado por dirección; RACI to-be v1
A3: 1 · Gobierno y estándares | B3: Modelo aprobado por dirección | C3: Grupo (todas) | F3: Director/a de Planificación | G3: Hito | H3: 46416 | I3: 46416 | J3: =IF(AND(H3<>"",I3<>""),I3-H3+1,"") -> 1 | K3: Pendiente
A4: 1 · Gobierno y estándares | B4: Revisar el catálogo de actividades (fusionar 4.4 en 4.1) | C4: Grupo (todas) | D4: Necesidades | E4: 4.1, 4.4 | F4: Responsable de procesos (Functional Lead) | G4: Tarea | H4: 46398 | I4: 46409 | J4: =IF(AND(H4<>"",I4<>""),I4-H4+1,"") -> 12 | K4: Pendiente | M4: Catálogo v2
A5: 1 · Gobierno y estándares | B5: Nombrar titulares y suplentes por rol en cada planta | C5: Grupo (todas) | F5: Director/a de Planificación | G5: Tarea | H5: 46405 | I5: 46430 | J5: =IF(AND(H5<>"",I5<>""),I5-H5+1,"") -> 26 | K5: Pendiente | M5: Personas y roles asignados con nombre y apellidos | N5: Con cada dirección de planta.
A6: 1 · Gobierno y estándares | B6: Completar el as-is del resto de plantas (Ondupack, MGT, PDA y Papresa) | C6: Grupo (todas) | F6: Responsable de procesos (Functional Lead) | G6: Tarea | H6: 46398 | I6: 46444 | J6: =IF(AND(H6<>"",I6<>""),I6-H6+1,"") -> 47 | K6: Pendiente | M6: Notas, RACI as-is y flujos as-is por planta
A7: 1 · Gobierno y estándares | B7: Calendario de planificación del grupo: S&OP mensual y reuniones de planta | C7: Grupo (todas) | D7: Gobierno y S&OP | E7: G.2 | F7: Coordinador/a de S&OP e intercompany | G7: Tarea | H7: 46419 | I7: 46444 | J7: =IF(AND(H7<>"",I7<>""),I7-H7+1,"") -> 26 | K7: Pendiente | M7: Calendario 2027 de reuniones
A8: 1 · Gobierno y estándares | B8: Políticas de planificación y KPIs comunes (definición y fórmula) | C8: Grupo (todas) | D8: Control | F8: Responsable de procesos (Functional Lead) | G8: Tarea | H8: 46447 | I8: 46507 | J8: =IF(AND(H8<>"",I8<>""),I8-H8+1,"") -> 61 | K8: Pendiente | M8: Políticas y KPIs validados
A9: 1 · Gobierno y estándares | B9: Manual de planificación v1: procedimiento estándar por proceso | C9: Grupo (todas) | F9: Responsable de procesos (Functional Lead) | G9: Tarea | H9: 46426 | I9: 46507 | J9: =IF(AND(H9<>"",I9<>""),I9-H9+1,"") -> 82 | K9: Pendiente | M9: Manual v1 con el to-be de cada proceso | N9: Parte del to-be diseñado en Ondupet.
A10: 1 · Gobierno y estándares | B10: Manual de planificación v1 publicado | C10: Grupo (todas) | F10: Responsable de procesos (Functional Lead) | G10: Hito | H10: 46507 | I10: 46507 | J10: =IF(AND(H10<>"",I10<>""),I10-H10+1,"") -> 1 | K10: Pendiente
A11: 2 · Piloto Ondupet | B11: Cerrar el E2E de Ondupet: capacidad, programación, entrega y control (5–8) | C11: Ondupet | F11: Responsable de procesos (Functional Lead) | G11: Tarea | H11: 46398 | I11: 46423 | J11: =IF(AND(H11<>"",I11<>""),I11-H11+1,"") -> 26 | K11: Pendiente | M11: As-is y to-be de los procesos 5 a 8 | N11: Si se termina antes de 2027, eliminar esta acción.
A12: 2 · Piloto Ondupet | B12: Plantilla única de alta de material con estrategia y ruta | C12: Ondupet | D12: Dato maestro | E12: 1.1 | F12: Responsable de dato maestro | G12: Tarea | H12: 46419 | I12: 46477 | J12: =IF(AND(H12<>"",I12<>""),I12-H12+1,"") -> 59 | K12: Pendiente | M12: Plantilla de alta en GIO y circuito Comercial → Calidad → Dato maestro
A13: 2 · Piloto Ondupet | B13: Primera revisión de ABC/XYZ y estrategias; después, trimestral | C13: Ondupet | D13: Dato maestro | E13: 1.2 | F13: Responsable de dato maestro | G13: Tarea | H13: 46447 | I13: 46507 | J13: =IF(AND(H13<>"",I13<>""),I13-H13+1,"") -> 61 | K13: Pendiente | M13: Materiales reclasificados | N13: Con Victoriano Perez y Manuel Jesus Trinidad, usando la transacción automática de GIO.
A14: 2 · Piloto Ondupet | B14: Criterio de qué define un material y limpieza de duplicados | C14: Ondupet | D14: Dato maestro | E14: 1.5 | F14: Responsable de dato maestro | G14: Tarea | H14: 46447 | I14: 46535 | J14: =IF(AND(H14<>"",I14<>""),I14-H14+1,"") -> 89 | K14: Pendiente | M14: Criterio documentado; duplicados unidos con «material reemplazante»
A15: 2 · Piloto Ondupet | B15: Revisión mensual de rutas por defecto con la carga del mes | C15: Ondupet | D15: Dato maestro | E15: 1.3 | F15: Programador/a de producción | G15: Tarea | H15: 46482 | I15: 46535 | J15: =IF(AND(H15<>"",I15<>""),I15-H15+1,"") -> 54 | K15: Pendiente | M15: Rutina mensual en marcha
A16: 2 · Piloto Ondupet | B16: Levantar y estandarizar el calendario de turnos y paradas | C16: Ondupet | D16: Dato maestro | E16: 1.4 | F16: Responsable de planificación de planta | G16: Tarea | H16: 46482 | I16: 46535 | J16: =IF(AND(H16<>"",I16<>""),I16-H16+1,"") -> 54 | K16: Pendiente | M16: As-is y to-be de 1.4 | N16: El E2E no lo cubre todavía.
A17: 2 · Piloto Ondupet | B17: Calendario de previsión con día de cierre y mes en curso congelado | C17: Ondupet | D17: Demanda | E17: 2.1 | F17: Responsable de planificación de planta | G17: Tarea | H17: 46419 | I17: 46472 | J17: =IF(AND(H17<>"",I17<>""),I17-H17+1,"") -> 54 | K17: Pendiente | M17: Calendario y regla de congelación acordados con Comercial
A18: 2 · Piloto Ondupet | B18: Primer cierre de previsión en fecha | C18: Ondupet | D18: Demanda | F18: Responsable de planificación de planta | G18: Hito | H18: 46477 | I18: 46477 | J18: =IF(AND(H18<>"",I18<>""),I18-H18+1,"") -> 1 | K18: Pendiente
A19: 2 · Piloto Ondupet | B19: Reunión mensual de consenso con revisión de temporales | C19: Ondupet | D19: Demanda | E19: 2.2, 2.5 | F19: Coordinador/a de S&OP e intercompany | G19: Tarea | H19: 46447 | I19: 46507 | J19: =IF(AND(H19<>"",I19<>""),I19-H19+1,"") -> 61 | K19: Pendiente | M19: Dos ciclos de prueba y acta tipo
A20: 2 · Piloto Ondupet | B20: Definir qué es un agotado y registrarlo a diario con motivo | C20: Ondupet | D20: Demanda | E20: 2.3 | F20: Planificador/a de demanda y cartera | G20: Tarea | H20: 46447 | I20: 46507 | J20: =IF(AND(H20<>"",I20<>""),I20-H20+1,"") -> 61 | K20: Pendiente | M20: Definición y registro diario
A21: 2 · Piloto Ondupet | B21: KPI de precisión y sesgo con plan de acción por desviación | C21: Ondupet | D21: Demanda | E21: 2.4 | F21: Planificador/a de demanda y cartera | G21: Tarea | H21: 46482 | I21: 46535 | J21: =IF(AND(H21<>"",I21<>""),I21-H21+1,"") -> 54 | K21: Pendiente | M21: KPI mensual y lista de acciones
A22: 2 · Piloto Ondupet | B22: Revisión única de cartera y uso de las dos fechas del pedido | C22: Ondupet | D22: Cartera | E22: 3.1 | F22: Responsable de planificación de planta | G22: Tarea | H22: 46447 | I22: 46507 | J22: =IF(AND(H22<>"",I22<>""),I22-H22+1,"") -> 61 | K22: Pendiente | M22: Fecha confirmada viable en todos los pedidos
A23: 2 · Piloto Ondupet | B23: Validación de cargas contra el pedido: cantidad y fecha | C23: Ondupet | D23: Cartera | E23: 3.2 | F23: Logística / Expediciones | G23: Tarea | H23: 46482 | I23: 46568 | J23: =IF(AND(H23<>"",I23<>""),I23-H23+1,"") -> 87 | K23: Pendiente | M23: Validación activa y KPI de cargas atrasadas | N23: Necesita un desarrollo en SAP (Sistemas).
A24: 2 · Piloto Ondupet | B24: Regla de saldado semanal con aviso a Planificación | C24: Ondupet | D24: Cartera | E24: 3.3 | F24: Planificador/a de demanda y cartera | G24: Tarea | H24: 46482 | I24: 46521 | J24: =IF(AND(H24<>"",I24<>""),I24-H24+1,"") -> 40 | K24: Pendiente | M24: Regla y aviso
A25: 2 · Piloto Ondupet | B25: Reglas de prioridad para pedidos en conflicto | C25: Ondupet | D25: Cartera | E25: 3.4 | F25: Responsable de planificación de planta | G25: Tarea | H25: 46482 | I25: 46535 | J25: =IF(AND(H25<>"",I25<>""),I25-H25+1,"") -> 54 | K25: Pendiente | M25: Reglas acordadas con Comercial y S&OP
A26: 2 · Piloto Ondupet | B26: Revisión semanal única del MRP (incluye materias primas y auxiliares) | C26: Ondupet | D26: Necesidades | E26: 4.1, 4.4 | F26: Planificador/a de materiales | G26: Tarea | H26: 46419 | I26: 46444 | J26: =IF(AND(H26<>"",I26<>""),I26-H26+1,"") -> 26 | K26: Pendiente | M26: Procedimiento estándar del grupo
A27: 2 · Piloto Ondupet | B27: Reglas para corregir propuestas de PT y semielaborado con motivo registrado | C27: Ondupet | D27: Necesidades | E27: 4.2, 4.3 | F27: Responsable de planificación de planta | G27: Tarea | H27: 46482 | I27: 46535 | J27: =IF(AND(H27<>"",I27<>""),I27-H27+1,"") -> 54 | K27: Pendiente | M27: Reglas y registro de motivos
A28: 2 · Piloto Ondupet | B28: Seguimiento del piloto con KPIs y ajustes | C28: Ondupet | F28: Responsable de planificación de planta | G28: Tarea | H28: 46510 | I28: 46568 | J28: =IF(AND(H28<>"",I28<>""),I28-H28+1,"") -> 59 | K28: Pendiente | M28: Informe del piloto
A29: 2 · Piloto Ondupet | B29: Cierre del piloto y lecciones aprendidas | C29: Ondupet | F29: Director/a de Planificación | G29: Hito | H29: 46568 | I29: 46568 | J29: =IF(AND(H29<>"",I29<>""),I29-H29+1,"") -> 1 | K29: Pendiente
A30: 3 · Sistemas y herramientas | B30: Papresa integrada en SAP | C30: Papresa | F30: Sistemas de planificación (Technical Lead y desarrollo) | G30: Hito | H30: 46388 | I30: 46388 | J30: =IF(AND(H30<>"",I30<>""),I30-H30+1,"") -> 1 | K30: Pendiente | N30: Objetivo ya fijado; condiciona el despliegue en Papresa.
A31: 3 · Sistemas y herramientas | B31: SIGPA en MGT y PDA: cierre de pruebas del algoritmo de combinación | C31: MGT | F31: Sistemas de planificación (Technical Lead y desarrollo) | G31: Tarea | H31: 46398 | I31: 46477 | J31: =IF(AND(H31<>"",I31<>""),I31-H31+1,"") -> 80 | K31: Pendiente | M31: Algoritmo en producción | N31: Proyecto en pruebas. Aplica a MGT y PDA.
A32: 3 · Sistemas y herramientas | B32: Informe automático de KPIs de planificación | C32: Grupo (todas) | F32: Sistemas de planificación (Technical Lead y desarrollo) | G32: Tarea | H32: 46447 | I32: 46568 | J32: =IF(AND(H32<>"",I32<>""),I32-H32+1,"") -> 122 | K32: Pendiente | M32: Cuadro de mando mensual por planta
A33: 3 · Sistemas y herramientas | B33: Algoritmo de combinación en Ondupack (Almendralejo y Navalmoral) | C33: Ondupack Almendralejo | F33: Sistemas de planificación (Technical Lead y desarrollo) | G33: Tarea | H33: 46447 | I33: 46660 | J33: =IF(AND(H33<>"",I33<>""),I33-H33+1,"") -> 214 | K33: Pendiente | N33: Proyecto 2027 sin confirmar con negocio.
A34: 3 · Sistemas y herramientas | B34: Migración de GIO a web en Ondupet | C34: Ondupet | F34: Sistemas de planificación (Technical Lead y desarrollo) | G34: Tarea | H34: 46510 | I34: 46689 | J34: =IF(AND(H34<>"",I34<>""),I34-H34+1,"") -> 180 | K34: Pendiente | N34: Proyecto 2027 sin confirmar con negocio.
A35: 3 · Sistemas y herramientas | B35: PRAE Ondupet: asignación de personas a turnos y máquinas | C35: Ondupet | F35: Sistemas de planificación (Technical Lead y desarrollo) | G35: Tarea | H35: 46636 | I35: 46843 | J35: =IF(AND(H35<>"",I35<>""),I35-H35+1,"") -> 208 | K35: Pendiente | N35: Proyecto 2027 sin confirmar con negocio.
A36: 3 · Sistemas y herramientas | B36: Migración de GIO a web en Ondupack | C36: Ondupack Almendralejo | F36: Sistemas de planificación (Technical Lead y desarrollo) | G36: Tarea | H36: 46664 | I36: 46843 | J36: =IF(AND(H36<>"",I36<>""),I36-H36+1,"") -> 180 | K36: Pendiente | N36: Proyecto 2027 sin confirmar con negocio. Aplica a las dos plantas.
A37: 4 · Despliegue en plantas | B37: Despliegue en Ondupack Almendralejo | C37: Ondupack Almendralejo | F37: Responsable de procesos (Functional Lead) | G37: Tarea | H37: 46545 | I37: 46689 | J37: =IF(AND(H37<>"",I37<>""),I37-H37+1,"") -> 145 | K37: Pendiente | M37: To-be adaptado, RACI con nombres, formación y arranque | N37: Agosto, a medio ritmo.
A38: 4 · Despliegue en plantas | B38: Ondupack Almendralejo trabajando con el modelo | C38: Ondupack Almendralejo | F38: Director/a de Planificación | G38: Hito | H38: 46689 | I38: 46689 | J38: =IF(AND(H38<>"",I38<>""),I38-H38+1,"") -> 1 | K38: Pendiente
A39: 4 · Despliegue en plantas | B39: Despliegue en Ondupack Navalmoral | C39: Ondupack Navalmoral | F39: Responsable de procesos (Functional Lead) | G39: Tarea | H39: 46636 | I39: 46738 | J39: =IF(AND(H39<>"",I39<>""),I39-H39+1,"") -> 103 | K39: Pendiente | M39: To-be adaptado, RACI con nombres, formación y arranque
A40: 4 · Despliegue en plantas | B40: Ondupack Navalmoral trabajando con el modelo | C40: Ondupack Navalmoral | F40: Director/a de Planificación | G40: Hito | H40: 46738 | I40: 46738 | J40: =IF(AND(H40<>"",I40<>""),I40-H40+1,"") -> 1 | K40: Pendiente
A41: 4 · Despliegue en plantas | B41: Despliegue en MGT y PDA (papeleras) | C41: MGT | F41: Responsable de procesos (Functional Lead) | G41: Tarea | H41: 46664 | I41: 46808 | J41: =IF(AND(H41<>"",I41<>""),I41-H41+1,"") -> 145 | K41: Pendiente | M41: To-be adaptado, RACI con nombres, formación y arranque | N41: Junto con el flujo intercompany. Aplica a MGT y PDA.
A42: 4 · Despliegue en plantas | B42: MGT y PDA trabajando con el modelo | C42: MGT | F42: Director/a de Planificación | G42: Hito | H42: 46808 | I42: 46808 | J42: =IF(AND(H42<>"",I42<>""),I42-H42+1,"") -> 1 | K42: Pendiente
A43: 4 · Despliegue en plantas | B43: Despliegue en Papresa | C43: Papresa | F43: Responsable de procesos (Functional Lead) | G43: Tarea | H43: 46762 | I43: 46899 | J43: =IF(AND(H43<>"",I43<>""),I43-H43+1,"") -> 138 | K43: Pendiente | M43: To-be adaptado, RACI con nombres, formación y arranque | N43: Después de su integración en SAP y en el intercompany.
A44: 4 · Despliegue en plantas | B44: Papresa trabajando con el modelo | C44: Papresa | F44: Director/a de Planificación | G44: Hito | H44: 46899 | I44: 46899 | J44: =IF(AND(H44<>"",I44<>""),I44-H44+1,"") -> 1 | K44: Pendiente
A45: 5 · Consolidación | B45: Auditoría trimestral de cumplimiento del modelo por planta | C45: Grupo (todas) | F45: Responsable de procesos (Functional Lead) | G45: Tarea | H45: 46569 | I45: 46934 | J45: =IF(AND(H45<>"",I45<>""),I45-H45+1,"") -> 366 | K45: Pendiente | M45: Informe trimestral: RACI, KPIs y calendario
A46: 5 · Consolidación | B46: Revisión anual del modelo: RACI, políticas y KPIs | C46: Grupo (todas) | F46: Director/a de Planificación | G46: Tarea | H46: 46722 | I46: 46780 | J46: =IF(AND(H46<>"",I46<>""),I46-H46+1,"") -> 59 | K46: Pendiente | M46: Modelo v2
A47: 5 · Consolidación | B47: Modelo desplegado en todo el grupo | C47: Grupo (todas) | F47: Director/a de Planificación | G47: Hito | H47: 46934 | I47: 46934 | J47: =IF(AND(H47<>"",I47<>""),I47-H47+1,"") -> 1 | K47: Pendiente

Sheet Gantt
A1: Gantt del plan de acción
A2: Se calcula desde la hoja Plan: si cambias allí una fecha, aquí se mueve la barra. ◆ = hito.
G3: T1 2027 | J3: T2 2027 | M3: T3 2027 | P3: T4 2027 | S3: T1 2028 | V3: T2 2028
A4: Fase | B4: Acción | C4: Empresa | D4: Responsable | E4: Inicio | F4: Fin | G4: 46388 | H4: 46419 | I4: 46447 | J4: 46478 | K4: 46508 | L4: 46539 | M4: 46569 | N4: 46600 | O4: 46631 | P4: 46661 | Q4: 46692 | R4: 46722 | S4: 46753 | T4: 46784 | U4: 46813 | V4: 46844 | W4: 46874 | X4: 46905
A5: =IF(Plan!A2="","",Plan!A2) -> 1 · Gobierno y estándares | B5: =IF(Plan!B2="","",Plan!B2) -> Arranque y aprobación del modelo: roles, RACI to-be y calendario | C5: =IF(Plan!C2="","",Plan!C2) -> Grupo (todas) | D5: =IF(Plan!F2="","",Plan!F2) -> Director/a de Planificación | E5: =IF(Plan!H2="","",Plan!H2) -> 46398 | F5: =IF(Plan!I2="","",Plan!I2) -> 46416 | G5: =IF(OR($E5="",$F5=""),"",IF(AND($E5<=EOMONTH(G$4,0),$F5>=G$4),IF(Plan!$G2="Hito","◆",1),"")) -> 1 | H5: =IF(OR($E5="",$F5=""),"",IF(AND($E5<=EOMONTH(H$4,0),$F5>=H$4),IF(Plan!$G2="Hito","◆",1),"")) | I5: =IF(OR($E5="",$F5=""),"",IF(AND($E5<=EOMONTH(I$4,0),$F5>=I$4),IF(Plan!$G2="Hito","◆",1),"")) | J5: =IF(OR($E5="",$F5=""),"",IF(AND($E5<=EOMONTH(J$4,0),$F5>=J$4),IF(Plan!$G2="Hito","◆",1),"")) | K5: =IF(OR($E5="",$F5=""),"",IF(AND($E5<=EOMONTH(K$4,0),$F5>=K$4),IF(Plan!$G2="Hito","◆",1),"")) | L5: =IF(OR($E5="",$F5=""),"",IF(AND($E5<=EOMONTH(L$4,0),$F5>=L$4),IF(Plan!$G2="Hito","◆",1),"")) | M5: =IF(OR($E5="",$F5=""),"",IF(AND($E5<=EOMONTH(M$4,0),$F5>=M$4),IF(Plan!$G2="Hito","◆",1),"")) | N5: =IF(OR($E5="",$F5=""),"",IF(AND($E5<=EOMONTH(N$4,0),$F5>=N$4),IF(Plan!$G2="Hito","◆",1),"")) | ... X5: =IF(OR($E5="",$F5=""),"",IF(AND($E5<=EOMONTH(X$4,0),$F5>=X$4),IF(Plan!$G2="Hito","◆",1),""))
A6: =IF(Plan!A3="","",Plan!A3) -> 1 · Gobierno y estándares | B6: =IF(Plan!B3="","",Plan!B3) -> Modelo aprobado por dirección | C6: =IF(Plan!C3="","",Plan!C3) -> Grupo (todas) | D6: =IF(Plan!F3="","",Plan!F3) -> Director/a de Planificación | E6: =IF(Plan!H3="","",Plan!H3) -> 46416 | F6: =IF(Plan!I3="","",Plan!I3) -> 46416 | G6: =IF(OR($E6="",$F6=""),"",IF(AND($E6<=EOMONTH(G$4,0),$F6>=G$4),IF(Plan!$G3="Hito","◆",1),"")) -> ◆ | H6: =IF(OR($E6="",$F6=""),"",IF(AND($E6<=EOMONTH(H$4,0),$F6>=H$4),IF(Plan!$G3="Hito","◆",1),"")) | I6: =IF(OR($E6="",$F6=""),"",IF(AND($E6<=EOMONTH(I$4,0),$F6>=I$4),IF(Plan!$G3="Hito","◆",1),"")) | J6: =IF(OR($E6="",$F6=""),"",IF(AND($E6<=EOMONTH(J$4,0),$F6>=J$4),IF(Plan!$G3="Hito","◆",1),"")) | K6: =IF(OR($E6="",$F6=""),"",IF(AND($E6<=EOMONTH(K$4,0),$F6>=K$4),IF(Plan!$G3="Hito","◆",1),"")) | L6: =IF(OR($E6="",$F6=""),"",IF(AND($E6<=EOMONTH(L$4,0),$F6>=L$4),IF(Plan!$G3="Hito","◆",1),"")) | M6: =IF(OR($E6="",$F6=""),"",IF(AND($E6<=EOMONTH(M$4,0),$F6>=M$4),IF(Plan!$G3="Hito","◆",1),"")) | N6: =IF(OR($E6="",$F6=""),"",IF(AND($E6<=EOMONTH(N$4,0),$F6>=N$4),IF(Plan!$G3="Hito","◆",1),"")) | ... X6: =IF(OR($E6="",$F6=""),"",IF(AND($E6<=EOMONTH(X$4,0),$F6>=X$4),IF(Plan!$G3="Hito","◆",1),""))
A7: =IF(Plan!A4="","",Plan!A4) -> 1 · Gobierno y estándares | B7: =IF(Plan!B4="","",Plan!B4) -> Revisar el catálogo de actividades (fusionar 4.4 en 4.1) | C7: =IF(Plan!C4="","",Plan!C4) -> Grupo (todas) | D7: =IF(Plan!F4="","",Plan!F4) -> Responsable de procesos (Functional Lead) | E7: =IF(Plan!H4="","",Plan!H4) -> 46398 | F7: =IF(Plan!I4="","",Plan!I4) -> 46409 | G7: =IF(OR($E7="",$F7=""),"",IF(AND($E7<=EOMONTH(G$4,0),$F7>=G$4),IF(Plan!$G4="Hito","◆",1),"")) -> 1 | H7: =IF(OR($E7="",$F7=""),"",IF(AND($E7<=EOMONTH(H$4,0),$F7>=H$4),IF(Plan!$G4="Hito","◆",1),"")) | I7: =IF(OR($E7="",$F7=""),"",IF(AND($E7<=EOMONTH(I$4,0),$F7>=I$4),IF(Plan!$G4="Hito","◆",1),"")) | J7: =IF(OR($E7="",$F7=""),"",IF(AND($E7<=EOMONTH(J$4,0),$F7>=J$4),IF(Plan!$G4="Hito","◆",1),"")) | K7: =IF(OR($E7="",$F7=""),"",IF(AND($E7<=EOMONTH(K$4,0),$F7>=K$4),IF(Plan!$G4="Hito","◆",1),"")) | L7: =IF(OR($E7="",$F7=""),"",IF(AND($E7<=EOMONTH(L$4,0),$F7>=L$4),IF(Plan!$G4="Hito","◆",1),"")) | M7: =IF(OR($E7="",$F7=""),"",IF(AND($E7<=EOMONTH(M$4,0),$F7>=M$4),IF(Plan!$G4="Hito","◆",1),"")) | N7: =IF(OR($E7="",$F7=""),"",IF(AND($E7<=EOMONTH(N$4,0),$F7>=N$4),IF(Plan!$G4="Hito","◆",1),"")) | ... X7: =IF(OR($E7="",$F7=""),"",IF(AND($E7<=EOMONTH(X$4,0),$F7>=X$4),IF(Plan!$G4="Hito","◆",1),""))
A8: =IF(Plan!A5="","",Plan!A5) -> 1 · Gobierno y estándares | B8: =IF(Plan!B5="","",Plan!B5) -> Nombrar titulares y suplentes por rol en cada planta | C8: =IF(Plan!C5="","",Plan!C5) -> Grupo (todas) | D8: =IF(Plan!F5="","",Plan!F5) -> Director/a de Planificación | E8: =IF(Plan!H5="","",Plan!H5) -> 46405 | F8: =IF(Plan!I5="","",Plan!I5) -> 46430 | G8: =IF(OR($E8="",$F8=""),"",IF(AND($E8<=EOMONTH(G$4,0),$F8>=G$4),IF(Plan!$G5="Hito","◆",1),"")) -> 1 | H8: =IF(OR($E8="",$F8=""),"",IF(AND($E8<=EOMONTH(H$4,0),$F8>=H$4),IF(Plan!$G5="Hito","◆",1),"")) -> 1 | I8: =IF(OR($E8="",$F8=""),"",IF(AND($E8<=EOMONTH(I$4,0),$F8>=I$4),IF(Plan!$G5="Hito","◆",1),"")) | J8: =IF(OR($E8="",$F8=""),"",IF(AND($E8<=EOMONTH(J$4,0),$F8>=J$4),IF(Plan!$G5="Hito","◆",1),"")) | K8: =IF(OR($E8="",$F8=""),"",IF(AND($E8<=EOMONTH(K$4,0),$F8>=K$4),IF(Plan!$G5="Hito","◆",1),"")) | L8: =IF(OR($E8="",$F8=""),"",IF(AND($E8<=EOMONTH(L$4,0),$F8>=L$4),IF(Plan!$G5="Hito","◆",1),"")) | M8: =IF(OR($E8="",$F8=""),"",IF(AND($E8<=EOMONTH(M$4,0),$F8>=M$4),IF(Plan!$G5="Hito","◆",1),"")) | N8: =IF(OR($E8="",$F8=""),"",IF(AND($E8<=EOMONTH(N$4,0),$F8>=N$4),IF(Plan!$G5="Hito","◆",1),"")) | ... X8: =IF(OR($E8="",$F8=""),"",IF(AND($E8<=EOMONTH(X$4,0),$F8>=X$4),IF(Plan!$G5="Hito","◆",1),""))
A9: =IF(Plan!A6="","",Plan!A6) -> 1 · Gobierno y estándares | B9: =IF(Plan!B6="","",Plan!B6) -> Completar el as-is del resto de plantas (Ondupack, MGT, PDA y Papresa) | C9: =IF(Plan!C6="","",Plan!C6) -> Grupo (todas) | D9: =IF(Plan!F6="","",Plan!F6) -> Responsable de procesos (Functional Lead) | E9: =IF(Plan!H6="","",Plan!H6) -> 46398 | F9: =IF(Plan!I6="","",Plan!I6) -> 46444 | G9: =IF(OR($E9="",$F9=""),"",IF(AND($E9<=EOMONTH(G$4,0),$F9>=G$4),IF(Plan!$G6="Hito","◆",1),"")) -> 1 | H9: =IF(OR($E9="",$F9=""),"",IF(AND($E9<=EOMONTH(H$4,0),$F9>=H$4),IF(Plan!$G6="Hito","◆",1),"")) -> 1 | I9: =IF(OR($E9="",$F9=""),"",IF(AND($E9<=EOMONTH(I$4,0),$F9>=I$4),IF(Plan!$G6="Hito","◆",1),"")) | J9: =IF(OR($E9="",$F9=""),"",IF(AND($E9<=EOMONTH(J$4,0),$F9>=J$4),IF(Plan!$G6="Hito","◆",1),"")) | K9: =IF(OR($E9="",$F9=""),"",IF(AND($E9<=EOMONTH(K$4,0),$F9>=K$4),IF(Plan!$G6="Hito","◆",1),"")) | L9: =IF(OR($E9="",$F9=""),"",IF(AND($E9<=EOMONTH(L$4,0),$F9>=L$4),IF(Plan!$G6="Hito","◆",1),"")) | M9: =IF(OR($E9="",$F9=""),"",IF(AND($E9<=EOMONTH(M$4,0),$F9>=M$4),IF(Plan!$G6="Hito","◆",1),"")) | N9: =IF(OR($E9="",$F9=""),"",IF(AND($E9<=EOMONTH(N$4,0),$F9>=N$4),IF(Plan!$G6="Hito","◆",1),"")) | ... X9: =IF(OR($E9="",$F9=""),"",IF(AND($E9<=EOMONTH(X$4,0),$F9>=X$4),IF(Plan!$G6="Hito","◆",1),""))
A10: =IF(Plan!A7="","",Plan!A7) -> 1 · Gobierno y estándares | B10: =IF(Plan!B7="","",Plan!B7) -> Calendario de planificación del grupo: S&OP mensual y reuniones de planta | C10: =IF(Plan!C7="","",Plan!C7) -> Grupo (todas) | D10: =IF(Plan!F7="","",Plan!F7) -> Coordinador/a de S&OP e intercompany | E10: =IF(Plan!H7="","",Plan!H7) -> 46419 | F10: =IF(Plan!I7="","",Plan!I7) -> 46444 | G10: =IF(OR($E10="",$F10=""),"",IF(AND($E10<=EOMONTH(G$4,0),$F10>=G$4),IF(Plan!$G7="Hito","◆",1),"")) | H10: =IF(OR($E10="",$F10=""),"",IF(AND($E10<=EOMONTH(H$4,0),$F10>=H$4),IF(Plan!$G7="Hito","◆",1),"")) -> 1 | I10: =IF(OR($E10="",$F10=""),"",IF(AND($E10<=EOMONTH(I$4,0),$F10>=I$4),IF(Plan!$G7="Hito","◆",1),"")) | J10: =IF(OR($E10="",$F10=""),"",IF(AND($E10<=EOMONTH(J$4,0),$F10>=J$4),IF(Plan!$G7="Hito","◆",1),"")) | K10: =IF(OR($E10="",$F10=""),"",IF(AND($E10<=EOMONTH(K$4,0),$F10>=K$4),IF(Plan!$G7="Hito","◆",1),"")) | L10: =IF(OR($E10="",$F10=""),"",IF(AND($E10<=EOMONTH(L$4,0),$F10>=L$4),IF(Plan!$G7="Hito","◆",1),"")) | M10: =IF(OR($E10="",$F10=""),"",IF(AND($E10<=EOMONTH(M$4,0),$F10>=M$4),IF(Plan!$G7="Hito","◆",1),"")) | N10: =IF(OR($E10="",$F10=""),"",IF(AND($E10<=EOMONTH(N$4,0),$F10>=N$4),IF(Plan!$G7="Hito","◆",1),"")) | ... X10: =IF(OR($E10="",$F10=""),"",IF(AND($E10<=EOMONTH(X$4,0),$F10>=X$4),IF(Plan!$G7="Hito","◆",1),""))
A11: =IF(Plan!A8="","",Plan!A8) -> 1 · Gobierno y estándares | B11: =IF(Plan!B8="","",Plan!B8) -> Políticas de planificación y KPIs comunes (definición y fórmula) | C11: =IF(Plan!C8="","",Plan!C8) -> Grupo (todas) | D11: =IF(Plan!F8="","",Plan!F8) -> Responsable de procesos (Functional Lead) | E11: =IF(Plan!H8="","",Plan!H8) -> 46447 | F11: =IF(Plan!I8="","",Plan!I8) -> 46507 | G11: =IF(OR($E11="",$F11=""),"",IF(AND($E11<=EOMONTH(G$4,0),$F11>=G$4),IF(Plan!$G8="Hito","◆",1),"")) | H11: =IF(OR($E11="",$F11=""),"",IF(AND($E11<=EOMONTH(H$4,0),$F11>=H$4),IF(Plan!$G8="Hito","◆",1),"")) | I11: =IF(OR($E11="",$F11=""),"",IF(AND($E11<=EOMONTH(I$4,0),$F11>=I$4),IF(Plan!$G8="Hito","◆",1),"")) -> 1 | J11: =IF(OR($E11="",$F11=""),"",IF(AND($E11<=EOMONTH(J$4,0),$F11>=J$4),IF(Plan!$G8="Hito","◆",1),"")) -> 1 | K11: =IF(OR($E11="",$F11=""),"",IF(AND($E11<=EOMONTH(K$4,0),$F11>=K$4),IF(Plan!$G8="Hito","◆",1),"")) | L11: =IF(OR($E11="",$F11=""),"",IF(AND($E11<=EOMONTH(L$4,0),$F11>=L$4),IF(Plan!$G8="Hito","◆",1),"")) | M11: =IF(OR($E11="",$F11=""),"",IF(AND($E11<=EOMONTH(M$4,0),$F11>=M$4),IF(Plan!$G8="Hito","◆",1),"")) | N11: =IF(OR($E11="",$F11=""),"",IF(AND($E11<=EOMONTH(N$4,0),$F11>=N$4),IF(Plan!$G8="Hito","◆",1),"")) | ... X11: =IF(OR($E11="",$F11=""),"",IF(AND($E11<=EOMONTH(X$4,0),$F11>=X$4),IF(Plan!$G8="Hito","◆",1),""))
A12: =IF(Plan!A9="","",Plan!A9) -> 1 · Gobierno y estándares | B12: =IF(Plan!B9="","",Plan!B9) -> Manual de planificación v1: procedimiento estándar por proceso | C12: =IF(Plan!C9="","",Plan!C9) -> Grupo (todas) | D12: =IF(Plan!F9="","",Plan!F9) -> Responsable de procesos (Functional Lead) | E12: =IF(Plan!H9="","",Plan!H9) -> 46426 | F12: =IF(Plan!I9="","",Plan!I9) -> 46507 | G12: =IF(OR($E12="",$F12=""),"",IF(AND($E12<=EOMONTH(G$4,0),$F12>=G$4),IF(Plan!$G9="Hito","◆",1),"")) | H12: =IF(OR($E12="",$F12=""),"",IF(AND($E12<=EOMONTH(H$4,0),$F12>=H$4),IF(Plan!$G9="Hito","◆",1),"")) -> 1 | I12: =IF(OR($E12="",$F12=""),"",IF(AND($E12<=EOMONTH(I$4,0),$F12>=I$4),IF(Plan!$G9="Hito","◆",1),"")) -> 1 | J12: =IF(OR($E12="",$F12=""),"",IF(AND($E12<=EOMONTH(J$4,0),$F12>=J$4),IF(Plan!$G9="Hito","◆",1),"")) -> 1 | K12: =IF(OR($E12="",$F12=""),"",IF(AND($E12<=EOMONTH(K$4,0),$F12>=K$4),IF(Plan!$G9="Hito","◆",1),"")) | L12: =IF(OR($E12="",$F12=""),"",IF(AND($E12<=EOMONTH(L$4,0),$F12>=L$4),IF(Plan!$G9="Hito","◆",1),"")) | M12: =IF(OR($E12="",$F12=""),"",IF(AND($E12<=EOMONTH(M$4,0),$F12>=M$4),IF(Plan!$G9="Hito","◆",1),"")) | N12: =IF(OR($E12="",$F12=""),"",IF(AND($E12<=EOMONTH(N$4,0),$F12>=N$4),IF(Plan!$G9="Hito","◆",1),"")) | ... X12: =IF(OR($E12="",$F12=""),"",IF(AND($E12<=EOMONTH(X$4,0),$F12>=X$4),IF(Plan!$G9="Hito","◆",1),""))
A13: =IF(Plan!A10="","",Plan!A10) -> 1 · Gobierno y estándares | B13: =IF(Plan!B10="","",Plan!B10) -> Manual de planificación v1 publicado | C13: =IF(Plan!C10="","",Plan!C10) -> Grupo (todas) | D13: =IF(Plan!F10="","",Plan!F10) -> Responsable de procesos (Functional Lead) | E13: =IF(Plan!H10="","",Plan!H10) -> 46507 | F13: =IF(Plan!I10="","",Plan!I10) -> 46507 | G13: =IF(OR($E13="",$F13=""),"",IF(AND($E13<=EOMONTH(G$4,0),$F13>=G$4),IF(Plan!$G10="Hito","◆",1),"")) | H13: =IF(OR($E13="",$F13=""),"",IF(AND($E13<=EOMONTH(H$4,0),$F13>=H$4),IF(Plan!$G10="Hito","◆",1),"")) | I13: =IF(OR($E13="",$F13=""),"",IF(AND($E13<=EOMONTH(I$4,0),$F13>=I$4),IF(Plan!$G10="Hito","◆",1),"")) | J13: =IF(OR($E13="",$F13=""),"",IF(AND($E13<=EOMONTH(J$4,0),$F13>=J$4),IF(Plan!$G10="Hito","◆",1),"")) -> ◆ | K13: =IF(OR($E13="",$F13=""),"",IF(AND($E13<=EOMONTH(K$4,0),$F13>=K$4),IF(Plan!$G10="Hito","◆",1),"")) | L13: =IF(OR($E13="",$F13=""),"",IF(AND($E13<=EOMONTH(L$4,0),$F13>=L$4),IF(Plan!$G10="Hito","◆",1),"")) | M13: =IF(OR($E13="",$F13=""),"",IF(AND($E13<=EOMONTH(M$4,0),$F13>=M$4),IF(Plan!$G10="Hito","◆",1),"")) | N13: =IF(OR($E13="",$F13=""),"",IF(AND($E13<=EOMONTH(N$4,0),$F13>=N$4),IF(Plan!$G10="Hito","◆",1),"")) | ... X13: =IF(OR($E13="",$F13=""),"",IF(AND($E13<=EOMONTH(X$4,0),$F13>=X$4),IF(Plan!$G10="Hito","◆",1),""))
A14: =IF(Plan!A11="","",Plan!A11) -> 2 · Piloto Ondupet | B14: =IF(Plan!B11="","",Plan!B11) -> Cerrar el E2E de Ondupet: capacidad, programación, entrega y control (5–8) | C14: =IF(Plan!C11="","",Plan!C11) -> Ondupet | D14: =IF(Plan!F11="","",Plan!F11) -> Responsable de procesos (Functional Lead) | E14: =IF(Plan!H11="","",Plan!H11) -> 46398 | F14: =IF(Plan!I11="","",Plan!I11) -> 46423 | G14: =IF(OR($E14="",$F14=""),"",IF(AND($E14<=EOMONTH(G$4,0),$F14>=G$4),IF(Plan!$G11="Hito","◆",1),"")) -> 1 | H14: =IF(OR($E14="",$F14=""),"",IF(AND($E14<=EOMONTH(H$4,0),$F14>=H$4),IF(Plan!$G11="Hito","◆",1),"")) -> 1 | I14: =IF(OR($E14="",$F14=""),"",IF(AND($E14<=EOMONTH(I$4,0),$F14>=I$4),IF(Plan!$G11="Hito","◆",1),"")) | J14: =IF(OR($E14="",$F14=""),"",IF(AND($E14<=EOMONTH(J$4,0),$F14>=J$4),IF(Plan!$G11="Hito","◆",1),"")) | K14: =IF(OR($E14="",$F14=""),"",IF(AND($E14<=EOMONTH(K$4,0),$F14>=K$4),IF(Plan!$G11="Hito","◆",1),"")) | L14: =IF(OR($E14="",$F14=""),"",IF(AND($E14<=EOMONTH(L$4,0),$F14>=L$4),IF(Plan!$G11="Hito","◆",1),"")) | M14: =IF(OR($E14="",$F14=""),"",IF(AND($E14<=EOMONTH(M$4,0),$F14>=M$4),IF(Plan!$G11="Hito","◆",1),"")) | N14: =IF(OR($E14="",$F14=""),"",IF(AND($E14<=EOMONTH(N$4,0),$F14>=N$4),IF(Plan!$G11="Hito","◆",1),"")) | ... X14: =IF(OR($E14="",$F14=""),"",IF(AND($E14<=EOMONTH(X$4,0),$F14>=X$4),IF(Plan!$G11="Hito","◆",1),""))
A15: =IF(Plan!A12="","",Plan!A12) -> 2 · Piloto Ondupet | B15: =IF(Plan!B12="","",Plan!B12) -> Plantilla única de alta de material con estrategia y ruta | C15: =IF(Plan!C12="","",Plan!C12) -> Ondupet | D15: =IF(Plan!F12="","",Plan!F12) -> Responsable de dato maestro | E15: =IF(Plan!H12="","",Plan!H12) -> 46419 | F15: =IF(Plan!I12="","",Plan!I12) -> 46477 | G15: =IF(OR($E15="",$F15=""),"",IF(AND($E15<=EOMONTH(G$4,0),$F15>=G$4),IF(Plan!$G12="Hito","◆",1),"")) | H15: =IF(OR($E15="",$F15=""),"",IF(AND($E15<=EOMONTH(H$4,0),$F15>=H$4),IF(Plan!$G12="Hito","◆",1),"")) -> 1 | I15: =IF(OR($E15="",$F15=""),"",IF(AND($E15<=EOMONTH(I$4,0),$F15>=I$4),IF(Plan!$G12="Hito","◆",1),"")) -> 1 | J15: =IF(OR($E15="",$F15=""),"",IF(AND($E15<=EOMONTH(J$4,0),$F15>=J$4),IF(Plan!$G12="Hito","◆",1),"")) | K15: =IF(OR($E15="",$F15=""),"",IF(AND($E15<=EOMONTH(K$4,0),$F15>=K$4),IF(Plan!$G12="Hito","◆",1),"")) | L15: =IF(OR($E15="",$F15=""),"",IF(AND($E15<=EOMONTH(L$4,0),$F15>=L$4),IF(Plan!$G12="Hito","◆",1),"")) | M15: =IF(OR($E15="",$F15=""),"",IF(AND($E15<=EOMONTH(M$4,0),$F15>=M$4),IF(Plan!$G12="Hito","◆",1),"")) | N15: =IF(OR($E15="",$F15=""),"",IF(AND($E15<=EOMONTH(N$4,0),$F15>=N$4),IF(Plan!$G12="Hito","◆",1),"")) | ... X15: =IF(OR($E15="",$F15=""),"",IF(AND($E15<=EOMONTH(X$4,0),$F15>=X$4),IF(Plan!$G12="Hito","◆",1),""))
A16: =IF(Plan!A13="","",Plan!A13) -> 2 · Piloto Ondupet | B16: =IF(Plan!B13="","",Plan!B13) -> Primera revisión de ABC/XYZ y estrategias; después, trimestral | C16: =IF(Plan!C13="","",Plan!C13) -> Ondupet | D16: =IF(Plan!F13="","",Plan!F13) -> Responsable de dato maestro | E16: =IF(Plan!H13="","",Plan!H13) -> 46447 | F16: =IF(Plan!I13="","",Plan!I13) -> 46507 | G16: =IF(OR($E16="",$F16=""),"",IF(AND($E16<=EOMONTH(G$4,0),$F16>=G$4),IF(Plan!$G13="Hito","◆",1),"")) | H16: =IF(OR($E16="",$F16=""),"",IF(AND($E16<=EOMONTH(H$4,0),$F16>=H$4),IF(Plan!$G13="Hito","◆",1),"")) | I16: =IF(OR($E16="",$F16=""),"",IF(AND($E16<=EOMONTH(I$4,0),$F16>=I$4),IF(Plan!$G13="Hito","◆",1),"")) -> 1 | J16: =IF(OR($E16="",$F16=""),"",IF(AND($E16<=EOMONTH(J$4,0),$F16>=J$4),IF(Plan!$G13="Hito","◆",1),"")) -> 1 | K16: =IF(OR($E16="",$F16=""),"",IF(AND($E16<=EOMONTH(K$4,0),$F16>=K$4),IF(Plan!$G13="Hito","◆",1),"")) | L16: =IF(OR($E16="",$F16=""),"",IF(AND($E16<=EOMONTH(L$4,0),$F16>=L$4),IF(Plan!$G13="Hito","◆",1),"")) | M16: =IF(OR($E16="",$F16=""),"",IF(AND($E16<=EOMONTH(M$4,0),$F16>=M$4),IF(Plan!$G13="Hito","◆",1),"")) | N16: =IF(OR($E16="",$F16=""),"",IF(AND($E16<=EOMONTH(N$4,0),$F16>=N$4),IF(Plan!$G13="Hito","◆",1),"")) | ... X16: =IF(OR($E16="",$F16=""),"",IF(AND($E16<=EOMONTH(X$4,0),$F16>=X$4),IF(Plan!$G13="Hito","◆",1),""))
... A50: =IF(Plan!A47="","",Plan!A47) -> 5 · Consolidación | B50: =IF(Plan!B47="","",Plan!B47) -> Modelo desplegado en todo el grupo | C50: =IF(Plan!C47="","",Plan!C47) -> Grupo (todas) | D50: =IF(Plan!F47="","",Plan!F47) -> Director/a de Planificación | E50: =IF(Plan!H47="","",Plan!H47) -> 46934 | F50: =IF(Plan!I47="","",Plan!I47) -> 46934 | G50: =IF(OR($E50="",$F50=""),"",IF(AND($E50<=EOMONTH(G$4,0),$F50>=G$4),IF(Plan!$G47="Hito","◆",1),"")) | H50: =IF(OR($E50="",$F50=""),"",IF(AND($E50<=EOMONTH(H$4,0),$F50>=H$4),IF(Plan!$G47="Hito","◆",1),"")) | I50: =IF(OR($E50="",$F50=""),"",IF(AND($E50<=EOMONTH(I$4,0),$F50>=I$4),IF(Plan!$G47="Hito","◆",1),"")) | J50: =IF(OR($E50="",$F50=""),"",IF(AND($E50<=EOMONTH(J$4,0),$F50>=J$4),IF(Plan!$G47="Hito","◆",1),"")) | K50: =IF(OR($E50="",$F50=""),"",IF(AND($E50<=EOMONTH(K$4,0),$F50>=K$4),IF(Plan!$G47="Hito","◆",1),"")) | L50: =IF(OR($E50="",$F50=""),"",IF(AND($E50<=EOMONTH(L$4,0),$F50>=L$4),IF(Plan!$G47="Hito","◆",1),"")) | M50: =IF(OR($E50="",$F50=""),"",IF(AND($E50<=EOMONTH(M$4,0),$F50>=M$4),IF(Plan!$G47="Hito","◆",1),"")) | N50: =IF(OR($E50="",$F50=""),"",IF(AND($E50<=EOMONTH(N$4,0),$F50>=N$4),IF(Plan!$G47="Hito","◆",1),"")) | ... X50: =IF(OR($E50="",$F50=""),"",IF(AND($E50<=EOMONTH(X$4,0),$F50>=X$4),IF(Plan!$G47="Hito","◆",1),"")) -> ◆
